Workbook
Name SegmentaciónDeDatos_ESPECIALIDAD: #N/A
Name SegmentaciónDeDatos_ESTADO_2: #N/A
Name SegmentaciónDeDatos_ESTADO_FINAL: #N/A
Name SegmentaciónDeDatos_MOTIVO: #N/A
Name SegmentaciónDeDatos_PERIODO: #N/A
Name SegmentaciónDeDatos_PROCESO: #N/A
Name SegmentaciónDeDatos_TIPO_CONTRATO: #N/A

Sheet base pendientes viva 1a
A1: FECHA DE INGRESO DEL REQUERIMIENTO | B1: CANAL | C1: DNI | D1: NOMBRES Y APELLIDOS | E1: RUC CONTRATANTE | F1: DESCRIPCIÓN DE CONTRATANTE | G1: TENOR DEL CORREO | H1: TIPO DE REQUERIMIENTO | I1: TIPO DE RECLAMO | J1: RECLAMO FUNDAMENTADO | K1: RESPONSABLE DE LA RESPUESTA | L1: ESTATUS DE GESTIÓN | M1: FECHA DE RESOLUCION | N1: DIAS TOTALES | O1: DENTRO DEL ANS ESTABLECIDO | P1: OBS | Q1: CON RESPUESTA | R1: RESPONSABLE | S1: FECHA | T1: ANS | U1: CRUCE BASE TOTAL | V1: FECHA DE RESPUESTA | W1: obs
A2: 45712 | B2: CORREO | C2: 7218366 | D2: GLADYS PATRICIA GUTIERREZ VELEZMORO | G2: RIMAC VIP//PROGRAMA CRONICOS REUMATOLOGIA//GLADYS PATRICIA GUTIERREZ VELEZMORO | H2: RECLAMOS | I2: DEMORA COORDINACIÓN DE CITAS | J2: SI | K2: Viva 1 A | L2: SIN RESPUESTA | M2: 45742 | N2: 19 | P2: si | Q2: SI | R2: Maribel | S2: 45749 | T2: Finalizado | U2: =VLOOKUP(C2,'DATA CORREO'!G:W,17,0) -> CERRADA | V2: =VLOOKUP(C2,'DATA CORREO'!G:V,16,0) -> 45749
A3: 45716 | B3: CORREO | C3: 8287353 | D3: LEON MAGNO SANCHEZ QUINTANILLA | G3: programa cuídate / LEON MAGNO SANCHEZ QUINTANILLA | H3: RECLAMOS | I3: DEMORA ENTREGA DE MEDICAMENTOS | J3: SI | K3: Viva 1 A | L3: RESPONDIDO | M3: 45742 | N3: 19 | P3: data rimac x | Q3: SI | R3: Maribel | S3: 45749 | T3: Finalizado | U3: =VLOOKUP(C3,'DATA CORREO'!G:W,17,0) -> CERRADA | V3: =VLOOKUP(C3,'DATA CORREO'!G:V,16,0) -> 45749
A4: 45716 | B4: CORREO | C4: 3684166 | D4: DIEGO VILLANUEVA RUIZ | G4: INSCRIPCION PARA EL PROGRAMA CUIDATE PX DIEGO VILLANUEVA RUIZ | H4: SOLICITUDES | I4: DEMANDA INDUCIDA | J4: SI | K4: Viva 1 A | L4: SIN RESPUESTA | M4: 45742 | N4: 19 | P4: data rimac x | Q4: SI | R4: Chrismerly | S4: 45750 | T4: Finalizado | U4: =VLOOKUP(C4,'DATA CORREO'!G:W,17,0) -> CERRADA | V4: =VLOOKUP(C4,'DATA CORREO'!G:V,16,0) -> 45750
A5: 45716 | B5: CORREO | C5: 8783626 | D5: GIOVANNA MARIA LUZ VALEGA DURAND | G5: RIMAC VIP // CONSULTA PROGRAMA CUIDATE // GIOVANNA MARIA LUZ VALEGA DURAND// CLIENTE CRÍTICA | H5: RECLAMOS | I5: DEMORA COORDINACIÓN DE CITAS | J5: SI | K5: Viva 1 A | L5: SIN RESPUESTA | M5: 45742 | N5: 18 | P5: correo enviado | Q5: SI | R5: Gianina | S5: 45735 | T5: Finalizado | U5: =VLOOKUP(C5,'DATA CORREO'!G:W,17,0) -> CERRADA | V5: =VLOOKUP(C5,'DATA CORREO'!G:V,16,0) -> 45737
A6: 45716 | B6: CORREO | C6: 8249657 | D6: FARA NOEMI MIRANDA PACHECO DE CHOY | G6: PACIENTE DEL PROGRAMA CUIDATE PENDIENTE ENTREGA DE SUS MEDICAMENTOS /FARA NOEMI MIRANDA PACHECO DE CHOY DNI :08249657 | H6: RECLAMOS | I6: DEMORA ENTREGA DE MEDICAMENTOS | J6: SI | K6: Viva 1 A | L6: SIN RESPUESTA | M6: 45742 | N6: 17 | P6: correo enviado | Q6: SI | R6: Maribel | S6: 45747 | T6: Finalizado | U6: =VLOOKUP(C6,'DATA CORREO'!G:W,17,0) -> CERRADA | V6: =VLOOKUP(C6,'DATA CORREO'!G:V,16,0) -> 45747
A7: 45716 | B7: CORREO | C7: 44000062 | D7: LLAMOJA VICENTE DENNISE | G7: CUIDATE- PROGRAMA CRONICO | H7: RECLAMOS | I7: DEMORA TOMA DE TOMA DE MUESTRAS | J7: SI | K7: Viva 1 A | L7: SIN RESPUESTA | M7: 45742 | N7: 19 | P7: sin correo inicial | Q7: SI | R7: Chrismerly | S7: 45754 | T7: Finalizado | U7: =VLOOKUP(C7,'DATA CORREO'!G:W,17,0) -> CERRADA | V7: =VLOOKUP(C7,'DATA CORREO'!G:V,16,0) -> 45754
A8: 45719 | B8: CORREO | C8: 29561921 | D8: ALVAREZ MONGE LELIA | G8: REVISION ASEGURADO : ALVAREZ MONGE LELIA DNI : 29561921 - MINSUR | H8: RECLAMOS | I8: DEMORA COORDINACIÓN DE CITAS | J8: SI | K8: Viva 1 A | L8: RESPONDIDO | M8: 45742 | N8: 16 | P8: data rimac x | Q8: SI | R8: Maribel | S8: 45749 | T8: Finalizado | U8: =VLOOKUP(C8,'DATA CORREO'!G:W,17,0) -> CERRADA | V8: =VLOOKUP(C8,'DATA CORREO'!G:V,16,0) -> 45749
A9: 45720 | B9: CORREO | C9: 8243493 | D9: Talia Gianina Martínez de Arauzo | G9: Ingreso al programa Cuídate | H9: SOLICITUDES | I9: DEMANDA INDUCIDA | K9: Viva 1 A | L9: SIN RESPUESTA | M9: 45742 | N9: 19 | P9: correo enviado | Q9: SI | R9: Maribel | S9: 45748 | T9: Finalizado | U9: =VLOOKUP(C9,'DATA CORREO'!G:W,17,0) -> CERRADA | V9: =VLOOKUP(C9,'DATA CORREO'!G:V,16,0) -> 45748
A10: 45721 | B10: CORREO | C10: 77742062 | D10: EDGAR IGNACIO DE LA TORRE RODRIGUEZ | G10: PACIENTE DEL PROGRAMA CUIDATE /EDGAR IGNACIO DE LA TORRE RODRIGUEZ DNI :77742062 | H10: RECLAMOS | I10: DEMORA COORDINACIÓN DE CITAS | J10: SI | K10: Viva 1 A | L10: SIN RESPUESTA | M10: 45742 | N10: 16 | P10: correo enviado | Q10: SI | R10: Maribel | S10: 45748 | T10: Finalizado | U10: =VLOOKUP(C10,'DATA CORREO'!G:W,17,0) -> CERRADA | V10: =VLOOKUP(C10,'DATA CORREO'!G:V,16,0) -> 45748
A11: 45721 | B11: CORREO | D11: POTENCIALES AL PROGRAMA CUIDATE Y OTROS CRONICOS-SURA /RIESGO | G11: POTENCIALES AL PROGRAMA CUIDATE Y OTROS CRONICOS-SURA /RIESGO | H11: SOLICITUDES | I11: DEMANDA INDUCIDA | K11: Viva 1 A | L11: SIN RESPUESTA | M11: 45742 | N11: 23 | P11: data rimac x | Q11: SI | R11: Chrismerly | S11: 45754 | T11: Seguimiento | U11: SEGUIMIENTO | V11: 45754 | W11: Discriminado por usuarios, resuelto parcialmente
A12: 45721 | B12: CORREO | C12: 8268085 | D12: GARCIA CASTILLO NORA EMMA | G12: TALMA - EPS - ATENCION MEDICA - ASEG: GARCIA CASTILLO NORA EMMA | H12: RECLAMOS | I12: DEMORA ENTREGA DE MEDICAMENTOS | J12: SI | K12: Viva 1 A | L12: SIN RESPUESTA | M12: 45742 | N12: 16 | P12: correo enviado | Q12: SI | R12: Antonio | S12: 45726 | T12: Finalizado | U12: =VLOOKUP(C12,'DATA CORREO'!G:W,17,0) -> CERRADA | V12: =VLOOKUP(C12,'DATA CORREO'!G:V,16,0) -> 45726
A13: 45721 | B13: CORREO | C13: 7307988 | D13: CECILIA ESTHER CANALES ANICAMA | G13: PROGRAMA CRONICOS - Paciente - CECILIA ESTHER CANALES ANICAMA | H13: RECLAMOS | I13: DEMORA COORDINACIÓN DE CITAS | K13: Viva 1 A | L13: SIN RESPUESTA | M13: 45742 | N13: 16 | P13: correo enviado | Q13: SI | R13: Maribel | S13: 45748 | T13: Finalizado | U13: =VLOOKUP(C13,'DATA CORREO'!G:W,17,0) -> CERRADA | V13: =VLOOKUP(C13,'DATA CORREO'!G:V,16,0) -> 45748
A14: 45721 | B14: CORREO | C14: 72182950 | D14: XIMENA SOFIA DELGADILLO CABRERA | G14: XIMENA SOFIA DELGADILLO CABRERA-72182950 | H14: SOLICITUDES | I14: DEMANDA INDUCIDA | K14: Viva 1 A | L14: SIN RESPUESTA | M14: 45742 | N14: 16 | P14: correo enviado | Q14: SI | R14: Kathy | S14: 45746 | T14: Finalizado | U14: =VLOOKUP(C14,'DATA CORREO'!G:W,17,0) -> CERRADA | V14: =VLOOKUP(C14,'DATA CORREO'!G:V,16,0) -> 45746
A15: 45722 | B15: CORREO | C15: 9876517 | D15: Victor Edgar Solis Plaza | G15: REFINERIA LA PAMPILLA / EPS N° E0001009 / ASEGURADO: Victor Edgar Solis Plaza / RECLAMO URGENTE | I15: NO ACEPTA COPAGOS | K15: Viva 1 A | L15: SIN RESPUESTA | M15: 45742 | N15: 15 | P15: respondido 30/3 | Q15: SI | R15: Chrismerly | S15: 45750 | T15: Finalizado | U15: =VLOOKUP(C15,'DATA CORREO'!G:W,17,0) -> CERRADA | V15: =VLOOKUP(C15,'DATA CORREO'!G:V,16,0) -> 45750 | W15: No se evidencia correo de respuesta al asegurador, ultimo correo de seguimiento del dr fredy el 3/4/2025 Freddy Garzón<fgarzon@viva1a.com.pe> ​ Gianina Jessica Sigueña Aldana ​ ​ Antonio Torres Olivas; ​ Maximo Alfaro Andrade; ​ Chrismerly Abigail Huaranca López ​ saludos este correo avala la entrega del concentrador de oxigeno al paciente solis Gianina sobre el correo Principal demos respuesta a la EPS para que ejecuten el pago gracias
A16: 45723 | B16: CORREO | C16: 3506981 | D16: Juan Manuel Rivas Castillo | G16: DERIVACION MDC A CUIDATE | H16: SOLICITUDES | I16: DEMANDA INDUCIDA | K16: Viva 1 A | L16: SIN RESPUESTA | M16: 45742 | N16: 8 | P16: correo enviado | Q16: SI | R16: Maribel | S16: 45748 | T16: Finalizado | U16: =VLOOKUP(C16,'DATA CORREO'!G:W,17,0) -> CERRADA | V16: =VLOOKUP(C16,'DATA CORREO'!G:V,16,0) -> 45733
A17: 45723 | B17: CORREO | C17: 2009433 | D17: ESMEIDA ODILA SUBERO DE HERNANDEZ | G17: RIMAC VIP // CONSULTA ENVIO DE MEDICAMENTOS // PROGRAMA CRONICO // ESMEIDA ODILA SUBERO DE HERNANDEZ | H17: RECLAMOS | I17: DEMORA ENTREGA DE MEDICAMENTOS | J17: SI | K17: Viva 1 A | L17: SIN RESPUESTA | M17: 45734 | N17: 8 | P17: respondido | Q17: SI | R17: Chrismerly | S17: 45750 | T17: Finalizado | U17: =VLOOKUP(C17,'DATA CORREO'!G:W,17,0) -> CERRADA | V17: =VLOOKUP(C17,'DATA CORREO'!G:V,16,0) -> 45750 | W17: Hay un caso de este paciente resuelto en el correo con el asunto: URGENTE PACIENTE Programa Cuídate SUBERO DE HERNANDEZ ESMEIDA ODILA Gianina Jessica Sigueña Aldana ​ CUI_Guissela Bedon Espinoza <xt10033@rimac.com.pe>; ​y 3 más ​ ​ ​ ​y 5 más ​ ​ ​ ​ ​ Estimada Guissela, buen día: En referencia a lo solicitado, se valida que efectivamente nuestra mutua paciente ha tenido consulta efectiva con el Dr. Moncada el día 17/2/24. Se valida con farmacia la dispensación conforme de los medicamentos indicados en RM. Cabe resaltar que la Sra. Subero indica en base de migración programa RCV; sin embargo, no cuenta con dx acorde al programa indicado. Para tranquilidad de cara a la experiencia del usuario, nuestro médico de piso realizará una llamada para validar los medicamentos que indican se encuentran faltantes. Se reportará luego de que la paciente responda. Saludos Cordiales,
A18: 45726 | B18: CORREO | C18: 29222292 | D18: PACHECO TEJADA JORGE ADALBERTO | G18: UCSP// PROGRAMA CUIDATE// INCONVENIENTES DE ENTREGA DE MEDICAMENTOS// PACHECO TEJADA JORGE ADALBERTO | H18: RECLAMOS | I18: DEMORA COORDINACIÓN DE CITAS | J18: SI | K18: Viva 1 A | L18: SIN RESPUESTA | M18: 45742 | N18: 7 | P18: correo enviado | Q18: SI | R18: Maribel | S18: 45750 | T18: Finalizado | U18: =VLOOKUP(C18,'DATA CORREO'!G:W,17,0) -> CERRADA | V18: =VLOOKUP(C18,'DATA CORREO'!G:V,16,0) -> 45750
A19: 45726 | B19: CORREO | C19: 8170776 | D19: NILTON HERMAN JIMENEZ ROSALES | G19: CONTINUDAD DE TERAPIAS FISICAS USUARIO NILTON HERMAN JIMENEZ ROSALES DNI:08170776 -DIAMANTE | H19: SOLICITUDES | I19: DERIVACIÓN ESPECIALIDADES | K19: Viva 1 A | L19: SIN RESPUESTA | M19: 45742 | N19: 7 | P19: no se ubica el correo | Q19: SI | R19: Chrismerly | S19: 45751 | T19: Seguimiento | U19: =VLOOKUP(C19,'DATA CORREO'!G:W,17,0) -> CERRADA | V19: =VLOOKUP(C19,'DATA CORREO'!G:V,16,0) -> 45751 | W19: No se encuentra en correo
A20: 45726 | B20: CORREO | C20: 44841514 | D20: URGENTE // RIMAC VIP // CARINA MIRANDA LAZO // DNI 44841514 // CONSULTA PROVEEDOR REEMPLAZO STARVITAL | H20: RECLAMOS | I20: DEMORA ENTREGA DE MEDICAMENTOS | J20: SI | K20: Viva 1 A | L20: SIN RESPUESTA | M20: 45742 | N20: 13 | P20: correo enviado | Q20: SI | R20: Maribel | S20: 45748 | T20: Finalizado | U20: =VLOOKUP(C20,'DATA CORREO'!G:W,17,0) -> CERRADA | V20: =VLOOKUP(C20,'DATA CORREO'!G:V,16,0) -> 45748
A21: 45726 | B21: CORREO | C21: 72154157 | D21: FIORELLA CRISEL VERGARA OLIVO | G21: CONDICIONES DE CONTRATO CON EL PRESTADOR PARA ATENCION A PACIENTE EN MENCION | H21: RECLAMOS | I21: INSATISFACCION POR ATENCIÓN MEDICA | J21: SI | K21: Viva 1 A | L21: SIN RESPUESTA | M21: 45742 | N21: 8 | P21: se respondio fecha 11/3 | Q21: SI | R21: Chrismerly | S21: 45751 | T21: Finalizado | U21: =VLOOKUP(C21,'DATA CORREO'!G:W,17,0) -> CERRADA | V21: =VLOOKUP(C21,'DATA CORREO'!G:V,16,0) -> 45751 | W21: No se evidencia respuesta al asegurador, fue reenviado al correo de quejasyreclamos hoy por chrismerly, ultimo correo de seguimiento: De: Freddy Garzón <fgarzon@viva1a.com.pe> Enviado: martes, 11 de marzo de 2025 16:07 Para: Admision Rimac <admisionrimac@viva1a.com.pe>; Gianina Jessica Sigueña Aldana <gsiguenas@viva1a.com.pe> Cc: Julio Marco Inocencio Pereyra <jinocencio@viva1a.com.pe>; Chrismerly Abigail Huaranca López <chuaranca@viva1a.com.pe> Asunto: RV: CONDICIONES DE CONTRATO CON EL PRESTADOR PARA ATENCION A PACIENTE EN MENCION saludos en relación al caso favor programar las atenciones presenciales y cuando la paciente lo requiera se puede ofrecer tele consulta o atención en sede laboratorios según protocolo. gracias
A22: 45726 | B22: CORREO | C22: 44841514 | D22: CARINA MIRANDA LAZO | G22: URGENTE // RIMAC VIP // CARINA MIRANDA LAZO // DNI 44841514 // CONSULTA PROVEEDOR REEMPLAZO STARVITAL | H22: RECLAMOS | I22: DEMORA ENTREGA DE MEDICAMENTOS | J22: SI | K22: Viva 1 A | L22: SIN RESPUESTA | M22: 45742 | N22: 13 | P22: correo enviado | Q22: SI | R22: Maribel | S22: 45748 | T22: Finalizado | U22: =VLOOKUP(C22,'DATA CORREO'!G:W,17,0) -> CERRADA | V22: =VLOOKUP(C22,'DATA CORREO'!G:V,16,0) -> 45748
A23: 45727 | B23: CORREO | C23: 74839971 | D23: ALEJANDRO MIGUEL FIELD HERRERA | G23: programa cuidate - ALEJANDRO MIGUEL FIELD HERRERA | H23: SOLICITUDES | I23: DEMANDA INDUCIDA | K23: Viva 1 A | L23: SIN RESPUESTA | M23: 45742 | N23: 9 | P23: correo enviado | Q23: SI | R23: Maribel | S23: 45748 | T23: Finalizado | U23: =VLOOKUP(C23,'DATA CORREO'!G:W,17,0) -> CERRADA | V23: =VLOOKUP(C23,'DATA CORREO'!G:V,16,0) -> 45748
A24: 45727 | B24: CORREO | C24: 72845505 | D24: MORALES HERNANDEZ FABRICIO ANDRE | G24: URGENTE !!!CONFIRMACIÓN DE ATENCIÓN DE USUARIO MORALES HERNANDEZ FABRICIO ANDRE DNI 72845505-REDONDOS | H24: RECLAMOS | I24: DEMORA COORDINACIÓN DE CITAS | J24: SI | K24: Viva 1 A | L24: SIN RESPUESTA | M24: 45742 | N24: 9 | P24: no | Q24: SI | R24: Chrismerly | S24: 45751 | T24: Finalizado | U24: =VLOOKUP(C24,'DATA CORREO'!G:W,17,0) -> CERRADA | V24: =VLOOKUP(C24,'DATA CORREO'!G:V,16,0) -> 45751 | W24: No se encuentra en correo, llego en esta base
A25: 45728 | B25: CORREO | C25: 72844745 | D25: Diego Alejandro Vasquez Iglesias | G25: ADMINISTRADORA JOCKEY - programa Cuidate Rimac // Aseg. Vasquez Iglesias Diego // EPS - E0003570 | H25: RECLAMOS | I25: DEMORA ENTREGA DE MEDICAMENTOS | J25: SI | K25: Viva 1 A | L25: SIN RESPUESTA | M25: 45735 | N25: 5 | P25: respondido 31/3 | Q25: SI | R25: Kathy | S25: 45747 | T25: Finalizado | U25: =VLOOKUP(C25,'DATA CORREO'!G:W,17,0) -> CERRADA | V25: =VLOOKUP(C25,'DATA CORREO'!G:V,16,0) -> 45747
A26: 45728 | B26: CORREO | C26: 6698348 | D26: DANIEL AUGUSTO REYES HUERTA | G26: RIMAC VIP / REGISTRO PARA PROGRAMA CUIDATE /DANIEL AUGUSTO REYES HUERTA | H26: SOLICITUDES | I26: DEMANDA INDUCIDA | K26: Viva 1 A | L26: SIN RESPUESTA | M26: 45742 | N26: 10 | P26: correo enviado | Q26: SI | R26: Gianina | S26: 45741 | T26: Finalizado | U26: =VLOOKUP(C26,'DATA CORREO'!G:W,17,0) -> TRASLADADA | V26: =VLOOKUP(C26,'DATA CORREO'!G:V,16,0) -> 45741
A27: 45728 | B27: CORREO | C27: 7805048 | D27: JAVIER CARLOS SUAREZ HELFER | G27: INSCRIPCION PROGRAMA CUIDATE / HIPERTENSION ARTERIAL / JAVIER CARLOS SUAREZ HELFER | H27: RECLAMOS | I27: DEMORA COORDINACIÓN DE CITAS | J27: SI | K27: Viva 1 A | L27: SIN RESPUESTA | M27: 45742 | N27: 9 | P27: correo enviado | Q27: SI | R27: Maribel | S27: 45748 | T27: Finalizado | U27: =VLOOKUP(C27,'DATA CORREO'!G:W,17,0) -> CERRADA | V27: =VLOOKUP(C27,'DATA CORREO'!G:V,16,0) -> 45748
A28: 45728 | B28: CORREO | C28: 44852752 | D28: Elizabeth Elena Santos Rudas | G28: Urgente solicitud de ingreso: Programa cuidate asma - Sra. Elizabeth Santos Rudas | H28: SOLICITUDES | I28: DEMANDA INDUCIDA | K28: Viva 1 A | L28: SIN RESPUESTA | M28: 45742 | N28: 10 | P28: no | Q28: SI | R28: Chrismerly | S28: 45751 | T28: Finalizado | U28: =VLOOKUP(C28,'DATA CORREO'!G:W,17,0) -> CERRADA | V28: =VLOOKUP(C28,'DATA CORREO'!G:V,16,0) -> 45751 | W28: No se encuentra en correo, llego en esta base
A29: 45728 | B29: CORREO | C29: 7731756 | D29: La Serna Garcia Laura | G29: QUEJA VIVA 1A / CONSULTA / URGENTE PAGO DE MEDICAMENTO PROGRAMA CUIDATE - RIMAC // ASOC. BENEFICA PRISMA // Seguimiento ZL | H29: RECLAMOS | I29: DEMORA ENTREGA DE MEDICAMENTOS | K29: Viva 1 A | L29: SIN RESPUESTA | M29: 45742 | N29: 9 | P29: si | Q29: SI | R29: Chrismerly | S29: 45751 | T29: Finalizado | U29: =VLOOKUP(C29,'DATA CORREO'!G:W,17,0) -> CERRADA | V29: =VLOOKUP(C29,'DATA CORREO'!G:V,16,0) -> 45749 | W29: Respuesta enviada por maribel el 2/4/2025
A30: 45728 | B30: CORREO | C30: 6040784 | D30: JULIO RAFAEL MARTIN CAMPOS | G30: RIMAC VIP // JULIO RAFAEL MARTIN CAMPOS | H30: RECLAMOS | I30: DEMORA COORDINACIÓN DE CITAS | J30: SI | K30: Viva 1 A | L30: SIN RESPUESTA | M30: 45742 | N30: 11 | P30: si | Q30: SI | R30: Maribel | S30: 45718 | T30: Finalizado | U30: =VLOOKUP(C30,'DATA CORREO'!G:W,17,0) -> CERRADA | V30: =VLOOKUP(C30,'DATA CORREO'!G:V,16,0) -> 45749
A31: 45728 | B31: CORREO | C31: 42413293 | D31: Julissa Fabiola Gómez Paz | G31: PROGRAMA CUIDATE// EPS RIMAC//Julissa Fabiola Gómez Paz//Hipertensión arterial | H31: RECLAMOS | I31: DEMORA COORDINACIÓN DE CITAS | J31: SI | K31: Viva 1 A | L31: SIN RESPUESTA | M31: 45742 | N31: 11 | P31: no | Q31: SI | R31: Chrismerly | S31: 45750 | T31: Finalizado | U31: =VLOOKUP(C31,'DATA CORREO'!G:W,17,0) -> CERRADA | V31: =VLOOKUP(C31,'DATA CORREO'!G:V,16,0) -> 45751 | W31: No se encuentra en correo, llego en esta base
A32: 45728 | B32: CORREO | C32: 46674191 | D32: CASO CRITICO VERONICA ANDREA TAMARIZ VALENTIN - 46674191 | G32: CASO CRITICO VERONICA ANDREA TAMARIZ VALENTIN - 46674191 | H32: RECLAMOS | I32: DEMORA COORDINACIÓN DE CITAS | J32: SI | K32: Viva 1 A | L32: SIN RESPUESTA | M32: 45742 | N32: 11 | P32: si | Q32: SI | R32: Maribel | S32: 45718 | T32: Finalizado | U32: =VLOOKUP(C32,'DATA CORREO'!G:W,17,0) -> CERRADA | V32: =VLOOKUP(C32,'DATA CORREO'!G:V,16,0) -> 45749
A33: 45729 | B33: CORREO | C33: 25616130 | D33: PAULA ZARELA MATTA VDA DE RAMOS | G33: RECLAMO 25-SBS013610 // PAULA ZARELA MATTA VDA DE RAMOS | H33: RECLAMOS | I33: INSATISFACCION POR ATENCIÓN MEDICA | J33: SI | K33: Viva 1 A | L33: SIN RESPUESTA | M33: 45742 | N33: 11 | P33: no | Q33: NO | T33: Seguimiento | U33: =VLOOKUP(C33,'DATA CORREO'!G:W,17,0) -> CERRADA | V33: =VLOOKUP(C33,'DATA CORREO'!G:V,16,0) -> 45748 | W33: Resuelto en base oriana ok
A34: 45729 | B34: CORREO | D34: PACIENTES CRONICOS - GRUPO CARVAJAL - E0037430, E0037415, E0037416, E0037420 | G34: PACIENTES CRONICOS - GRUPO CARVAJAL - E0037430, E0037415, E0037416, E0037420 | H34: SOLICITUDES | I34: DEMANDA INDUCIDA | J34: SI | K34: Viva 1 A | L34: SIN RESPUESTA | M34: 45742 | N34: 11 | P34: no | Q34: SI | R34: Chrismerly | S34: 45751 | T34: Seguimiento | U34: SEGUIMIENTO | V34: 45751 | W34: Discriminado por usuarios, resuelto parcialmente
A35: 45729 | B35: CORREO | C35: 8185495 | D35: PATRICIA OCHOA LUBINOFF | G35: URGENTE ENTREGA DE MEDICINAS // GALLAGHER : PLAN EPS (PROGRAMA CRONICOS HIPOTIROIDISMO): PATRICIA OCHOA LUBINOFF (reclamo) | H35: RECLAMOS | I35: DEMORA COORDINACIÓN DE CITAS | J35: SI | K35: Viva 1 A | L35: SIN RESPUESTA | M35: 45742 | N35: 11 | P35: SI | Q35: SI | R35: Maribel | S35: 45718 | T35: Finalizado | U35: =VLOOKUP(C35,'DATA CORREO'!G:W,17,0) -> CERRADA | V35: =VLOOKUP(C35,'DATA CORREO'!G:V,16,0) -> 45749
A36: 45729 | B36: CORREO | C36: 10060304 | D36: Glicerio Camino Siles | G36: Programa Cuidate | H36: SOLICITUDES | I36: DEMANDA INDUCIDA | J36: SI | K36: Viva 1 A | L36: SIN RESPUESTA | M36: 45742 | N36: 11 | P36: no | Q36: SI | R36: Chrismerly | S36: 45751 | T36: Finalizado | U36: =VLOOKUP(C36,'DATA CORREO'!G:W,17,0) -> CERRADA | V36: =VLOOKUP(C36,'DATA CORREO'!G:V,16,0) -> 45751 | W36: No tiene respuesta
A37: 45730 | B37: CORREO | D37: INVITACION PACIENTES CRONICOS - HORTUS | G37: INVITACION PACIENTES CRONICOS - HORTUS | H37: SOLICITUDES | I37: DEMANDA INDUCIDA | K37: Viva 1 A | L37: SIN RESPUESTA | M37: 45742 | N37: 11 | P37: no | Q37: SI | R37: Maribel | S37: 45750 | T37: Seguimiento | U37: SEGUIMIENTO | V37: 45750 | W37: Son 6 pacientes, se asignaron 4 pendiente 2 que no se ha logrado comunicación
A38: 45730 | B38: CORREO | D38: URGENTE : Programa PPC / URGENTE / EMPRESA SAPET / ACTUALIZACION/ LISTADO PACIENTE CRONICOS | G38: URGENTE : Programa PPC / URGENTE / EMPRESA SAPET / ACTUALIZACION | H38: SOLICITUDES | I38: INORMACIÓN PROCESOS | J38: SI | K38: Viva 1 A | L38: SIN RESPUESTA | M38: 45742 | N38: 12 | P38: NO | Q38: SI | R38: Chrismerly | S38: 45751 | T38: seguimiento | U38: SEGUIMIENTO | V38: 45751 | W38: Discriminado por usuarios, resuelto parcialmente
A39: 45730 | B39: CORREO | C39: 7731756 | D39: La Serna Garcia Laura | G39: QUEJA CHEQUEO PREVENTIVO //B CONSULTA / QUEJA ATENCION EN LA EPS // ASOC. BENEFICA PRISMA . Aseg. Laura Laserna // Seguimiento ZL | H39: RECLAMOS | I39: DEMORA COORDINACIÓN DE CITAS | J39: SI | K39: Viva 1 A | L39: SIN RESPUESTA | M39: 45742 | N39: 12 | P39: correo enviado | Q39: SI | R39: Maribel | S39: 45751 | T39: Finalizado | U39: =VLOOKUP(C39,'DATA CORREO'!G:W,17,0) -> CERRADA | V39: =VLOOKUP(C39,'DATA CORREO'!G:V,16,0) -> 45749
A40: 45730 | B40: CORREO | C40: 25639731 | D40: CONTRERA SOLARI ROSARIO | G40: URGENTE - COORDINACION PENDIENTE - ANALISIS - KATHERINE OCHOA - DNI: 25639731 | H40: RECLAMOS | I40: DEMORA TOMA DE TOMA DE MUESTRAS | J40: SI | K40: Viva 1 A | L40: SIN RESPUESTA | M40: 45735 | N40: 8 | P40: correo enviado | Q40: SI | R40: Maribel | S40: 45747 | T40: Finalizado | U40: =VLOOKUP(C40,'DATA CORREO'!G:W,17,0) -> CERRADA | V40: =VLOOKUP(C40,'DATA CORREO'!G:V,16,0) -> 45747
A41: 45733 | B41: CORREO | C41: 2760176 | D41: Zhu Lei | G41: URGENTE _ Proveedor Viva 1A y Pacientes Crónicos | H41: RECLAMOS | I41: INSATISFACCION POR ATENCIÓN MEDICA | J41: SI | K41: Viva 1 A | L41: SIN RESPUESTA | M41: 45742 | N41: 10 | P41: correo enviado | Q41: SI | R41: Chrismerly | S41: 45754 | T41: Finalizado | U41: CERRADA | V41: =VLOOKUP(C41,'DATA CORREO'!G:V,16,0) -> 45754
A42: 45733 | B42: CORREO | C42: 6927900 | D42: MARIA TERESA RODRIGUEZ GI | G42: RECLAMO 25-EPS002295 // MARIA TERESA RODRIGUEZ GIL DE VARGAS | H42: RECLAMOS | I42: DEMORA REGANDEMIENTO DE CITAS | J42: SI | K42: Viva 1 A | L42: SIN RESPUESTA | M42: 45742 | N42: 13 | P42: correo enviado | Q42: SI | R42: Maribel | S42: 45747 | T42: Finalizado | U42: =VLOOKUP(C42,'DATA CORREO'!G:W,17,0) -> CERRADA | V42: =VLOOKUP(C42,'DATA CORREO'!G:V,16,0) -> 45742
A43: 45734 | B43: CORREO | C43: 8248299 | D43: RIMAC VIP // ATENCION PENDIENTE AL PROGRAMA CUIDATE // C: FREDY GAMARRA ELIAS | H43: RECLAMOS | I43: DEMORA COORDINACIÓN DE CITAS | J43: SI | K43: Viva 1 A | L43: SIN RESPUESTA | M43: 45742 | N43: 13 | P43: correo enviado | Q43: SI | R43: Pedro Bereche | S43: 45744 | T43: Finalizado | U43: =VLOOKUP(C43,'DATA CORREO'!G:W,17,0) -> CERRADA | V43: =VLOOKUP(C43,'DATA CORREO'!G:V,16,0) -> 45744
A44: 45734 | B44: CORREO | C44: 30849054 | D44: RICARDO ARTURO NUÑEZ RODRIGO | G44: URGENTE - PROGRAMA CUIDATE // RICARDO ARTURO NUÑEZ RODRIGO // E0001394 | H44: RECLAMOS | I44: NO ACEPTA COPAGOS | J44: SI | K44: Viva 1 A | L44: SIN RESPUESTA | M44: 45742 | N44: 14 | P44: si | Q44: SI | R44: Gianina | S44: 45721 | T44: Finalizado | U44: =VLOOKUP(C44,'DATA CORREO'!G:W,17,0) -> CERRADA | V44: =VLOOKUP(C44,'DATA CORREO'!G:V,16,0) -> 45721
A45: 45735 | B45: CORREO | C45: 25677282 | D45: ROXANA ESPERANZA TAVERA D ANGELO | G45: RE: RIMAC VIP / Reclamo de cliente por falta de atención / ROXANA ESPERANZA TAVERA D ANGELO | H45: RECLAMOS | I45: DEMORA COORDINACIÓN DE CITAS | J45: SI | K45: Viva 1 A | L45: SIN RESPUESTA | M45: 45742 | N45: 5 | P45: si | Q45: SI | R45: Maribel | S45: 45718 | T45: Finalizado | U45: =VLOOKUP(C45,'DATA CORREO'!G:W,17,0) -> CERRADA | V45: =VLOOKUP(C45,'DATA CORREO'!G:V,16,0) -> 45749
A46: 45736 | B46: CORREO | C46: 7806297 | D46: BARUA ALZAMORA VICTOR | G46: PCTE BARUA ALZAMORA VICTOR | H46: RECLAMOS | I46: DEMORA ENTREGA DE MEDICAMENTOS | J46: SI | K46: Viva 1 A | L46: SIN RESPUESTA | M46: 45742 | N46: 6 | P46: si | Q46: SI | R46: Maribel | S46: 45718 | T46: Finalizado | U46: =VLOOKUP(C46,'DATA CORREO'!G:W,17,0) -> CERRADA | V46: =VLOOKUP(C46,'DATA CORREO'!G:V,16,0) -> 45749
A47: 45737 | B47: CORREO | D47: DHAGA DEL CASTILLO YLLANES | G47: VALIDACIÓN OM NUEVO DIAGNOSTICO - PACIENTE DHAGA DEL CASTILLO YLLANES | H47: SOLICITUDES | I47: DEMANDA INDUCIDA | K47: Viva 1 A | L47: EN GESTIÓN | M47: 45742 | N47: 4 | P47: no | Q47: NO | T47: Cancelado | U47: ACTIVA | V47: =VLOOKUP(C47,'DATA CORREO'!G:V,16,0) -> #N/A | W47: No se encuentra en el correo
A48: 45737 | B48: CORREO | D48: PROGRAMA CUIDATE: PROGRAMA DE CONTROL DE ENFERMEDADES CRÓNICAS - ASEACES RUC 20342985646 | G48: PROGRAMA CUIDATE: PROGRAMA DE CONTROL DE ENFERMEDADES CRÓNICAS - ASEACES RUC 20342985646 | H48: SOLICITUDES | I48: DEMANDA INDUCIDA | K48: Viva 1 A | L48: EN GESTIÓN | M48: 45742 | N48: 3 | P48: no | Q48: SI | R48: Maribel | S48: 45718 | T48: Seguimiento | U48: SEGUIMIENTO | V48: 45749 | W48: Son 8 pacientes, se le asigno cita a 5 de ellos y 3 no se ha logrado contacto
A49: 45737 | B49: CORREO | C49: 8743921 | D49: YOLANDA MOSCOL AREVALO | G49: RIMAC VIP//PROGRAMA VIVA A// YOLANDA MOSCOL AREVALO | H49: RECLAMOS | I49: DEMORA ENTREGA DE MEDICAMENTOS | K49: Viva 1 A | L49: EN GESTIÓN | M49: 45742 | N49: 3 | P49: no | Q49: SI | R49: Chrismerly | S49: 45747 | T49: Finalizado | U49: =VLOOKUP(C49,'DATA CORREO'!G:W,17,0) -> CERRADA | V49: =VLOOKUP(C49,'DATA CORREO'!G:V,16,0) -> 45758
A50: 45737 | B50: CORREO | C50: 6686347 | G50: RIMAC VIP // INSCRIPCION PROGRAMA CUIDATE // C: DAVID BALLARTA GUEVARA | H50: SOLICITUDES | I50: DEMANDA INDUCIDA | K50: Viva 1 A | L50: EN GESTIÓN | M50: 45742 | N50: 4 | P50: correo enviado | Q50: SI | R50: Maribel | S50: 45745 | T50: Finalizado | U50: =VLOOKUP(C50,'DATA CORREO'!G:W,17,0) -> CERRADA | V50: =VLOOKUP(C50,'DATA CORREO'!G:V,16,0) -> 45745
A51: 45737 | B51: CORREO | C51: 6204981 | D51: URGENTE : Programa PPC / URGENTE / EMPRESA SAPET / ACTUALIZACION/ LISTADO PACIENTE CRONICOS | G51: URGENTE : Programa PPC / URGENTE / EMPRESA SAPET / ACTUALIZACION/ LISTADO PACIENTE CRONICOS | H51: SOLICITUDES | I51: DEMANDA INDUCIDA | K51: Viva 1 A | L51: EN GESTIÓN | M51: 45742 | N51: 4 | P51: correo enviado | Q51: SI | R51: Maribel | S51: 45745 | T51: Seguimiento | U51: =VLOOKUP(C51,'DATA CORREO'!G:W,17,0) -> CERRADA | V51: =VLOOKUP(C51,'DATA CORREO'!G:V,16,0) -> 45745 | W51: Solo enviaron datos de un paciente FELIPE ALBERTO BARRAZA SUAREZ y se soluciono, pero ahora estan solicitando el listado de pacientes de empresa SAPET que han coordinado o estan pendientes: Estimado Freddy, Lo que venimos solicitando es el listado de afiliados de pacientes crónicos con los cuales ya han coordinado las órdenes para exámenes de laboratorio y los que están pendientes de programación o fecha siguiente de consulta agendada. Atte, Liz Dulanto Administradora de Cuenta
A52: 45740 | B52: CORREO | C52: 10808635 | D52: SANDRA URBINA PEREZ | G52: CASO PACIENTE SANDRA URBINA PEREZ | H52: RECLAMOS | I52: DEMORA ENTREGA DE MEDICAMENTOS | K52: Viva 1 A | L52: EN GESTIÓN | M52: 45742 | N52: 4 | P52: correo enviado | Q52: SI | R52: Maribel | S52: 45748 | T52: Finalizado | U52: =VLOOKUP(C52,'DATA CORREO'!G:W,17,0) -> CERRADA | V52: =VLOOKUP(C52,'DATA CORREO'!G:V,16,0) -> 45748
A53: 45740 | B53: CORREO | C53: 40204963 | D53: OLGA TATIANA CUADROS BASIS | G53: RIMAC VIP/ ENVÍO DE MEDICAMENTOS DE PROGRAMA CRÓNICO/ OLGA TATIANA CUADROS BASIS | H53: RECLAMOS | I53: DEMORA COORDINACIÓN DE CITAS | K53: Viva 1 A | L53: EN GESTIÓN | M53: 45742 | N53: 3 | P53: data rimac si | Q53: SI | R53: Dr. Freddy Garzon | S53: 45718 | T53: Finalizado | U53: =VLOOKUP(C53,'DATA CORREO'!G:W,17,0) -> CERRADA | V53: =VLOOKUP(C53,'DATA CORREO'!G:V,16,0) -> 45749
A54: 45740 | B54: CORREO | C54: 1 | D54: CONTINUIDAD DE TERAPIAS FISICAS/REFERIDOS HOL SALUD | G54: CONTINUIDAD DE TERAPIAS FISICAS/REFERIDOS HOL SALUD | H54: SOLICITUDES | I54: INORMACIÓN PROCESOS | K54: Viva 1 A | L54: EN GESTIÓN | M54: 45742 | N54: 3 | P54: no | Q54: SI | R54: Chrismerly | S54: 45751 | T54: Seguimiento | U54: SEGUIMIENTO | V54: =VLOOKUP(C54,'DATA CORREO'!G:V,16,0) -> #N/A | W54: Discriminado por usuarios, resuelto parcialmente
A55: 45740 | B55: CORREO | C55: 10796964 | D55: Walter Ronald García Becerra | G55: INSCRIPCION A PROGRAMA CUIDATE / CLIENTE AMERICA MOVIL / E0021609 / PCTE GARCIA BECERRA WALTER RONALD | H55: RECLAMOS | I55: DEMORA COORDINACIÓN DE CITAS | K55: Viva 1 A | L55: EN GESTIÓN | M55: 45742 | N55: 3 | P55: correo enviado | Q55: SI | R55: Chrismerly | S55: 45747 | T55: Finalizado | U55: =VLOOKUP(C55,'DATA CORREO'!G:W,17,0) -> CERRADA | V55: =VLOOKUP(C55,'DATA CORREO'!G:V,16,0) -> 45747
A56: 45740 | B56: CORREO | C56: 6686347 | D56: DAVID BALLARTA GUEVARA | G56: RIMAC VIP // INSCRIPCION PROGRAMA CUIDATE // C: DAVID BALLARTA GUEVARA | H56: SOLICITUDES | I56: DEMANDA INDUCIDA | K56: Viva 1 A | L56: EN GESTIÓN | M56: 45742 | N56: 4 | P56: correo enviado | Q56: SI | R56: Maribel | S56: 45745 | T56: Finalizado | U56: =VLOOKUP(C56,'DATA CORREO'!G:W,17,0) -> CERRADA | V56: =VLOOKUP(C56,'DATA CORREO'!G:V,16,0) -> 45745

Sheet pendientes rimac 2506
A1: FECHA DE INGRESO DEL REQUERIMIENTO | B1: CANAL | C1: DNI | D1: NOMBRES Y APELLIDOS | E1: RUC CONTRATANTE | F1: DESCRIPCIÓN DE CONTRATANTE | G1: TENOR DEL CORREO | H1: TIPO DE REQUERIMIENTO | I1: TIPO DE RECLAMO | J1: RECLAMO FUNDAMENTADO | K1: RESPONSABLE DE LA RESPUESTA | L1: ESTATUS DE GESTIÓN | M1: FECHA DE RESOLUCION | N1: DIAS TOTALES | O1: OBSERVACION | P1: cruce base reclamos
A2: 45743 | B2: CORREO | C2: 1 | D2: UCSM // PROGRAMA OTRAS ENFERMEDADES/ PROVEEDOR: VIVA A1 | G2: UCSM // PROGRAMA OTRAS ENFERMEDADES/ PROVEEDOR: VIVA A1 | H2: RECLAMOS | I2: INSATISFACCION POR ATENCIÓN MEDICA | K2: Viva 1 A | L2: SIN RESPUESTA | M2: 45833 | N2: 65 | P2: =VLOOKUP(C2,'DATA CORREO'!G:W,17,0) -> #N/A
A3: 45747 | B3: CORREO | C3: 7636877 | D3: MARIA DEL CARMEN CARRASCO PANTA | G3: RECLAMO 25-EPS002484 // MARIA DEL CARMEN CARRASCO PANTA | H3: RECLAMOS | I3: DEMORA COORDINACIÓN DE CITAS | K3: Viva 1 A | L3: SIN RESPUESTA | M3: 45833 | N3: 63 | P3: =VLOOKUP(C3,'DATA CORREO'!G:W,17,0) -> CERRADA
A4: 45748 | B4: CORREO | C4: 10004424 | D4: JOSE HERNAN LATORRE DIAZ | G4: URGENTE // HOSPITALIZACION EN CASA | H4: SOLICITUDES | I4: DEMANDA INDUCIDA | K4: Viva 1 A | L4: SIN RESPUESTA | M4: 45833 | N4: 62 | P4: =VLOOKUP(C4,'DATA CORREO'!G:W,17,0) -> CERRADA
A5: 45751 | B5: CORREO | C5: 29702122 | D5: CÁCERES CHALCO HIPOLITO. | G5: INGRESO RCV CONTINUADOR ANGLO AMERICAM CACERES CHALCO HIPOLITO DNI: 29702122 | H5: SOLICITUDES | I5: DEMANDA INDUCIDA | K5: Viva 1 A | L5: SIN RESPUESTA | M5: 45833 | N5: 59 | P5: =VLOOKUP(C5,'DATA CORREO'!G:W,17,0) -> CERRADA
A6: 45756 | B6: CORREO | C6: 74334143 | D6: MICHAEL ANDERSON URIARTE LEON | G6: MEDICINAS PENDIENTES - MICHAEL ANDERSON URIARTE LEON - dni 74334143 | H6: RECLAMOS | I6: DEMORA ENTREGA DE MEDICAMENTOS | K6: Viva 1 A | L6: SIN RESPUESTA | M6: 45833 | N6: 56 | P6: =VLOOKUP(C6,'DATA CORREO'!G:W,17,0) -> CERRADA
A7: 45758 | B7: CORREO | C7: 46036087 | D7: SALVATIERRA MELGAREJO JOHN ANDERSSON | G7: INGRESO AL PROGRAMA CUIDATE - SALVATIERRA MELGAREJO JOHN ANDERSSON - EPS CUIDA DIGITAL S.A.C E0028227 | H7: SOLICITUDES | I7: DEMANDA INDUCIDA | K7: Viva 1 A | L7: SIN RESPUESTA | M7: 45833 | N7: 54 | P7: =VLOOKUP(C7,'DATA CORREO'!G:W,17,0) -> CERRADA
A8: 45757 | B8: CORREO | C8: 72844745 | D8: Diego Alejandro Vasquez Iglesias | G8: ADMINISTRADORA JOCKEY - programa Cuidate Rimac // Aseg. Vasquez Iglesias Diego // EPS - E0003570 | H8: RECLAMOS | I8: DEMORA TOMA DE TOMA DE MUESTRAS | J8: SI | K8: Viva 1 A | L8: SIN RESPUESTA | M8: 45833 | N8: 55 | P8: =VLOOKUP(C8,'DATA CORREO'!G:W,17,0) -> CERRADA
A9: 45776 | B9: CORREO | C9: 8224705 | D9: RUBINI SUITO MARIO | G9: Paciente: MARIO RUBINI SUITO | H9: SOLICITUDES | I9: DEMANDA INDUCIDA | K9: Viva 1 A | L9: SIN RESPUESTA | M9: 45833 | N9: 42 | P9: =VLOOKUP(C9,'DATA CORREO'!G:W,17,0) -> CERRADA
A10: 45769 | B10: CORREO | C10: 9309622 | D10: RAUL ANTONIO MEJIA RAMIREZ | G10: CONFIRMAR INSCRIPCION PROGRAMA CUIDATE - RAUL ANTONIO MEJIA RAMIREZ DNI 09309622 | H10: RECLAMOS | I10: DEMORA TOMA DE TOMA DE MUESTRAS | K10: Viva 1 A | L10: SIN RESPUESTA | M10: 45833 | N10: 47 | P10: =VLOOKUP(C10,'DATA CORREO'!G:W,17,0) -> CERRADA
A11: 45779 | B11: CORREO | C11: 7879761 | D11: CARMEN YSABEL DENEGRI MORALES | G11: CARMEN YSABEL DENEGRI MORALES/Dni: 07879761/póliza: E0018055 | H11: RECLAMOS | I11: DEMORA ENTREGA DE MEDICAMENTOS | K11: Viva 1 A | L11: SIN RESPUESTA | M11: 45833 | N11: 39 | P11: =VLOOKUP(C11,'DATA CORREO'!G:W,17,0) -> CERRADA
A12: 45749 | B12: CORREO | C12: 2869403 | D12: GARCÍA SÁNCHEZ RAFAEL GUSTAVO | G12: URGENTE Gestión Programa de Pacientes Crónicos / EMPRESA SAPET / URGENT | H12: RECLAMOS | I12: DEMORA ENTREGA DE MEDICAMENTOS | K12: Viva 1 A | L12: SIN RESPUESTA | M12: 45833 | N12: 61 | P12: =VLOOKUP(C12,'DATA CORREO'!G:W,17,0) -> CERRADA
A13: 45749 | B13: CORREO | C13: 23656818 | D13: MENESES SERPA ANGELINO FORTUNATO | G13: RIMAC VIP//INSCRIPCIÓN PROGRAMA CUIDATE// ANGELINO FORTUNATO MENESES SERPA | H13: SOLICITUDES | I13: DEMANDA INDUCIDA | K13: Viva 1 A | L13: SIN RESPUESTA | M13: 45833 | N13: 61 | P13: =VLOOKUP(C13,'DATA CORREO'!G:W,17,0) -> CERRADA
A14: 45779 | B14: CORREO | C14: 9437292 | D14: ALFREDO CARLOS VALDIVIA DEL ALCAZAR I | G14: Envio orden de Analisis | H14: SOLICITUDES | I14: DEMORA TOMA DE TOMA DE MUESTRAS | K14: Viva 1 A | L14: SIN RESPUESTA | M14: 45833 | N14: 39 | P14: =VLOOKUP(C14,'DATA CORREO'!G:W,17,0) -> CERRADA
A15: 45779 | B15: CORREO | C15: 71119014 | D15: RAMON DIAZ DIANA MARLIZ | G15: OTROS CRONICOS//ARTRITIS REMATOIDE//INRETAIL | H15: RECLAMOS | I15: DEMORA TOMA DE TOMA DE MUESTRAS | K15: Viva 1 A | L15: SIN RESPUESTA | M15: 45833 | N15: 39 | P15: =VLOOKUP(C15,'DATA CORREO'!G:W,17,0) -> CERRADA | X15: 1575
A16: 45779 | B16: CORREO | C16: 7727653 | D16: OSCAR MARCIAL VELIT CASAS | G16: RIMAC VIP/ INSCRIPCION AL PROGRAMA OSCAR MARCIAL VELIT CASAS DNI 07727653 | H16: SOLICITUDES | I16: DEMANDA INDUCIDA | K16: Viva 1 A | L16: SIN RESPUESTA | M16: 45833 | N16: 39 | P16: =VLOOKUP(C16,'DATA CORREO'!G:W,17,0) -> TRASLADADA
A17: 45779 | B17: CORREO | C17: 1 | D17: GERMAN ROLANDO DE LA CRUZ RAMIREZ | G17: CUIDATE - DX POLINEUROPATIA // GERMAN ROLANDO DE LA CRUZ RAMIREZ DM-HTA | H17: SOLICITUDES | I17: DEMANDA INDUCIDA | K17: Viva 1 A | L17: SIN RESPUESTA | M17: 45833 | N17: 39 | P17: =VLOOKUP(C17,'DATA CORREO'!G:W,17,0) -> #N/A
A18: 45783 | B18: CORREO | C18: 1 | D18: URGENTE - Coordinaciones de entrega de medicamentos y cobertura de exámenes de laboratorio // CNCP - CRONICOS | G18: URGENTE - Coordinaciones de entrega de medicamentos y cobertura de exámenes de laboratorio // CNCP - CRONICOS | H18: RECLAMOS | I18: NO ACEPTA COPAGOS | K18: Viva 1 A | L18: SIN RESPUESTA | M18: 45833 | N18: 37 | P18: =VLOOKUP(C18,'DATA CORREO'!G:W,17,0) -> #N/A
A19: 45761 | B19: CORREO | C19: 6167823 | D19: DIAZ DE AVILES LUZ ANGELICA | G19: ESTATUS CLINICO USUARIA: DIAZ DE AVILES LUZ ANGELICA DNI 06167823 | H19: SOLICITUDES | I19: DEMANDA INDUCIDA | K19: Viva 1 A | L19: SIN RESPUESTA | M19: 45833 | N19: 53 | P19: =VLOOKUP(C19,'DATA CORREO'!G:W,17,0) -> CERRADA
A20: 45784 | B20: CORREO | C20: 78642647 | D20: LOREDO RAMIREZ MARCELO ALONSO | G20: URGENTE!!! DNI: 78642647 LOREDO RAMIREZ MARCELO ALONSO DM TIPO 1 | H20: RECLAMOS | I20: DEMORA ENTREGA DE MEDICAMENTOS | K20: Viva 1 A | L20: SIN RESPUESTA | M20: 45833 | N20: 36 | P20: =VLOOKUP(C20,'DATA CORREO'!G:W,17,0) -> CERRADA
A21: 45785 | B21: CORREO | C21: 1 | D21: *****URGENTE**** IASD - Pacientes con enfermedades crónicas | G21: *****URGENTE**** IASD - Pacientes con enfermedades crónicas | H21: SOLICITUDES | I21: DEMANDA INDUCIDA | K21: Viva 1 A | L21: SIN RESPUESTA | M21: 45833 | N21: 35 | P21: =VLOOKUP(C21,'DATA CORREO'!G:W,17,0) -> #N/A
A22: 45782 | B22: CORREO | C22: 1 | D22: RE: IASD - Pacientes con enfermedades crónicas | G22: RE: IASD - Pacientes con enfermedades crónicas | H22: SOLICITUDES | I22: DEMANDA INDUCIDA | K22: Viva 1 A | L22: SIN RESPUESTA | M22: 45833 | N22: 38 | P22: =VLOOKUP(C22,'DATA CORREO'!G:W,17,0) -> #N/A
A23: 45805 | B23: CORREO | C23: 6040784 | D23: JULIO RAFAEL MARTIN CAMPOS | G23: RIMAC VIP // JULIO RAFAEL MARTIN CAMPOS | H23: RECLAMOS | I23: DEMORA COORDINACIÓN DE CITAS | K23: Viva 1 A | L23: SIN RESPUESTA | M23: 45833 | N23: 21 | P23: =VLOOKUP(C23,'DATA CORREO'!G:W,17,0) -> CERRADA
A24: 45811 | B24: CORREO | C24: 562206 | D24: MOUSA JJ SANSOUR | G24: Paciente Mousa Sansour | H24: SOLICITUDES | I24: DEMANDA INDUCIDA | K24: Viva 1 A | L24: SIN RESPUESTA | M24: 45833 | N24: 17 | P24: =VLOOKUP(C24,'DATA CORREO'!G:W,17,0) -> CERRADA
A25: 45814 | B25: CORREO | C25: 8244905 | D25: FERNANDO ALFONSO CORDOVA PEREZ ALBELA | G25: RIMAC VIP // INCIDENCIA PROGRAMA CUIDATE // C: FERNANDO ALFONSO CORDOVA PEREZ ALBELA | H25: RECLAMOS | I25: DEMORA COORDINACIÓN DE CITAS | K25: Viva 1 A | L25: SIN RESPUESTA | M25: 45833 | N25: 14 | P25: =VLOOKUP(C25,'DATA CORREO'!G:W,17,0) -> CERRADA
A26: 45813 | B26: CORREO | C26: 3889684 | D26: HERRADA GALVEZ GINA | G26: SOLICITUDES PENDIENTES- Gestión Programa de Pacientes Crónicos / EMPRESA SAPET / URGENTE | H26: RECLAMOS | I26: DEMORA TOMA DE TOMA DE MUESTRAS | K26: Viva 1 A | L26: SIN RESPUESTA | M26: 45833 | N26: 15 | P26: =VLOOKUP(C26,'DATA CORREO'!G:W,17,0) -> CERRADA
A27: 45814 | B27: CORREO | C27: 22268777 | D27: LOYOLA VASQUEZ SARA PATRICIA | G27: RECLAMO 0025462603 / PROGRAMA CUIDATE / SARA PATRICIA LOYOLA VASQUEZ | H27: RECLAMOS | I27: DEMORA TOMA DE TOMA DE MUESTRAS | K27: Viva 1 A | L27: SIN RESPUESTA | M27: 45833 | N27: 14 | P27: =VLOOKUP(C27,'DATA CORREO'!G:W,17,0) -> CERRADA
... A29: 45814 | B29: CORREO | C29: 10808635 | D29: URBINA PEREZ SANDRA DANIELLA | G29: URGENTE!!!! URBINA PEREZ SANDRA DANIELLA DNI: 10808635 | H29: RECLAMOS | I29: INSATISFACCION POR ATENCIÓN MEDICA | K29: Viva 1 A | L29: SIN RESPUESTA | M29: 45833 | N29: 14 | P29: =VLOOKUP(C29,'DATA CORREO'!G:W,17,0) -> CERRADA
A30: 45812 | B30: CORREO | C30: 9437292(1) | D30: CARLOS VALDIVIA DEL ALCAZAR | G30: URGENTE ENTREGA DE MEDICINAS DEL PROGRAMA CUIDATE - ALFREDO CARLOS VALDIVIA DEL ALCAZAR CLIENTE: CORTE SUPERIOR DE JUSTICIA DE SAN MARTIN E0037244 | H30: RECLAMOS | I30: DEMORA ENTREGA DE MEDICAMENTOS | K30: Viva 1 A | L30: SIN RESPUESTA | M30: 45833 | N30: 16 | P30: =VLOOKUP(C30,'DATA CORREO'!G:W,17,0) -> CERRADA
A31: 45814 | B31: CORREO | C31: 29278513 | D31: VILLENA FARFAN PEDRO | G31: **URGENTE Revisar Problemas** RE: Programa Cuídate - EPS HORTUS | H31: SOLICITUDES | I31: DEMANDA INDUCIDA | K31: Viva 1 A | L31: SIN RESPUESTA | M31: 45833 | N31: 14 | P31: =VLOOKUP(C31,'DATA CORREO'!G:W,17,0) -> CERRADA
A32: 45819 | B32: CORREO | C32: 42161130 | D32: GUEVARA DELGADO LETICIA | G32: ****** URGENTE****INGRESO PROGRAMA CUIDATE // HORTUS | H32: SOLICITUDES | I32: DEMANDA INDUCIDA | K32: Viva 1 A | L32: SIN RESPUESTA | M32: 45833 | N32: 11 | P32: =VLOOKUP(C32,'DATA CORREO'!G:W,17,0) -> CERRADA
A33: 45804 | B33: CORREO | C33: 1 | D33: VILLAGARAY ESTRADA CARLOS ALBERTO | G33: URGENTE!!! INGRESO AL PROGRAMA-DIAMANTE TERAPIAS FISICAS VILLAGARAY ESTRADA CARLOS ALBERTO | H33: SOLICITUDES | I33: DEMANDA INDUCIDA | K33: Viva 1 A | L33: SIN RESPUESTA | M33: 45833 | N33: 22 | P33: =VLOOKUP(C33,'DATA CORREO'!G:W,17,0) -> #N/A
A34: 45819 | B34: CORREO | C34: 42161130(1) | D34: GUEVARA DELGADO LETICIA | G34: ****** URGENTE****INGRESO PROGRAMA CUIDATE // HORTUS | H34: RECLAMOS | I34: DEMORA ENTREGA DE MEDICAMENTOS | K34: Viva 1 A | L34: SIN RESPUESTA | M34: 45833 | N34: 11 | P34: =VLOOKUP(C34,'DATA CORREO'!G:W,17,0) -> CERRADA
A35: 45817 | B35: CORREO | C35: 8647598 | D35: GUILLERMO HURTADO SILVERA | G35: GUILLERMO HURTADO SILVERA//DNI:25755348//PÓLIZA E0001394 | H35: RECLAMOS | I35: DEMORA ENTREGA DE MEDICAMENTOS | K35: Viva 1 A | L35: SIN RESPUESTA | M35: 45833 | N35: 13 | P35: =VLOOKUP(C35,'DATA CORREO'!G:W,17,0) -> CERRADA
A36: 45803 | B36: CORREO | C36: 29278513 | D36: VILLENA FARFAN PEDRO | G36: *****URGENTE***** INGRESO CUIDATE HOURTUS | H36: RECLAMOS | I36: DEMORA COORDINACIÓN DE CITAS | K36: Viva 1 A | L36: SIN RESPUESTA | M36: 45833 | N36: 23 | P36: =VLOOKUP(C36,'DATA CORREO'!G:W,17,0) -> CERRADA
A37: 45826 | B37: CORREO | C37: 795889 | D37: MARIA LUISA VELASQUEZ | G37: NO CUENTO CON PRESTADOR | TOMA PARA LABORATORIO | TACNA | PX MARIA LUISA VELASQUEZ . | DNI 00795889 | H37: RECLAMOS | I37: DEMORA TOMA DE TOMA DE MUESTRAS | K37: Viva 1 A | L37: SIN RESPUESTA | M37: 45833 | N37: 6 | P37: =VLOOKUP(C37,'DATA CORREO'!G:W,17,0) -> CERRADA
A38: 45833 | B38: CORREO | C38: 7717416 | D38: NOEMI INES ROMAN OLAECHEA DE CARRILLO | G38: VALIDACIÓN INGRESO USUARIA NOEMI INES ROMAN OLAECHEA DE CARRILLO DNI 07717416 | H38: RECLAMOS | I38: INFORMACIÓN PROCESOS | K38: Viva 1 A | L38: EN GESTIÓN | M38: 45833 | N38: 1 | P38: =VLOOKUP(C38,'DATA CORREO'!G:W,17,0) -> TRASLADADA
A39: 45832 | B39: CORREO | C39: 8170776 | D39: NILTON HERNAN JIMENEZ ROSALES | G39: RIMAC | SOLICITUD DE CONSULTA MÉDICA ADICIONAL POR PROGRAMA DIAMANTE | ASEG. NILTON HERNAN JIMENEZ ROSALES | DNI 08170776 | H39: RECLAMOS | I39: NO ACEPTA COPAGOS | K39: Viva 1 A | L39: EN GESTIÓN | M39: 45833 | N39: 2 | P39: =VLOOKUP(C39,'DATA CORREO'!G:W,17,0) -> CERRADA
A40: 45825 | B40: CORREO | C40: 1 | D40: ANGLOAMERICAN | G40: ATENCIÓN DE PACIENTES CRÓNICOS | H40: RECLAMOS | I40: DEMORA ENTREGA DE MEDICAMENTOS | K40: Viva 1 A | L40: SIN RESPUESTA | M40: 45833 | N40: 7 | P40: =VLOOKUP(C40,'DATA CORREO'!G:W,17,0) -> #N/A
A41: 45831 | B41: CORREO | C41: 25-EPS003156 | D41: SARA ANGELICA CACERES LOPEZ | G41: RECLAMO 25-EPS003156 / PACIENTE : SARA ANGELICA CACERES LOPEZ / PROGRAMA CRONICO | H41: RECLAMOS | I41: DEMORA TOMA DE TOMA DE MUESTRAS | K41: Viva 1 A | L41: EN GESTIÓN | M41: 45833 | N41: 3 | P41: =VLOOKUP(C41,'DATA CORREO'!G:W,17,0) -> CERRADA
A42: 45792 | B42: CORREO | C42: 123 | D42: Martina Albirena de Sipion//Jaime Sipion Montero | G42: URGENTE - Atraso en la entrega de Medicina en Piura // CNPC - PACIENTES CRONICOS - Martina Albirena de Sipion//Jaime Sipion Montero | H42: RECLAMOS | I42: DEMORA ENTREGA DE MEDICAMENTOS | K42: Viva 1 A | L42: SIN RESPUESTA | M42: 45833 | N42: 30 | P42: =VLOOKUP(C42,'DATA CORREO'!G:W,17,0) -> CERRADA

Sheet VISUAL
A1: INFORME RECLAMOS Y SOLICITUDES PERÚ
L2: ACTUALIZACIÓN | M2: 46009
D3: TOTAL RADICADAS | G3: RECLAMOS ACTIVAS | J3: RECLAMOS CERRADOS
D4: =GETPIVOTDATA("Cuenta de MOTIVO",TD__!$K$3) -> 1 | E4: =GETPIVOTDATA("Cuenta de MOTIVO2",TD__!$K$3) -> 1 | G4: =IFERROR(GETPIVOTDATA("Cuenta de MOTIVO",TD__!$K$3,"ESTADO FINAL","ACTIVA"),"0") -> 1 | H4: =IFERROR(GETPIVOTDATA("Cuenta de MOTIVO2",TD__!$K$3,"ESTADO FINAL","ACTIVA"),"0%") -> 1 | J4: =IFERROR(GETPIVOTDATA("Cuenta de MOTIVO",TD__!$K$3,"ESTADO FINAL","CERRADA"),"0") -> 0 | K4: =IFERROR(GETPIVOTDATA("Cuenta de MOTIVO2",TD__!$K$3,"ESTADO FINAL","CERRADA"),"0%") -> 0%
T9: 0.010893246
D66: PERIODO | E66: 202602

Sheet TD__
A3: Etiquetas de fila | B3: Cuenta de MOTIVO | F3: Etiquetas de fila | G3: Cuenta de MOTIVO | K3: Etiquetas de fila | L3: Cuenta de MOTIVO | M3: Cuenta de MOTIVO2 | O3: Etiquetas de fila | P3: Cuenta de MOTIVO | R3: Etiquetas de fila | S3: Cuenta de MOTIVO | U3: TIEMPO | V3: CANT
A4: INCONFORMIDAD CON LA ATENCION EN GENERAL | B4: 1 | F4: feb-19 | G4: 1 | K4: ACTIVA | L4: 1 | M4: 1 | O4: CUIDATE | P4: 1 | R4: 24 HORAS | S4: 1 | U4: 24 HORAS | V4: =IFERROR(VLOOKUP(U4,R:S,2,0),0) -> 1
A5: Total general | B5: 1 | F5: Total general | G5: 1 | K5: Total general | L5: 1 | M5: 1 | O5: Total general | P5: 1 | R5: Total general | S5: 1 | U5: 48 HORAS | V5: =IFERROR(VLOOKUP(U5,R:S,2,0),0) -> 0
U6: 72 HORAS | V6: =IFERROR(VLOOKUP(U6,R:S,2,0),0) -> 0
U7: 96 HORAS | V7: =IFERROR(VLOOKUP(U7,R:S,2,0),0) -> 0
U8: 120 HORAS | V8: =IFERROR(VLOOKUP(U8,R:S,2,0),0) -> 0
U9: 6 DIAS O MAS | V9: =IFERROR(VLOOKUP(U9,R:S,2,0),0) -> 0
U10: Total general | V10: =VLOOKUP(U10,R:S,2,0) -> 1

Sheet revision lorena
A1: TIPO DE DOCUMENTO | B1: DOCUMENTO | C1: PACIENTE | D1: DIRECCIÓN | E1: TELÉFONO | F1: CORREO | G1: RADICADO | H1: COD. SUBASTA | I1: PROCESO | J1: VIA DE RECEPCIÓN | K1: DESCRIPCIÓN QUEJA | L1: MOTIVO | M1: SERVICIO | N1: ESPECIALIDAD | O1: FECHA DEL INCIDENTE | P1: RESPUESTA | Q1: Comentarios | R1: FECHA DE RESPUESTA | S1: ESTADO
A2: DNI | B2: 8783626 | C2: GLORIA DURAND DE VALEGA | I2: SOLICITUD | J2: ASEGURADOR | K2: Me comenta la hija de la asegurada del detalle que todos los meses ha sido atendida en casa por Estar Vital, Empresa que como sabemos trabajaba con Rimac; sin embargo, para las atenciones del mes pasado febrero, al llamar para la cita respectiva le han indicado que ya no tienen convenio, por favor podrían informarme que Empresa será ahora quien otorgue el servicio. Asegurada: Gloria Durand de Valega. DNI 08783626. Tener en cuenta que, hasta enero 2025, la asegurada ha sido atendida mensualmente por *Estar Vital* quien la visitaba en casa, ya sea por un geriatra, medicina general o cardiólogo para revisión general y le otorgaban la medicina para la presión y el anticoagulante coberturado al 100% y se pagaba por el Hardal que es para el Parkinson. | L2: SOLICITUD DE CITA | M2: Atencion domiciliaria | N2: MEDICINA GENERAL | O2: 45720 | P2: REPROGRAMACION | Q2: SE AGENDA CITA CORRESPONDIENTE AL MES POR PROGRAMA (QUIERE DOMICILIARIA PARA EL SIGUIENTE MES ) | S2: ACTIVA
A3: DNI | B3: 7307988 | C3: CECILIA ESTHER CANALES ANICAMA | I3: SOLICITUD | J3: ASEGURADOR | K3: Buenas tardes Se está comunicando paciente en mención solicitando su programación de cita médica. Agradeceremos el contacto con la asegurada para su atención, al 943920495 | L3: SOLICITUD DE CITA | N3: MEDICA FAMILIAR - TELECONSULTA | O3: 45721 | P3: FUE ATENDIDA | Q3: 05/03/2025 6:40 PM VIVA 1A CENTRO MEDICO PERU Antonio David Moncada Catalan MEDICA FAMILIAR - TELECONSULTA PROCESADO 05/03/2025 | S3: ACTIVA
B4: 77742062 | C4: EDGAR IGNACIO DE LA TORRE RODRIGUEZ | E4: 994988665 | F4: jackelinrt2013@gmail.com | I4: QUEJAS Y RECLAMOS | J4: ASEGURADOR | K4: Madre del asegurado indica que hace un mes no se ponen en contacto para el seguimiento del programa CUIDATE por diagnóstico de asma y la gestión de envió de medicinas para su menor . Solicita que puedan llamarla en la brevedad posible | L4: NO ASIGNACIÓN DE CITA | M4: CUIDATE | N4: ASMA | O4: 45721 | S4: ACTIVA
B5: 7731756 | C5: LAURA LASERNA | I5: QUEJAS Y RECLAMOS | J5: ASEGURADOR | K5: Hola Ivon, he tenido 2 insidentes: 1 En el chequeo preventivo, no me tomaron la muestra de orina ni la densitometría ósea, cuando enviaste informacion este año, me di cuenta, llame a la clinica y me dieron cita para la densitometría ósea, pero el examen de orina no se podia porque ya habia pasado mas de 7 dias. 2 Estaba en el plan de otras enfermedades cronicas - hipotiroidismo, pero la reserva de cita y examenes, tenia que estar llamando al provedor, en diciembre se olvidaron y no llegaron a comunicarse conmigo. En febrero cambiaron de proveedor y tambien tuve que estar llamando por la cita medica porque se estaba terminando mi medicacion. Luego me llamaron y me indicaron que no podian darme la medicacion para el colesterol alto que mi plan no cubria, habiando estado llevando varios meses la misma medicacion, asi que me han cambiado de plan ahora estoy en deslipidemia. Este plan era muy bueno al principio, porque se tiene atencion medica, medicamentos y analisis de laboratorio, espero que el nuevo proveedor mejore No son consultas propiamente dicha pero me ha pasado. | L5: NO ASIGNACIÓN DE CITA | M5: PACIENTE CRONICO | N5: DISLIPIDEMIA | O5: 45726 | S5: ACTIVA
B6: 8185495 | C6: PATRICIA OCHOA LUBINOFF | E6: 969608702 | I6: QUEJAS Y RECLAMOS | J6: ASEGURADOR | K6: Vania buenas tardes. Hace dos meses me afilié al programa crónicos por hipotiroidismo. Me agendaron hace mes y medio la consulta médica y entregaron la medicina y nunca más se comunicaron conmigo hasta el sábado pasado que me llamaron del teléfono 6183000 (VIVA A1) indicándome que me estaban programando para esta semana y que me confirmarían, osea pasó un mes y medio. Supuestamente el compromiso era que las consultas son mensuales pues en mi caso, se olvidaron y como será con los afiliados que tenemos. Por lo expuesto y dado que me quieren programar sabe dios cuando, indicarme si puedo comprar la medicina (EUTIROX 74 MG) Y PASARLO POR REEMBOLSO bajo condiciones de este programa. Llamé a Rosa Baldeón de RIMAC que maneja este tema de crónicos pero no logré respuesta. Quedo atenta a sus noticias. | L6: NO ASIGNACIÓN DE CITA | M6: PACIENTE CRONICO | N6: HIPOTIROIDISMO | O6: 45727 | S6: ACTIVA
A7: DNI | B7: 46674191 | C7: VERONICA ANDREA TAMARIZ VALENTIN | E7: 959354515 | I7: QUEJAS Y RECLAMOS | J7: ASEGURADOR | K7: Hola Guissela por favor un apoyo con este caso con la cliente que es paciente crónico de hipotiroidismo, el cual comenta que el nuevo proveedor que viene trabajando con aviva 1 A no esta siendo eficiente ya que ella es la que tiene que llamar, preguntar, preocuparse por todo y si no llaman no agilizan nada según comenta. Indica que debe tienen que sacarle cita para atención de laboratorio y una cita pendiente de su ultima atención. NOMBRES: VERONICA ANDREA TAMARIZ VALENTIN DNI: 46674191 CELULAR: 959354515 POLIZA: E0002545 | L7: NO ASIGNACIÓN DE CITA | M7: PACIENTE CRONICO | N7: HIPOTIROIDISMO | O7: 45728 | P7: NO FUE ATENDIDA | Q7: 27/03/2025 2:10 PM VIVA 1A CENTRO MEDICO PERU Gerson Jacob Siura Trevejo Trevejo ENDOCRINOLOGÍA - TELECONSULTA FACTURADA 25/03/2025 | S7: ACTIVA
A8: DNI | B8: 6040784 | C8: JULIO RAFAEL MARTIN CAMPOS | E8: 997500213 | F8: rafomartincampos@gmail.com | I8: QUEJAS Y RECLAMOS | J8: ASEGURADOR | K8: Buenas tardes. Por favor su apoyo en coordinación de cita de clientes VIP que se encuentran en programa ESTAR VITAL. Favor de enviar mensaje por WhatsApp antes de llamar para que pueda contestar llamada, cliente tiene bloqueo SPAM y tiene que agregar a sus contactos para que le permita la recepción de llamadas. Cliente usualmente tiene las citas los primeros días, sin embargo, hasta el momento no lo contactan y se encuentra crítico, porque siempre tiene que reportar para que se pueda agendar su cita y entrega de medicamentos. Nombre: JULIO RAFAEL MARTIN CAMPOS DNI: 06040784 CEL CONTACTO:997500213 CORREO: rafomartincampos@gmail.com DIAGNOSTICO: DISLIPIDEMIA Nombre: MARIANA SOLE VARGAS DNI: 08275667 CEL CONTACTO:997500213 CORREO: rafomartincampos@gmail.com DIAGNOSTICO: HIPOTIROIDISMO, ARTROSIS, MIGRAÑA, OSTEOPOROSIS | L8: NO ASIGNACIÓN DE CITA | M8: PACIENTE CRONICO | N8: DISLIPIDEMIA | O8: 45728 | P8: NO FUE ATENDIDA | Q8: 13/03/2025 7:15 PM VIVA 1A CENTRO MEDICO PERU Antonio David Moncada Catalan MEDICA FAMILIAR - TELECONSULTA PROCESADO | S8: ACTIVA
A9: DNI | B9: 8275667 | C9: MARIANA SOLE VARGAS | E9: 997500213 | F9: rafomartincampos@gmail.com | I9: QUEJAS Y RECLAMOS | J9: ASEGURADOR | K9: Buenas tardes. Por favor su apoyo en coordinación de cita de clientes VIP que se encuentran en programa ESTAR VITAL. Favor de enviar mensaje por WhatsApp antes de llamar para que pueda contestar llamada, cliente tiene bloqueo SPAM y tiene que agregar a sus contactos para que le permita la recepción de llamadas. Cliente usualmente tiene las citas los primeros días, sin embargo, hasta el momento no lo contactan y se encuentra crítico, porque siempre tiene que reportar para que se pueda agendar su cita y entrega de medicamentos. Nombre: JULIO RAFAEL MARTIN CAMPOS DNI: 06040784 CEL CONTACTO:997500213 CORREO: rafomartincampos@gmail.com DIAGNOSTICO: DISLIPIDEMIA Nombre: MARIANA SOLE VARGAS DNI: 08275667 CEL CONTACTO:997500213 CORREO: rafomartincampos@gmail.com DIAGNOSTICO: HIPOTIROIDISMO, ARTROSIS, MIGRAÑA, OSTEOPOROSIS | L9: NO ASIGNACIÓN DE CITA | M9: PACIENTE CRONICO | N9: HIPOTIROIDISMO | O9: 45728 | P9: NO FUE ATENDIDA | Q9: FUE ATENDIDA 13/03/2025 7:00 PM VIVA 1A CENTRO MEDICO PERU Antonio David Moncada Catalan MEDICA FAMILIAR – TELECONSULTA | S9: ACTIVA
A10: DNI | B10: 44841514 | C10: CARINA MIRANDA LAZO | I10: QUEJAS Y RECLAMOS | J10: ASEGURADOR | K10: Buenas tardes Kenny / Kaila Solicito su gentil apoyo, cliente en mención cuenta con diabetes , se atiende en el programa CUIDATE, que era con STARVITAL, le informaron que lo contactarían para poder coordinar la cita médica programada, y la entrega de su medicina con el nuevo proveedor. Sin embargo, al momento no recibe comunicación, ni confirmación de la nueva cita. Indica necesitar sus medicinas de manera urgente por los diagnósticos que presenta .Adicional a ello indica que por favor se comuniquen vía WhatsApp ya que no responde teléfonos no registrados | L10: NO ASIGNACIÓN DE CITA | M10: CUIDATE | N10: NO ESPECIFICA | O10: 45735 | P10: NO FUE ATENDIDA | Q10: FUE ATENDIDA 20/03/2025 7:45 PM VIVA 1A CENTRO MEDICO PERU Gerson Jacob Siura Trevejo Trevejo ENDOCRINOLOGÍA - TELECONSULTA PROCESADO 17/03/2025 GADIAZHUAJAN CONFIRMACION DE CITA | S10: ACTIVA
B11: 7806297 | C11: VICTOR BARUA ALZAMORA | I11: QUEJAS Y RECLAMOS | J11: ASEGURADOR | K11: Estimada Guissela El 14 Feb 25 los señores de Viva A1 le brindaron la atencion medica al Sr. Fernando Barua Alzamora otorgando la medicación prescrita por el medico tratante por 30 dias. Es el caso que el control del mes Marzo debió ser el 15/03 hasta el día de hoy no se le ha brindado la atencion medica correspondiente por consiguiente no cuenta con medicación. El día de hoy he conversado con la Lic. Gianina Cigueñas quien me manifestó que la Dra. Anahis Seigas no le confirmaba la consulta, ya que ella estaba laborando en otro lugar. Que hacemos, por el estado de salud del Sr. Barua el no puede dejas de tomar su medicación, por eso requiero su apoyo a fin de que el día de hoy se le haga entrega de sus medicamentos. Esta situación no puede volver a repetirse, no pueden perjudicar de esta manera al asegurado, por lo que le solicito conversar con los señores de Viva A1 para que lleven un mejor control de las atenciones de los asegurados Quedo a la espera de su respuesta a lo solicitado. Saludos cordiales | L11: NO ASIGNACIÓN DE CITA | N11: NO ESPECIFICA | O11: 45736 | S11: ACTIVA
A12: DNI | B12: 42764761 | C12: HENRY WILLIAM CASTILLO JARA | G12: 25-EPS002420 | I12: QUEJAS Y RECLAMOS | J12: ASEGURADOR | K12: Buenas tardes estimados, Paciente de nuestro programa de enfermedades crónicas refiere que médico envió orden de lab. Anti TPO hace 2 meses, pero hasta el momento no le han realizado el examen, su gentil apoyo en cobertura de ese examen solicitado por el Dr. Gerson Siura, y así pueda ser evaluado con los resultados en su próxima consulta médica, su gentil apoyo en revisión del caso, por favor. PX: HENRY WILLIAM CASTILLO JARA DNI: 42764761 DX: Hipotiroidismo Quedamos pendientes | L12: NO ASIGNACIÓN DE CITA | M12: PRESTADOR EXTERNO | N12: LABORATORIO | O12: 45740 | Q12: NO SE CUENTA CON INFORMACIÓN | S12: ACTIVA
A13: DNI | B13: 7823787 | C13: DINA RAQUEL QUIROZ VELASQUEZ | I13: QUEJAS Y RECLAMOS | J13: ASEGURADOR | K13: Katherine buenas tardes, Cliente se comunica porque quedaron en llamarle entre ayer y hoy para coordinar su cita (porque se inscribió el jueves de la semana pasada) y le indicaron que en 72 horas le llamarían, pero no se comunican con ella aún. Solicita apoyo para que le llamen y separar su cita. DINA RAQUEL QUIROZ VELASQUEZ DNI 07823787 DIAGNOSITO Dislipidemia - Hipertensión PÓLIZA E0002545 TELEFONO 988243995 Sls, | L13: NO ASIGNACIÓN DE CITA | N13: NO ESPECIFICA | O13: 45741 | P13: NO FUE ATENDIDA | Q13: 02/04/2025 9:30 AM VIVA 1A CENTRO MEDICO PERU Virginia Cuevas Rivero MEDICA FAMILIAR - TELECONSULTA PROCESADO 01/04/2025 | S13: ACTIVA
A14: DNI | B14: 25677282 | C14: ROXANA ESPERANZA TAVERA D ANGELO | E14: 991888565 | I14: QUEJAS Y RECLAMOS | J14: ASEGURADOR | K14: Hola Andrés, gracias por tu llamada. Paso a comentarte lo sucedido con mi atención como Paciente del Programa Cuídate de Rimac. Me llamó la atención que no me llamaran para darme cita con el doctor, como todos los meses, y dijeron que ya no trabajaban con Rimac. Me contacté con ustedes y me asignaron a “Viva 1A”. Me dieron cita para el viernes 7 de marzo pasado. Me mandaron por mail mi receta de medicamentos y me mandaron hacer unos análisis. Hasta el lunes 10 nadie se había comunicado conmigo para coordinar entrega de mis medicinas ni toma de análisis. Los teléfonos que tenía de “Viva 1A”, me contesta un Robot, tanto por teléfono como por WhatsApp, y como mi pregunta no estaba dentro de sus alternativas, colgaban. Luego que los molesté a ustedes, me llamaron y recién ayer miércoles, me entregaron mis medicamentos. Pero para los análisis aún no se contactan conmigo. Pongo estos comentarios para tomen la mejor decisión, en vista que no puedo estar sin tomar esas medicinas. Saludos, | L14: NO ASIGNACIÓN DE CITA | M14: PRESTADOR EXTERNO | N14: LABORATORIO | O14: 45741 | P14: CITA PENDIENTE | Q14: 04/04/2025 8:00 AM VIVA 1A CENTRO MEDICO PERU Virginia Cuevas Rivero MEDICA FAMILIAR - TELECONSULTA ACTIVO 01/04/2025- PTE SOLICITA LABORATORIOS PENDIENTES | S14: ACTIVA
C15: BASILIO ALFONSO CESARO STROBBE | I15: QUEJAS Y RECLAMOS | J15: ASEGURADOR | K15: Buenas tardes: Por favor, para su atención. 1. Contacto (Apellidos y Nombres) : CONSUELO ROCIO LORA DESCALZO DE CESARO 2. Número de Póliza y Certificado: E0028656 3. Mail : rocio.lora@gmail.com telefono: 990265336 4. Observación: paciente BASILIO ALFONSO CESARO STROBBE se atendio por ultima vez hace mas de un mes y quedo pendiente su evaluacion cardiologica | L15: NO ASIGNACIÓN DE CITA | N15: RIESGO CARDIOVASCULAR | O15: 45741 | S15: ACTIVA
A16: DNI | B16: 72844745 | C16: DIEGO VASQUEZ IGLESIAS | I16: SOLICITUD | J16: ASEGURADOR | K16: Estimados @quejasyreclamos@viva1a.com.pe@admisionrimac@viva1a.com.pe Por favor se requiere el descargo y la pronta atención del usuario referido. Buenos días: Por favor paciente pertenece al programa CUIDATE diagnóstico HIPERTENSION ARTERIAL y nos informa que no le envían sus medicinas desde hace dos meses. DNI:72844745 DIEGO ALEJANDRO VASQUEZ IGLESIAS TELEFONO: 954775445 CORREO: diegoiglesiasvasquez@gmail.com Póliza : EPS Atte. 31/03/2025 Lo que se encuentra pendiente de atención es: La programación de la cita de control médico presencial. La coordinación para la toma de exámenes de laboratorio de seguimiento. | L16: SOLICITUD DE CITA | M16: CUIDATE | N16: HIPERTENSION | O16: 45742 | P16: FUE ATENDIDA | Q16: 26/03/2025 6:00 PM VIVA 1A CENTRO MEDICO PERU Hilton D Jango Cruz CARDIOLOGIA - ATENCIÓN DOMICILIARIA PROCESADO 26/03/2025 GSIGUENAS INGRESO HTA MANTENER BETALOC | ILTUX | S16: ACTIVA
C17: LUZ VELASQUEZ MUÑOZ | E17: 982491420 | I17: SOLICITUD | J17: ASEGURADOR | K17: Hola Gissela, Agradeceré tu apoyo con el presente reclamo, paciente Luz Velasquez Muñoz indica que hasta el momento no puede atenderse a través del programa Cuidate. Por favor tu apoyo a fin de contactarse con la asegurada y puedan brindarle la información del programa. DATOS: Luz Angelica Velasquez Muñoz Celular: 982491420 Quedo atenta a tu pronta respuesta. Saludos, | L17: SOLICITUD DE CITA | M17: CUIDATE | N17: NO ESPECIFICA | O17: 45742 | S17: ACTIVA
B18: 71528818 | C18: VALERIA XIMENA AGUIRRE VALER | G18: 25-SBS013956 | I18: QUEJAS Y RECLAMOS | J18: LIBRO DE RECLAMOS ASEGURADOR | K18: "Asegura manifiesta su incomodidad debido a que lleva ya 7 llamadas en las cuales solicita un médico virtual y hasta el momento no tiene respuesta alguna. Recipen el proveedor menciona que a partir de las 2 pm van a poder atenderla. Adicional a ello, no esta conforme con el proveedor aviva para proximas atenciones requiere a la clínica internacional." | L18: NO ASIGNACIÓN DE CITA | N18: NO ESPECIFICA | O18: 45737 | S18: ACTIVA
A19: DNI | B19: 41411250 | C19: VICTOR ARCADIO BERNAL FUENTES | E19: 951303432 | H19: 24819056 | I19: SOLICITUD | J19: WHASTAPP | K19: FUE ATENDIDO EL 24/03 Y SOLICTA SEGUIMIENTO | L19: SOLICITUD DE CITA | M19: MEDICINA GENERAL | N19: MEDICINA GENERAL | O19: 45742 | P19: FUE ATENDIDA | Q19: 26/03/2025 9:30 AM VIVA 1A CENTRO MEDICO PERU Greduin Alexander Romero Bompart MEDICINA GENERAL – TELECONSULTA- PTE SOLICITA SEGUIMIENTO | S19: ACTIVA
A20: DNI | C20: KAORI DANIELA INGA BALDEON | E20: 992770160 | H20: 24838224 | I20: SOLICITUD | J20: WHASTAPP | K20: SOLICTA PROGRAMACION 3:30PM | L20: SOLICITUD DE CITA | M20: MEDICINA GENERAL | N20: MEDICINA GENERAL | O20: 45742 | S20: ACTIVA
A21: DNI | B21: 41247452 | C21: JOSE CARLOS FARFAN HUAMAN | E21: 915375368 | H21: 24838255 | I21: SOLICITUD | J21: WHASTAPP | K21: MEDICO NO INGRESO AL LINK | L21: NO ATENCION DE CITA PROGRAMADA | M21: MEDICINA GENERAL | N21: MEDICINA GENERAL | O21: 45742 | P21: FUE ATENDIDA | Q21: 26/03/2025 9:40 AM VIVA 1A CENTRO MEDICO PERU Lourdes Vanesa Molina Acurio MEDICINA GENERAL - TELECONSULTA CENTRO MÉDICO VIRTUAL PROCESADO 26/03/2025 DDELEON Cita oficina virtual RIMAC S.A EPS | S21: ACTIVA
A22: DNI | B22: 43454029 | C22: DANIEL CLAUDIO ORBEGOSO CANCHIS | E22: 997610020 | H22: 24837859 | I22: SOLICITUD | J22: WHASTAPP | K22: MEDICO NO INGRESO AL LINK | L22: NO ATENCION DE CITA PROGRAMADA | M22: MEDICINA GENERAL | N22: MEDICINA GENERAL | O22: 45742 | P22: FUE ATENDIDA | Q22: 26/03/2025 10:00 AM VIVA 1A CENTRO MEDICO PERU Lourdes Vanesa Molina Acurio MEDICINA GENERAL - TELECONSULTA CENTRO MÉDICO VIRTUAL FACTURADA 26/03/2025 GADIAZHUAJAN | S22: ACTIVA
A23: DNI | B23: 47623959 | C23: KATHERINE KELLY BALLENA LARA | E23: 997895326 | H23: 24838471 | I23: QUEJAS Y RECLAMOS | J23: WHASTAPP | K23: MEDICO NO INGRESO AL LINK | L23: NO ATENCION DE CITA PROGRAMADA | M23: MEDICINA GENERAL | N23: MEDICINA GENERAL | O23: 45742 | P23: FUE ATENDIDA | Q23: 26/03/2025 10:20 AM VIVA 1A CENTRO MEDICO PERU Lourdes Vanesa Molina Acurio MEDICINA GENERAL - TELECONSULTA CENTRO MÉDICO VIRTUAL PROCESADO 26/03/2025 | S23: ACTIVA
A24: DNI | B24: 41380020 | C24: JESSICA CAROLINA RAMOS LINARES | E24: 906868565 | H24: 24822103 | I24: SOLICITUD | J24: WHASTAPP | K24: ECIBIO ATENCION VIRTUAL HACE 48 HORAS PROVEEDOR VIVA, DESEA QUE LA LLAMEN PARA REALIZAR SEGUIMIENTO YA QUE PACIENTE AUN NO SE ENCUENTRA BIEN | L24: SOLICITUD DE CITA | M24: MEDICINA GENERAL | N24: MEDICINA GENERAL | O24: 45742 | P24: FUE ATENDIDA | Q24: FUE ATENDIDA EL 26/03/2025 HISTORIA CLINICA NO REGISTRA EN EVEREST | S24: ACTIVA
A25: DNI | B25: 47622115 | C25: DAVID EDUARDO GOMEZ BOLUARTE | E25: 949574468 | H25: 24838076 | I25: SOLICITUD | J25: WHASTAPP | K25: FUE ATENDIDO EL 26/03 REFIERE QUE AUN PERSITE DOLOR , SEGUIMIENTO CMV | L25: SOLICITUD DE CITA | M25: MEDICINA GENERAL | N25: MEDICINA GENERAL | O25: 45743 | P25: FUE ATENDIDA-SEGUIMIENTO | Q25: 26/03/2025 8:00 AM VIVA 1A CENTRO MEDICO PERU Lourdes Vanesa Molina Acurio MEDICINA GENERAL - TELECONSULTA CENTRO MÉDICO VIRTUAL PROCESADO PTE SOLICTA SEGUIMIENTO | S25: ACTIVA
A26: DNI | B26: 91040753 | C26: FRANCO GABRIEL RODRIGUEZ ALPACA | E26: 996714343 | H26: 24836654 | I26: SOLICITUD | J26: WHASTAPP | K26: FUE ATENDIDA 25/03 , PRESENTA REACCION ALERGICA | L26: SOLICITUD DE CITA | M26: MEDICINA ESPECIALIZADA | N26: PEDIATRIA | O26: 45743 | P26: FUE ATENDIDA-SEGUIMIENTO | Q26: 28/03/2025 8:55 PM VIVA 1A CENTRO MEDICO PERU Eliana Jose Jaramillo Del Valle PEDIATRÍA - TELECONSULTA CENTRO MÉDICO VIRTUAL PROCESADO 28/03/2025 PTE SOLICITA SEGUIMIENTO | S26: ACTIVA
A27: DNI | B27: 5887878 | C27: JOAQUIN TALLEDO CASTRE | E27: 998111946 | H27: 24847536 | I27: SOLICITUD | J27: WHASTAPP | K27: REPROGRAMACION | L27: SOLICITUD DE CITA | M27: MEDICINA ESPECIALIZADA | N27: PEDIATRIA | O27: 45743 | P27: FUE ATENDIDA | Q27: 27/03/2025 12:25 732148 0024850342 - JOAQUIN TALLEDO CASTRE SANTIAGO DE SURCO Médico Virtual Pediatría 27/03/2025 13:00 | S27: ACTIVA
A28: DNI | B28: 44632024 | C28: KRISTY JOYCE NEVELYN ARTEAGA MOYA | E28: 936628006 | H28: 24838101 | I28: SOLICITUD | J28: WHASTAPP | K28: AUN PERSITE LOS SINTOMAS | L28: SOLICITUD DE CITA | M28: MEDICINA ESPECIALIZADA | N28: MEDICINA GENERAL | O28: 45744 | P28: FUE ATENDIDA | Q28: 31/03/2025 4:40 PM VIVA 1A CENTRO MEDICO PERU Adriana Espinoza Hoempler MEDICINA GENERAL - TELECONSULTA CENTRO MÉDICO VIRTUAL ACTIVO 31/03/2025 | S28: ACTIVA
A29: DNI | B29: 79775077 | C29: KLAUS MITTERHOFER HARMSEN | E29: 945669028 | H29: 24855022 | I29: SOLICITUD | J29: WHASTAPP | K29: Madre de menor informa que su hijo persiste con tos y no le han dejado medicación para la toS.seguimiento | L29: SOLICITUD DE CITA | M29: MEDICINA ESPECIALIZADA | N29: MEDICINA GENERAL | O29: 45744 | P29: FUE ATENDIDA-SEGUIMIENTO | Q29: 31/03/2025 4:40 PM VIVA 1A CENTRO MEDICO PERU Adriana Espinoza Hoempler MEDICINA GENERAL - TELECONSULTA CENTRO MÉDICO VIRTUAL - | S29: ACTIVA
A30: DNI | B30: 76239331 | C30: ALYSON NICOL TOVAR ALCALA | E30: 940923302 | H30: 24857484 | I30: QUEJAS Y RECLAMOS | J30: WHASTAPP | K30: paciente con MV programado a las 10:20am refiere que medico no ingresa a link. | L30: NO ATENCION DE CITA PROGRAMADA | N30: NO ESPECIFICA | O30: 45744 | P30: FUE ATENDIDA | Q30: 28/03/2025 11:10 AM VIVA 1A CENTRO MEDICO PERU Marciel Espinoza Noguera MEDICINA GENERAL - TELECONSULTA CENTRO MÉDICO VIRTUAL FACTURADA 28/03/2025 | S30: ACTIVA
A31: DNI | B31: 46603235 | C31: JOANA CRISTINA RAYGADA RISCO | I31: SOLICITUD | J31: ASEGURADOR | K31: Su urgente apoyo con atender el requerimiento de la usuaria. Buenas tardes estimados, Se verifica que la paciente tuvo consulta el 10/03 con el Dr. Moncada. No obstante, recientemente ha sido informada de su embarazo. Siguiendo la recomendación de su ginecóloga, se ha indicado que consulte con su médico tratante del programa Cuídate, debido a su diagnóstico de hipertensión arterial (HTA), con el fin de evaluar la continuidad de su tratamiento farmacológico. Por lo que se brinda el visto bueno para proceder con la reevaluación del médico tratante del programa a la brevedad posible de manera excepcional, de antemano gracias por el apoyo. | L31: SOLICITUD DE CITA | M31: CRONICOS | N31: HIPERTENSION | O31: 45744 | P31: NO FUE ATENDIDA | Q31: NO FUE ATENDIDA | S31: ACTIVA
A32: DNI | B32: 9994334 | C32: ANA GABRIELA CHAVEZ VARGAS | E32: 989640563 | I32: QUEJAS Y RECLAMOS | J32: ASEGURADOR | K32: Estimados buenos días, se acaba de comunicar conmigo la señora ANA CHAVEZ, quien indica que hasta ahorita no la llaman para poder generar sus exámenes de laboratorio y que cuando escribe al número de whatssap solo le responde una bot. Por favor su apoyo para poder llamara lo antes posible. TLF: 989 640 563 | L32: NO ASIGNACIÓN DE CITA | M32: PRESTADOR EXTERNNO | N32: LABORATORIO | O32: 45747 | S32: ACTIVA
A33: DNI | B33: 7218366 | C33: GLADYS PATRICIA GUTIERREZ VELEZMORO | I33: QUEJAS Y RECLAMOS | J33: ASEGURADOR | K33: RIMAC VIP//PROGRAMA CRONICOS REUMATOLOGIA//GLADYS PATRICIA GUTIERREZ VELEZMORO | L33: NO ASIGNACIÓN DE CITA | M33: CRONICOS | N33: REUMATOLOGIA | O33: 45716 | P33: PROGRAMA CRONICOS | S33: ACTIVA
A34: DNI | B34: 8287353 | C34: LEON MAGNO SANCHEZ QUINTANILLA | I34: QUEJAS Y RECLAMOS | J34: ASEGURADOR | K34: programa cuídate / LEON MAGNO SANCHEZ QUINTANILLA | L34: NO ASIGNACIÓN DE CITA | M34: CUIDATE | N34: NO ESPECIFICA | O34: 45716 | P34: PROGRAMA CRONICOS | S34: ACTIVA
A35: DNI | B35: 44000062 | C35: LLAMOJA VICENTE DENNISE | I35: QUEJAS Y RECLAMOS | J35: ASEGURADOR | K35: CUIDATE- PROGRAMA CRONICO | L35: NO ASIGNACIÓN DE CITA | M35: CUIDATE | N35: NO ESPECIFICA | O35: 45716 | P35: PROGRAMA CRONICOS | S35: ACTIVA
C36: POTENCIALES AL PROGRAMA CUIDATE Y OTROS CRONICOS-SURA /RIESGO | I36: SOLICITUD | J36: ASEGURADOR | K36: POTENCIALES AL PROGRAMA CUIDATE Y OTROS CRONICOS-SURA /RIESGO | L36: SOLICITUD DE CITA | M36: CUIDATE | N36: NO ESPECIFICA | O36: 45712 | S36: ACTIVA
A37: DNI | B37: 9876517 | C37: Victor Edgar Solis Plaza | I37: QUEJAS Y RECLAMOS | J37: ASEGURADOR | K37: REFINERIA LA PAMPILLA / EPS N° E0001009 / ASEGURADO: Victor Edgar Solis Plaza / RECLAMO URGENTE | L37: NO ASIGNACIÓN DE CITA | N37: NO ESPECIFICA | O37: - | P37: PROGRAMA CRONICOS | S37: ACTIVA
A38: DNI | B38: 8170776 | C38: NILTON HERMAN JIMENEZ ROSALES | I38: SOLICITUDES | J38: ASEGURADOR | K38: CONTINUDAD DE TERAPIAS FISICAS USUARIO NILTON HERMAN JIMENEZ ROSALES DNI:08170776 -DIAMANTE | L38: SOLICITUD DE CITA | M38: TERAPIAS | N38: TERAPÍA FISICA | O38: 45734 | P38: PROGRAMA CRONICOS | S38: ACTIVA
A39: DNI | B39: 72154157 | C39: FIORELLA CRISEL VERGARA OLIVO | I39: QUEJAS Y RECLAMOS | J39: ASEGURADOR | K39: CONDICIONES DE CONTRATO CON EL PRESTADOR PARA ATENCION A PACIENTE EN MENCION | L39: NO ASIGNACIÓN DE CITA | N39: NO ESPECIFICA | O39: 45733 | P39: PROGRAMA CRONICOS | S39: ACTIVA
A40: DNI | B40: 72845505 | C40: FABRICIO ANDRE MORALES HERNANDEZ | I40: QUEJAS Y RECLAMOS | J40: ASEGURADOR | K40: URGENTE !!!CONFIRMACIÓN DE ATENCIÓN DE USUARIO MORALES HERNANDEZ FABRICIO ANDRE DNI 72845505-REDONDOS | L40: NO ASIGNACIÓN DE CITA | N40: NO ESPECIFICA | O40: 45730 | P40: PROGRAMA CRONICOS | S40: ACTIVA
A41: DNI | B41: 7731756 | C41: Laura La Serna Garcia | I41: QUEJAS Y RECLAMOS | J41: ASEGURADOR | K41: Su gentil apoyo se requiere el descargo y medidas correctivas en cuanto el reclamo indicado por la usuaria referida. 2 Estaba en el plan de otras enfermedades cronicas - hipotiroidismo, pero la reserva de cita y examenes, tenia que estar llamando al provedor, en diciembre se olvidaron y no llegaron a comunicarse conmigo. En febrero cambiaron de proveedor y tambien tuve que estar llamando por la cita medica porque se estaba terminando mi medicacion. Luego me llamaron y me indicaron que no podian darme la medicacion para el colesterol alto que mi plan no cubria, habiando estado llevando varios meses la misma medicacion, asi que me han cambiado de plan ahora estoy en deslipidemia. Este plan era muy bueno al principio, porque se tiene atencion medica, medicamentos y analisis de laboratorio, espero que el nuevo proveedor mejore No son consultas propiamente dicha pero me ha pasado.” Estimada @Denisse Llamoja Vicente Por favor adjuntar el N° de Dni de la usaría referida. | L41: NO ASIGNACIÓN DE CITA | M41: CRONICOS | N41: DISLIPIDEMIA | O41: 45726 | P41: PROGRAMA CRONICOS | S41: ACTIVA
A42: DNI | B42: 42413293 | C42: Julissa Fabiola Gómez Paz | I42: QUEJAS Y RECLAMOS | J42: ASEGURADOR | K42: PROGRAMA CUIDATE// EPS RIMAC//Julissa Fabiola Gómez Paz//Hipertensión arterial | L42: SOLICITUD DE CITA | M42: CUIDATE | N42: HIPERTENSION | O42: 45728 | P42: PROGRAMA CRONICOS | S42: ACTIVA
C43: PACIENTES CRONICOS - GRUPO CARVAJAL - E0037430, E0037415, E0037416, E0037420 | I43: SOLICITUD | J43: ASEGURADOR | K43: PACIENTES CRONICOS - GRUPO CARVAJAL - E0037430, E0037415, E0037416, E0037420 | L43: SOLICITUD DE CITA | M43: CRONICOS | N43: NO ESPECIFICA | O43: 45728 | S43: ACTIVA
C44: INVITACION PACIENTES CRONICOS - HORTUS | I44: SOLICITUD | J44: ASEGURADOR | K44: INVITACION PACIENTES CRONICOS - HORTUS | L44: SOLICITUD DE CITA | M44: CRONICOS | N44: NO ESPECIFICA | O44: 45728 | S44: ACTIVA
C45: EMPRESA SAPET / ACTUALIZACION | I45: SOLICITUD | J45: ASEGURADOR | K45: URGENTE : Programa PPC / URGENTE / EMPRESA SAPET / ACTUALIZACION | L45: SOLICITUD DE CITA | N45: NO ESPECIFICA | O45: 45727 | S45: ACTIVA
C46: Zhu Lei | I46: QUEJAS Y RECLAMOS | J46: ASEGURADOR | K46: URGENTE _ Proveedor Viva 1A y Pacientes Crónicos | L46: NO ASIGNACIÓN DE CITA | M46: CRONICOS | N46: NO ESPECIFICA | O46: 45729 | S46: ACTIVA
A47: DNI | B47: 7636877 | C47: MARIA DEL CARMEN CARRASCO PANTA | G47: 25-EPS002484 | I47: QUEJAS Y RECLAMOS | J47: LIBRO DE RECLAMOS ASEGURADOR | K47: Estimada Carmen Se ha validado que la usuaria se encuentra inscrita actualmente en el Programa de Artritis, pero no está registrada en el Programa Cuídate por diagnóstico de Asma. Estimados @quejasyreclamos@viva1a.com.pe@admisionrimac@viva1a.com.pe@gsiguenas@viva1a.com.pe Solicitamos su urgente apoyo con el pronto contacto a la usuaria referida, quien se encuentra pendiente de atención por el diagnóstico de Artritis. Durante la próxima atención médica, el profesional tratante deberá realizar la caracterización clínica para el diagnóstico de Asma. En caso de que se confirme dicho diagnóstico, se deberá ejecutar la cobertura bajo el esquema de RCV Continuador, conforme a lo siguiente: Asma: cobertura al 100% Artritis: cobertura al 85% ----Buenos días Guissela, Tenemos el reclamo presentado por MARIA DEL CARMEN CARRASCO PANTA – DNI 07636877, paciente del programa crónico y hasta la fecha no recibe programación de cita con VIVA 1A. Asimismo, tiene pendiente cita del programa cuidate por asma. Por favor tu apoyo para notificarlo al proveedor y se concreten las citas. RECLAMO: Soy paciente de programa crónico por artritis, a la fecha via uno no me programa la cita, no voy a tener medicación del mes. Les he escrito al cell 942772650 que es el robot para programar citas y me dice que no puede procesar mi solicitud. He escrito al 942772654 que es de Gianina Sigueñas de Viva Uno y tampoco me contestan. Quiero interponer un reclamo porque me estoy quedando sin cita del mes, no tendré pastillas y soy paciente crónica, también me tienen pendiente la cita del programa cuidate por asma. cel 954645306. Gracias de antemano. Saludos, | L47: NO ASIGNACIÓN DE CITA | M47: CRONICOS | N47: ARTRITIS | O47: 45747 | P47: PROGRAMA CRONICOS | S47: ACTIVA
A48: DNI | B48: 19182849 | C48: Cecilia mercedes carrera de Gutiérrez | E48: 956923666 | F48: ceciliacarrera40@gmail.com | I48: SOLICITUD | J48: ASEGURADOR | K48: Estimadas, buen día: Por favor su especial apoyo con asegurada en referencia. Se requiere contactar a paciente para agendamiento de ECO - ECOCARDIOGRAMA y Holter. Adjunto datos de paciente: Paciente: CARRERA DE GUTIERREZ CECILIA MERCEDES DNI: 19182849 Celular: 956923666 Correo: ceciliacarrera40@gmail.com Cobertura: con copago del 15% Por favor remitir resultados en respuesta del presente correo. Saludos Cordiales, | L48: SOLICITUD DE CITA | M48: PROCEDIMIENTO | N48: CARDIOLOGIA | O48: 45748 | P48: PROGRAMA CRONICOS | S48: ACTIVA
A49: DNI | B49: 40204963 | C49: OLGA TATIANA CUADROS BASIS | E49: 999203060 | I49: SOLICITUD | J49: ASEGURADOR | K49: Estimado @Freddy Garzón Su urgente apoyo con el pronto contacto de la usuaria referida quien solicita manejo de terapia del dolor. Atte. GUISSELA M. BEDÓN ESPINOZA | L49: SOLICITUD DE CITA | M49: TERAPIA | N49: NO ESPECIFICA | O49: 45748 | P49: PROGRAMA CRONICOS | S49: ACTIVA
A50: DNI | B50: 6934099 | C50: JULIA DAMIANA MORENO TOSCANO | E50: 930873560 | I50: SOLICITUD | J50: ASEGURADOR | K50: Buenas tardes estimada Srta. Gomez Para informar que asegurada se encuentra dentro de programa crónicos refiere que le han solicitado exámenes de laboratorio el 25 /03 proveedor viva 1a pero hasta el momento no se han comunicado , solicita comunicación. Paciente : Julia Damiana Moreno Toscano edad: 63 años DNI : 06934099 Cel: 930873560 Atte. Yesenia Malca | L50: NO ASIGNACION DE CITA | M50: PRESTADOR EXTERNO | N50: LABORATORIO | O50: 45748 | P50: PROGRAMA CRONICOS | S50: ACTIVA

Sheet Archivo data rimac reclamos
A1: Fecha de Ingreso del Reclamo | B1: DNI | C1: Tenor del correo | D1: CRUCE | E1: Tipo de Reclamo | F1: Se envio correo de respuesta | G1: Fecha de solución reclamo | H1: Estado | I1: Fecha de cita | J1: Medicamentos | K1: Fecha de Entreda de Medicamentos | L1: Laboratorio | M1: Fecha de Realización de examen | N1: OBSERVACIONES | O1: Se contestó correo | P1: Fecha
A2: 45716 | B2: 9150324 | C2: URGENTE // RIMAC VIP // VERONICA PAOLA ROSSADO ESPINOZA // 09150324 // CONSULTA PROVEEDOR REEMPLAZO STARVITAL | D2: =VLOOKUP(B2,'DATA CORREO'!G:P,7,0) -> 0 | E2: DEMORA ENTREGA DE MEDICAMENTOS | F2: SI | G2: 45726 | H2: CITADO | I2: 45710 | J2: SI | L2: SI | O2: SI | P2: 45726
A3: 45709 | B3: 7258840 | C3: asegurada JOHANNA MYLENA BENDEZU DEL CASTILLO | D3: =VLOOKUP(B3,'DATA CORREO'!G:P,7,0) -> 0 | E3: DEMORA PROGRAMACIÓN DE CITA | F3: SI | G3: 45726 | H3: CITADO | I3: 45713 | J3: SI | L3: SI | N3: DEMORA EN PROGRAMACION DE CITA Y LABORATORIOS | O3: SI | P3: 45726
A4: 45716 | B4: 9596244 | C4: RIMAC VIP// CONSULTA// GIRELA MILAGROS GOMEZ LAZO | D4: =VLOOKUP(B4,'DATA CORREO'!G:P,7,0) -> #N/A | E4: DEMORA PROGRAMACIÓN DE CITA | F4: SI | G4: 45726 | H4: CITADO | I4: 45716 | J4: SI | L4: SI | O4: SI | P4: 45726
A5: 45714 | B5: 8612965 | C5: CASO URGENTE - DISCAPACIDAD - ELECTROPERU_ ABARCA HUARCAYA PRIMITIVA MARGARITA / ENTREGA DE MEDICINAS / URGENTE | D5: =VLOOKUP(B5,'DATA CORREO'!G:P,7,0) -> #N/A | E5: DEMORA PROGRAMACIÓN DE CITA | F5: SI | G5: 45726 | N5: Hija de paciente no acepta oferta, se comunicó el 20/02 | O5: SI | P5: 45726
A6: 45716 | B6: 8612544 | C6: Cliente sin medicinas - No entrega aún/GLORIA MARIA OBREGON CHAVEZ con DNI 08612544 | D6: =VLOOKUP(B6,'DATA CORREO'!G:P,7,0) -> 0 | E6: DEMORA ENTREGA DE MEDICAMENTOS | H6: CITADO | I6: 45705 | J6: SI | L6: NO
A7: 45714 | B7: 46840554 | C7: RECLAMO VIVA A1//ELLIS ORTIZ MARJORIE GRETTEL//OPERADORA DE SERVICIOS LOGISTICOS S.A.C.//HIPOTIROIDISMO | D7: =VLOOKUP(B7,'DATA CORREO'!G:P,7,0) -> 0 | E7: DEMORA ENTREGA DE MEDICAMENTOS | H7: CITADO | I7: 45701 | L7: NO | N7: COBRO INDEBIDO DE LABORATORIOS
A8: 45714 | B8: 8644487 | C8: RIMAC VIP -PROGRAMA CUIDATE - MAGLORIA NARCISA JULCA VEGA | D8: =VLOOKUP(B8,'DATA CORREO'!G:P,7,0) -> #N/A | E8: DEMORA PROGRAMACIÓN DE CITA | N8: CONFIRMACION DE ATENCION EJECUTADA se intento llamar ala pcte al numero proporcionado por rimac sin respuesta alguna , se deja mensaje de whattsapp
A9: 45714 | B9: 10127898 | C9: RIMAC VIP// PROGRAMA VIVA 1A//EBER CASTAÑEDA MAYTA | D9: =VLOOKUP(B9,'DATA CORREO'!G:P,7,0) -> #N/A | E9: DEMORA PROGRAMACIÓN DE CITA | H9: CITADO | I9: 45719 | J9: SI | L9: NO | N9: Se agendo la cita , sin embargo pcte no paso la consulta
A10: 45716 | B10: 2638270 | C10: Asunto: INSCRIPCIÓN PROGRAMA CUIDATE -LUIS FERNANDO REYES AREVALO | D10: =VLOOKUP(B10,'DATA CORREO'!G:P,7,0) -> #N/A | E10: DEMORA PROGRAMACIÓN DE CITA | N10: CONFIRMACION DE ATENCION EJECUTADA se intento llamar ala pcte al numero proporcionado por rimac sin respuesta alguna , se deja mensaje de whattsapp
A11: 45716 | B11: 8714637 | C11: PACIENTE DE PROGRAMA CUIDATE- URGENTE **PACIENTE CATTER COSSIO CLAUDIA NATALIA 04-85620 | D11: =VLOOKUP(B11,'DATA CORREO'!G:P,7,0) -> 0 | E11: DEMORA PROGRAMACIÓN DE CITA | H11: CITADO | I11: 45715 | J11: SI | L11: SI
A12: 45716 | B12: 7218366 | C12: RIMAC VIP//PROGRAMA CRONICOS REUMATOLOGIA//GLADYS PATRICIA GUTIERREZ VELEZMORO | D12: =VLOOKUP(B12,'DATA CORREO'!G:P,7,0) -> 0 | E12: DEMORA PROGRAMACIÓN DE CITA | H12: CITADO | I12: 45719 | J12: SI | L12: SI
A13: 45716 | B13: 8146369 | C13: PROGRAMA CUIDATE DEL PX MARROQUIN DEZA IVOR PAUL | D13: =VLOOKUP(B13,'DATA CORREO'!G:P,7,0) -> 0 | E13: DEMORA PROGRAMACIÓN DE CITA | N13: CONFIRMACION DE ATENCION EJECUTADA
A14: 45716 | B14: 8287353 | C14: programa cuídate / LEON MAGNO SANCHEZ QUINTANILLA | D14: =VLOOKUP(B14,'DATA CORREO'!G:P,7,0) -> 0 | E14: DEMORA ENTREGA DE MEDICAMENTOS | H14: CITADO | I14: 45710 | J14: SI | L14: SI
A15: 45716 | B15: 3684166 | C15: INSCRIPCION PARA EL PROGRAMA CUIDATE PX DIEGO VILLANUEVA RUIZ | D15: =VLOOKUP(B15,'DATA CORREO'!G:P,7,0) -> 0 | E15: DEMORA PROGRAMACIÓN DE CITA | N15: CONFIRMACION DE ATENCION EJECUTADA
A16: 45716 | B16: 40204963 | C16: RIMAC VIP/ ENVÍO DE MEDICAMENTOS DE PROGRAMA CRÓNICO/ OLGA TATIANA CUADROS BASIS | D16: =VLOOKUP(B16,'DATA CORREO'!G:P,7,0) -> 0 | E16: DEMORA ENTREGA DE MEDICAMENTOS | F16: SI | G16: 45726 | H16: CITADO | I16: 45712 | J16: SI | L16: NO | O16: SI | P16: 45726
A17: 45716 | B17: 18132161 | C17: RIMAC VIP // Inscripción - Otras enfermedades crónicas por Hipotiroidismo // OMAR RENATO RODRIGUEZ MURGA | D17: =VLOOKUP(B17,'DATA CORREO'!G:P,7,0) -> #N/A | E17: DEMORA PROGRAMACIÓN DE CITA | N17: CONFIRMACION DE ATENCION EJECUTADA
A18: 45715 | B18: 46699558 | C18: AFILIACION PROGRAMA CUIDATE // CI LIMA // YURIKO CORTES RODRIGUEZ 992375194 | D18: =VLOOKUP(B18,'DATA CORREO'!G:P,7,0) -> 0 | E18: DEMORA PROGRAMACIÓN DE CITA | N18: CONFIRMACION DE ATENCION EJECUTADA
A19: 45719 | C19: URGENTE!!!INFORMACIÓN PARA ELABORACIÓN DE FLYER DE CNPSC | D19: =VLOOKUP(B19,'DATA CORREO'!G:P,7,0) -> #N/A | N19: 1. ANS de tiempo de respuesta en la entrega de medicamentos, programación de citas, programación toma de muestras. 2. Canales de entrega de medicamentos disponibles. 3. Proceso de entrega de medicamentos (pasos detallados). 4. Procedimiento de toma de laboratorio (requisitos y flujo operativo).
A20: 45719 | B20: 8799045 | C20: RIMAC VIP // CONSULTA PROGRAMA CUIDATE // GIOVANNA MARIA LUZ VALEGA DURAND// CLIENTE CRÍTICA | D20: =VLOOKUP(B20,'DATA CORREO'!G:P,7,0) -> #N/A | E20: DEMORA PROGRAMACIÓN DE CITA | N20: CONFIRMACION DE ATENCION EJECUTADA
A21: 45719 | B21: 46083004 | C21: URGENTE - RIMAC - PROGRAMA CUIDATE EPS | D21: =VLOOKUP(B21,'DATA CORREO'!G:P,7,0) -> 0 | E21: DEMORA PROGRAMACIÓN DE CITA | H21: CITADO | I21: 45720 | J21: SI | L21: NO | N21: PX. NADIA NATALIE SOLANO DELGADO
A22: 45719 | B22: 78642647 | C22: Consulta atencion Pcte: MARCELO ALONSO LOREDO RAMIREZ | D22: =VLOOKUP(B22,'DATA CORREO'!G:P,7,0) -> 0 | E22: DEMORA PROGRAMACIÓN DE CITA | H22: CITADO | I22: 45723 | J22: SI | L22: SI
A23: 45719 | B23: 8783626 | C23: URGENTE /ATENCION ESTAR VITAL - GLORIA DURAND DE VALEGA - NESTLE JUBILADOS | D23: =VLOOKUP(B23,'DATA CORREO'!G:P,7,0) -> 0 | E23: DEMORA PROGRAMACIÓN DE CITA | H23: CITADO | I23: 45720 | J23: SI | L23: NO
A24: 45719 | B24: 8249657 | C24: PACIENTE DEL PROGRAMA CUIDATE PENDIENTE ENTREGA DE SUS MEDICAMENTOS /FARA NOEMI MIRANDA PACHECO DE CHOY DNI :08249657 | D24: =VLOOKUP(B24,'DATA CORREO'!G:P,7,0) -> 0 | E24: DEMORA ENTREGA DE MEDICAMENTOS | H24: CITADO | I24: 45707 | J24: SI | L24: NO
A25: 45720 | B25: 30849054 | C25: URGENTE - PROGRAMA CUIDATE // RICARDO ARTURO NUÑEZ RODRIGO // E0001394 | D25: =VLOOKUP(B25,'DATA CORREO'!G:P,7,0) -> 0 | E25: DEMORA ENTREGA DE MEDICAMENTOS | H25: CITADO | I25: 45721 | J25: SI | L25: NO
C26: CUIDATE- PROGRAMA CRONICO/DENNISE LLAMOJA VICENTE | D26: =VLOOKUP(B26,'DATA CORREO'!G:P,7,0) -> #N/A
A27: 45722 | B27: 7777013 | C27: Campbell Gianella Cindy Lee // DNI 07777013 // Póliza Ami Salud De Oro Nro 07-5503 /Programa ENDOCRINO // URGENTE ATENCION | D27: =VLOOKUP(B27,'DATA CORREO'!G:P,7,0) -> 0 | E27: DEMORA ENTREGA DE MEDICAMENTOS | H27: CITADO | I27: 45722 | J27: SI | L27: SI
C28: URGENTE - ENTREGA DE MEDICAMENTO - ERNESTO BENITES | D28: =VLOOKUP(B28,'DATA CORREO'!G:P,7,0) -> #N/A | E28: DEMORA ENTREGA DE MEDICAMENTOS
A29: 45721 | B29: 40157495 | C29: CASO PX LUCY YOVANI URIARTE CARRASCO | D29: =VLOOKUP(B29,'DATA CORREO'!G:P,7,0) -> 0 | E29: DEMORA EN PROGRAMACIÓN DE TOMA DE MUESTRAS | H29: CITADO | I29: 45692 | J29: SI | L29: SI
A30: 45721 | B30: 6934099 | C30: Programa Crónicos - Julia Damiana Moreno Toscano// PENDIENTE CITA | D30: =VLOOKUP(B30,'DATA CORREO'!G:P,7,0) -> 0 | E30: DEMORA PROGRAMACIÓN DE CITA | H30: CITADO | I30: 45741 | N30: PENDIENTE AGENDAMIENTO
A31: 45721 | B31: 7135754 | C31: RIMAC VIP // CONSULTA EXAMEN DE LABORATORIO // LUIS CARDENAS LUCERO | D31: =VLOOKUP(B31,'DATA CORREO'!G:P,7,0) -> 0 | E31: DEMORA EN PROGRAMACIÓN DE TOMA DE MUESTRAS | H31: CITADO | I31: 45702 | J31: SI | L31: SI
A32: 45721 | B32: 6225297 | C32: URGENTE - PROGRAMA CUIDATE / RAUL EDUARDO JARAMILLO GOMEZ / DNI 06225297 | D32: =VLOOKUP(B32,'DATA CORREO'!G:P,7,0) -> 0 | E32: DEMORA ENTREGA DE MEDICAMENTOS | H32: CITADO | I32: 45720 | J32: SI | L32: NO
A33: 45721 | B33: 25443941 | C33: RECLAMO 25-EPS002246 // ANGEL HERMOZA SALAS | D33: =VLOOKUP(B33,'DATA CORREO'!G:P,7,0) -> 0 | E33: DEMORA PROGRAMACIÓN DE CITA | F33: SI | G33: 45727 | H33: CITADO | I33: 45727 | J33: P | L33: P | N33: NoCONTESTA EL TELEFONO, SE PROCEDE A DEJAR MENSAJE DE WHATSAP | O33: SI | P33: 45727
A34: 45716 | B34: 8160842 | C34: REMITO INFORMACION PARA SER CONSIDERADA EN EL PROGRAMA CUIDATE DE RIMAC EPS | D34: =VLOOKUP(B34,'DATA CORREO'!G:P,7,0) -> 0 | E34: DEMORA PROGRAMACIÓN DE CITA | H34: CITADO | I34: 45721 | J34: SI | L34: NO | N34: Px. Yolanda Yesenia Milagros Yacila Cuya de Valdivia
A35: 45721 | B35: 29561921 | C35: REVISION ASEGURADO : ALVAREZ MONGE LELIA DNI : 29561921 - MINSUR | D35: =VLOOKUP(B35,'DATA CORREO'!G:P,7,0) -> 0 | E35: DEMORA PROGRAMACIÓN DE CITA | H35: CITADO | I35: 45721 | J35: SI | L35: NO | N35: CONFIRMACION DE ATENCION EJECUTADA
A36: 45721 | B36: 25443941 | C36: RECLAMO 25-EPS002246 // ANGEL HERMOZA SALAS | D36: =VLOOKUP(B36,'DATA CORREO'!G:P,7,0) -> 0 | E36: DEMORA PROGRAMACIÓN DE CITA | N36: NoCONTESTA EL TELEFONO, SE PROCEDE A DEJAR MENSAJE DE WHATSAP
A37: 45722 | B37: 77742062 | C37: PACIENTE DEL PROGRAMA CUIDATE /EDGAR IGNACIO DE LA TORRE RODRIGUEZ DNI :77742062 | D37: =VLOOKUP(B37,'DATA CORREO'!G:P,7,0) -> 0 | H37: CITADO | I37: 45721 | J37: SI | L37: NO
A38: 45716 | B38: 25791542 | C38: URGENTE RIMAC VIP / INSCRIPCION PROGRMA CUIDATE / CARLOS ALBERTO CHIRICHIGNO MENA | D38: =VLOOKUP(B38,'DATA CORREO'!G:P,7,0) -> 0 | E38: DEMORA PROGRAMACIÓN DE CITA | H38: CITADO | I38: 45730 | N38: Queda agendado
A39: 45721 | B39: 9994334 | C39: cuidate// endocrinología//CHAVEZ VARGAS, ANA GABRIELA //ADMINISTRACION FOOD REGIONAL S.A.C. | D39: =VLOOKUP(B39,'DATA CORREO'!G:P,7,0) -> 0 | E39: DEMORA PROGRAMACIÓN DE CITA | H39: CITADO | I39: 45722 | J39: SI | L39: SI
A40: 45721 | C40: POTENCIALES AL PROGRAMA CUIDATE Y OTROS CRONICOS-SURA /RIESGO | D40: =VLOOKUP(B40,'DATA CORREO'!G:P,7,0) -> #N/A | N40: EXCEL CON 68 PACIENTES, CONFIRMACION DE ATENCIONES EJECUTADAS
A41: 45725 | B41: 8268085 | C41: TALMA - EPS - ATENCION MEDICA - ASEG: GARCIA CASTILLO NORA EMMA | D41: =VLOOKUP(B41,'DATA CORREO'!G:P,7,0) -> 0 | F41: SI | G41: 45726 | H41: CITADO | I41: 45726 | O41: SI | P41: 45726
A42: 45721 | B42: 7307988 | C42: PROGRAMA CRONICOS - Paciente - CECILIA ESTHER CANALES ANICAMA | D42: =VLOOKUP(B42,'DATA CORREO'!G:P,7,0) -> 0 | H42: CITADO | I42: 45721 | J42: SI | L42: NO
A43: 45721 | B43: 72182950 | C43: XIMENA SOFIA DELGADILLO CABRERA-77742062 | D43: =VLOOKUP(B43,'DATA CORREO'!G:P,7,0) -> 0 | H43: CITADO | I43: 45721 | J43: SI | L43: NO | N43: CONFIRMACION DE ATENCION EJECUTADA
A44: 45722 | B44: 7368311 | C44: RIMAC VIP // INSCRIPCION PROGRAMA CUIDATE // C: JESSICA MILAGROS NALDOS BLANCO | D44: =VLOOKUP(B44,'DATA CORREO'!G:P,7,0) -> 0 | E44: DEMORA PROGRAMACIÓN DE CITA | N44: PENDIENTE AGENDAMIENTO
C45: REFINERIA LA PAMPILLA / EPS N° E0001009 / ASEGURADO: Victor Edgar Solis Plaza / RECLAMO URGENTE | D45: =VLOOKUP(B45,'DATA CORREO'!G:P,7,0) -> #N/A
A46: 45722 | B46: 29275734 | C46: DENEGADO PARA ATENCION EN RIMAC TE CUIDA | D46: =VLOOKUP(B46,'DATA CORREO'!G:P,7,0) -> #N/A | E46: DEMORA PROGRAMACIÓN DE CITA | N46: PENDIENTE AGENDAMIENTO
A47: 45722 | B47: 3506981 | C47: DERIVACION MDC A CUIDATE Juan Manuel Rivas Castillo | D47: =VLOOKUP(B47,'DATA CORREO'!G:P,7,0) -> 0 | E47: DEMORA PROGRAMACIÓN DE CITA | N47: PENDIENTE AGENDAMIENTO
A48: 45722 | B48: 79971601 | C48: SOLICITUD DE AFILIACION A PROGRAMA CUIDATE - TITULAR: Christian Portugal Sucapuca PACIENTE: Thiago Portugal Quispe DNI 79971601 - NO CONTESTAN EL TELEFONO | D48: =VLOOKUP(B48,'DATA CORREO'!G:P,7,0) -> 0 | E48: DEMORA PROGRAMACIÓN DE CITA | N48: NO CONTESTA EL TELEFONO
A49: 45722 | C49: *****URGENTE**** TRAMA PACIENTES CRONICOS //MEF- SOLICITUD DE DATA POR PROCESO DE RENOVACIÓN CONCURSO EPS | D49: =VLOOKUP(B49,'DATA CORREO'!G:P,7,0) -> #N/A | N49: STATUS DE AGENDAMIENTO DE PACIENTES CRONICOS
A50: 45722 | B50: 7006744 | C50: RIMAC VIP || PROGRAMA CRONICOS || MAURA ROSALINA PRADO SOTO | D50: =VLOOKUP(B50,'DATA CORREO'!G:P,7,0) -> 0 | E50: DEMORA PROGRAMACIÓN DE CITA | N50: PENDIENTE AGENDAMIENTO
A51: 45723 | B51: 29599302 | C51: CASO VILLAVICENCIO DE PALZA BETTY LILIAN- CORPORACION ACEROS AREQUIPA SA- POLIZA EPS | D51: =VLOOKUP(B51,'DATA CORREO'!G:P,7,0) -> 0 | N51: PENDIENTE AGENDAMIENTO
A52: 45706 | B52: 73028278 | C52: URGENTE / UCSP / AMC / PACIENTE: CASTELO VARGAS, JOAQUIN ALONSO (DNI 73028278) - TITULAR: REGINA VARGAS / SOLICITO ATENCIÓN PROGRAMA "OTRAS ENFERMEDADES" | D52: =VLOOKUP(B52,'DATA CORREO'!G:P,7,0) -> 0 | E52: DEMORA PROGRAMACIÓN DE CITA | F52: SI | G52: 45720 | H52: CITADO | I52: 45723 | J52: SI | L52: NO
A53: 45723 | B53: 73339945 | C53: PACIENTE DEL PROGRAMA CUIDATE / FRANCIS ANN ROJAS BISMARCK / NO RECIBIO RECETAS MEDICAS | D53: =VLOOKUP(B53,'DATA CORREO'!G:P,7,0) -> 0 | H53: CITADO | I53: 45724 | J53: SI | L53: NO
A54: 45723 | B54: 45482869 | C54: URGENTE PACIENTE Programa Cuídate VANESSA KAREN CORDOVA SANTOS | D54: =VLOOKUP(B54,'DATA CORREO'!G:P,7,0) -> #N/A | E54: DEMORA ENTREGA DE MEDICAMENTOS | F54: SI | G54: 45723 | H54: SITED INACTIVO | O54: SI | P54: 45723
A55: 45723 | B55: 7843321 | C55: DISLIPIDEMIA E HIPOTIROISDISMO//SANDRA MILAGROS RIVAROLA LIMONCHI | D55: =VLOOKUP(B55,'DATA CORREO'!G:P,7,0) -> 0 | H55: CITADO | I55: 45722 | J55: SI | L55: NO
A56: 45723 | B56: 10220773 | C56: PROGRAMA CUIDATE // Paciente: DANIEL PEDRO MARCELO INDACOCHEA NUGENT | D56: =VLOOKUP(B56,'DATA CORREO'!G:P,7,0) -> 0 | N56: PENDIENTE AGENDAMIENTO
A57: 45723 | B57: 10091783 | C57: DERIVACION MDC A CUIDATEGisella Isabel Galindo Cieza | D57: =VLOOKUP(B57,'DATA CORREO'!G:P,7,0) -> 0 | E57: DERIVACION DE PACIENTE | F57: SI | G57: 45723 | H57: CITADO | I57: 45727 | N57: PENDIENTE AGENDAMIENTO | O57: SI | P57: 45723
A58: 45723 | B58: 7819040 | C58: Asegurada Yolanda Patricia Tejeda Moscoso - Programa de Artritis Rematoidea // Contratante Obras de Ingenieria - Poliza E0003156// Rimac Seguros | D58: =VLOOKUP(B58,'DATA CORREO'!G:P,7,0) -> 0 | E58: DERIVACION DE PACIENTE | F58: SI | G58: 45726 | H58: CITADO | I58: 45721 | J58: SI | K58: 45722 | L58: NO | N58: PENDIENTE AGENDAMIENTO | O58: SI | P58: 45726
A59: 45723 | B59: 8804113 | C59: PACIENTE: BERTHA TALLEDO EYZAGUIRRE DE ECHEGARAY (92) | D59: =VLOOKUP(B59,'DATA CORREO'!G:P,7,0) -> 0 | E59: DEMORA ENTREGA DE MEDICAMENTOS | F59: SI | G59: 45726 | H59: CITADO | I59: 45709 | J59: SI | L59: NO | N59: PENDIENTE AGENDAMIENTO | O59: SI | P59: 45726

Sheet Reporte de casos MAD
A1: Fecha y hora | B1: Salesforce | C1: Código | D1: Estado | E1: Nombres del paciente | F1: Apellidos del paciente | G1: Tipo de documento | H1: Documento | I1: Edad | J1: Número whatsapp | K1: Dirección | L1: Referencia | M1: Distrito | N1: Tema | O1: Fecha asignación de proveedor | P1: Fecha programación de proveedor | Q1: Inicio de atención | R1: Fecha Hora de consulta | S1: Culminación | T1: Descripción | U1: Punto de partida | V1: PRESCRIPCIÓN DE MEDICAMENTOS | W1: ESTADO DE MEDICAMENTO | X1: FECHA DE ENTREGA | Y1: HORA | Z1: PROVEEDOR | AA1: CERRADO
A2: 45737.28 | B2: 24803769 | C2: 726885 | D2: Proveedor asignado | E2: SANTOS BERNARDO | F2: SIANCAS SEMINARIO | G2: DNI | H2: 25756556 | I2: 51 | J2: 961903526 | K2: AV RUISEÑORES 941 | L2: MINISTERIO PUBLICO | M2: SANTA ANITA | N2: Médico Virtual Medicina General | O2: 45737.307 | P2: 45737.314 | Q2: 45737.328 | R2: - | S2: 45737.356 | U2: - | V2: SI | W2: SIN INFORMACION | AA2: SI
A3: 45737.29 | B3: 24803817 | C3: 726897 | D3: Proveedor asignado | E3: ALLISON GIANELLA | F3: SALDARRIAGA ARENAS | G3: DNI | H3: 75369311 | J3: 993665038 | K3: JIRON PHILADELPHIA 2395 SEGUNDO PISO | L3: LA ALTURA DE LA CUADRA 23 DE LA AVENIDA PERU | M3: SAN MARTIN DE PORRES | N3: Médico Virtual Medicina General | O3: 45737.308 | P3: 45737.316 | Q3: 45737.332 | R3: - | S3: 45737.533 | U3: - | W3: SIN INFORMACION | AA3: SI
A4: 45737.299 | B4: 24803846 | C4: 726906 | D4: Proveedor asignado | E4: SERGIO | F4: QUIJANO SANDOVAL | G4: DNI | H4: 91063347 | I4: 6 | J4: 956614171 | K4: calle santo tomas 158 | L4: 15 de angelica gamarra | M4: LOS OLIVOS | N4: Médico Virtual Pediatría | O4: 45737.304 | P4: 45737.311 | Q4: 45737.326 | R4: - | S4: 45740.037 | U4: - | W4: SIN INFORMACION | AA4: SI
A5: 45737.303 | B5: 24803858 | C5: 726912 | D5: Proveedor asignado | E5: LUCIANA | F5: SALGADO CAMINO | G5: DNI | H5: 77193470 | I5: 13 | J5: 990371130 | K5: AV. GRAN MARISCAL RAMON CASTILLA 468 LA AURORA | L5: PARALELA A ROQUE Y BOLOÑA | M5: MIRAFLORES | N5: Médico Virtual Pediatría | O5: 45737.331 | P5: 45737.403 | Q5: 45737.384 | R5: - | S5: 45737.628 | U5: - | W5: SIN INFORMACION | AA5: NO
A6: 45737.304 | B6: 24803865 | C6: 726916 | D6: Proveedor asignado | E6: LEAO STEFFANO | F6: TREBEJO JIMENEZ | G6: DNI | H6: 91420305 | I6: 5 | J6: 900669280 | K6: Juan de Dios Bedoya y Seijas 1166, Lima 15081 | L6: NTRE JR JOSE FELIX BOGADO Y CALLE ELVIRA GARCIA Y GARCIA | M6: LIMA | N6: Médico Virtual Pediatría | O6: 45737.326 | P6: 45737.361 | Q6: 45737.371 | R6: - | S6: 45739.937 | U6: - | W6: SIN INFORMACION | AA6: SI
A7: 45737.306 | B7: 24803870 | C7: 726921 | D7: Proveedor asignado | E7: LUANA FERNANDA | F7: VIDAL TAIPE | G7: DNI | H7: 90641293 | I7: 7 | J7: 984119375 | K7: CALLE RAMON DEL VALLE INCLAN 171 - | L7: CUADRA 13 AVENIDA CONSTRUCTORES - | M7: LA MOLINA | N7: Médico Virtual Pediatría | O7: 45737.309 | P7: 45737.317 | Q7: 45737.402 | R7: - | S7: 45737.404 | U7: - | W7: SIN INFORMACION | AA7: SI
A8: 45737.309 | B8: 24803888 | C8: 726927 | D8: Proveedor asignado | E8: LUCCIANA MILAGROS | F8: CAMARRO MARCENARO | G8: DNI | H8: 91025289 | I8: 6 | J8: 995908375 | K8: JIRON EMILIO ALTHAUS 697 - | L8: - | M8: LINCE | N8: Médico Virtual Pediatría | O8: 45737.344 | P8: 45737.444 | Q8: 45737.433 | R8: - | S8: 45737.456 | U8: - | V8: SI | W8: ENTREGADO | X8: 45742 | Y8: 0.5299537 | Z8: CUIDA | AA8: SI
A9: 45737.31 | B9: 24803859 | C9: 726930 | D9: Proveedor asignado | E9: ZULLY MARIELLA | F9: DEL SOLAR MEDINA | G9: DNI | H9: 44725610 | I9: 37 | J9: 963151477 | K9: JR ECHENIQUE 633 | L9: DEP 905 / A UNA CUADRA PLAZA PRINCIPAL | M9: MAGDALENA DEL MAR | N9: Médico Virtual Medicina General | O9: 45737.334 | P9: 45737.382 | Q9: 45737.365 | R9: - | S9: 45737.533 | U9: - | W9: SIN INFORMACION | AA9: SI
A10: 45737.303 | B10: 24803863 | C10: 726915 | D10: Proveedor asignado | E10: JOAQUIN ANTONIO | F10: MEDINA LIMO | G10: DNI | H10: 74791525 | I10: 14 | J10: 956770210 | K10: CALLE LAS GAVIOTAS 21:10 EDIFICIO 4 DEPARTAMENTO 604 SANTIAGO DE SURCO - | L10: ALTURA DE LA CUADRA 12 FROZEN SURCO - | M10: SANTIAGO DE SURCO | N10: Médico Virtual Pediatría | O10: 45737.308 | P10: 45737.315 | Q10: 45737.369 | R10: - | S10: 45737.37 | U10: - | W10: SIN INFORMACION | AA10: SI
A11: 45737.311 | B11: 24803896 | C11: 726931 | D11: Proveedor asignado | E11: ALIDE DANISA | F11: ZEGARRA BULEJE | G11: DNI | H11: 7766958 | I11: 48 | J11: 973337616 | K11: PASAJE DANIEL CRUZ 414 DEPARTAMENTO 601 - | L11: ALTURA CUADRA 5 AVENIDA PRINCIPAL - | M11: SURQUILLO | N11: Médico Virtual Medicina General | O11: 45737.331 | P11: 45737.382 | Q11: 45737.362 | R11: - | S11: 45737.408 | U11: - | W11: SIN INFORMACION | AA11: SI
A12: 45737.318 | B12: 24803929 | C12: 726944 | D12: Proveedor asignado | E12: MAX CARLOS | F12: BAYES RAMOS | G12: DNI | H12: 44100076 | I12: 38 | J12: 970759311 | K12: JIRON PIEDRA DEL SOL 1635 URBANIZACION INCA MANCO CAPAC TERCERA ETAPA - | L12: A LA ALTURA DEL METRO DE LA HACIENDA - | M12: SAN JUAN DE LURIGANCHO | N12: Médico Virtual Medicina General | O12: 45737.332 | P12: 45737.382 | Q12: 45737.369 | R12: - | S12: 45737.469 | U12: - | W12: SIN INFORMACION | AA12: SI
A13: 45737.319 | B13: 24803931 | C13: 726945 | D13: Proveedor asignado | E13: DANIELA FERNANDA | F13: DE LA CRUZ VILCA | G13: DNI | H13: 78824992 | I13: 10 | J13: 991832424 | K13: AVENIDA CIPRIANO DULANTO EXCLAMAR 2041 DEPARTAMENTO 702 A PUEBLO LIBRE - | L13: FRENTE AL COLEGIO LA UNION - | M13: PUEBLO LIBRE | N13: Médico Virtual Pediatría | O13: 45737.331 | P13: 45737.403 | Q13: 45737.404 | R13: - | S13: 45737.418 | U13: - | W13: SIN INFORMACION | AA13: SI
A14: 45737.32 | B14: 24803933 | C14: 726947 | D14: Proveedor asignado | E14: SALVADOR | F14: BEGAZO SORIA | G14: DNI | H14: 74115162 | I14: 15 | J14: 937574601 | K14: CALLE PISANO 152 SAN BORJA - | L14: ALTURA DE LA CUADRA 28 DE AVIACION - | M14: SAN BORJA | N14: Médico Virtual Pediatría | O14: 45737.331 | P14: 45737.382 | Q14: 45737.381 | R14: - | S14: 45737.419 | U14: - | W14: SIN INFORMACION | AA14: SI
A15: 45737.324 | B15: 24803946 | C15: 726955 | D15: Proveedor asignado | E15: ISMAEL ANTONIO | F15: LA JARA MANOSALVA | G15: DNI | H15: 78973884 | I15: 10 | J15: 989471037 | K15: CALLE EL CONDADO MANZANA CAPRIMA 1 LOTE 4 URBANIZACION PORTADA DEL SOL - | L15: ALTURA CUADRA 15 AVENIDA DE LOS FRENOS - | M15: LIMA | N15: Médico Virtual Pediatría | O15: 45737.339 | P15: 45737.424 | Q15: 45737.419 | R15: - | S15: 45737.432 | U15: - | W15: SIN INFORMACION | AA15: SI
A16: 45737.324 | B16: 24803947 | C16: 726956 | D16: Proveedor asignado | E16: IVONNE MARGARET | F16: ANCAJIMA OROZCO | G16: DNI | H16: 2822951 | I16: 52 | J16: 992408310 | K16: PINCHE ROCA 2520 DEPARTAMENTO 10 02 LINCE - | L16: ALTURA DE LA CUADRA 13 DE CESAR VALLEJO O FRENTE AL PARQUE RAMON CASTILLA - | M16: LINCE | N16: Médico Virtual Medicina General | O16: 45737.328 | P16: 45737.361 | Q16: 45737.373 | R16: - | S16: 45737.469 | U16: - | W16: SIN INFORMACION | AA16: SI
A17: 45737.325 | B17: 24803952 | C17: 726958 | D17: Proveedor asignado | E17: KATIA CAROLINA | F17: RIVAS PAREDES | G17: DNI | H17: 73661268 | I17: 29 | J17: 987492301 | K17: ABETO 730 SALAMANCA - | L17: ALTURA CUADRA 13 AVENIDA LOS QUECHUAS - | M17: ATE | N17: Médico Virtual Medicina General | O17: 45737.335 | P17: 45737.403 | Q17: 45737.39 | R17: - | S17: 45737.47 | U17: - | W17: SIN INFORMACION | AA17: SI
A18: 45737.33 | B18: 24803971 | C18: 726966 | D18: Proveedor asignado | E18: JULISSA ROXANA | F18: HUAMANI HERRERA | G18: DNI | H18: 42833915 | I18: 40 | J18: 955098492 | K18: JIRON MATEO SILVA 2479 MIRONES BAJO - | L18: ALTURA DE LA CUADRA 24 EN MORALES SUAREZ - | M18: LIMA | N18: Médico Virtual Medicina General | O18: 45737.334 | P18: 45737.382 | Q18: 45737.404 | R18: - | S18: 45737.42 | U18: - | W18: SIN INFORMACION | AA18: SI
A19: 45737.331 | B19: 24803973 | C19: 726967 | D19: Proveedor asignado | E19: PAULO ADRIANO | F19: ZAPATA CARMONA | G19: DNI | H19: 77660867 | I19: 25 | J19: 929350962 | K19: CALLE 4 MZ i LOTE 2 URB RODRIGO FRANCO | L19: A 3 CDRAS DEL MERCADO RODRIGO FRANCO | M19: SANTIAGO DE SURCO | N19: Médico Virtual Medicina General | O19: 45737.335 | P19: 45737.403 | Q19: 45737.404 | R19: - | S19: 45737.422 | U19: - | W19: SIN INFORMACION | AA19: SI
A20: 45737.335 | B20: 24803974 | C20: 726972 | D20: Proveedor asignado | E20: LILIANA SARA | F20: VIA DIAZ | G20: DNI | H20: 9874662 | I20: 52 | J20: 994134904 | K20: CALLE RIO PARANA MZ E1 LOTE 4 DEP 2 URB PRADERAS DE LA MOLINA | L20: FINALIZANDO PROLONGACION LOS FRESNOS POR EL PARQUE ECOLOGICO DE LA MOLINA | M20: LA MOLINA | N20: Médico Virtual Medicina General | O20: 45737.363 | P20: 45737.424 | Q20: 45737.397 | R20: - | S20: 45737.402 | U20: - | W20: SIN INFORMACION | AA20: SI
... A23: 45737.344 | B23: 24804042 | C23: 726989 | D23: Proveedor asignado | E23: JOSE ALEXANDER | F23: MONJA CARRASCO | G23: DNI | H23: 44083338 | I23: 38 | J23: 969757523 | K23: MANZANA 1735 TERCERA ETAPA URBANIZACION PACHACAMAC - | L23: - | M23: VILLA EL SALVADOR | N23: Médico Virtual Medicina General | O23: 45737.348 | P23: 45737.465 | Q23: 45737.41 | R23: - | S23: 45737.424 | U23: - | W23: SIN INFORMACION | AA23: SI
A24: 45737.347 | B24: 24803977 | C24: 726992 | D24: Proveedor asignado | E24: MARIA MERCEDES DEL ROSARIO | F24: RIVAS OTAKE | G24: DNI | H24: 44366663 | J24: 957397694 | K24: AV BOLIVAR 528 DPTO 2009 | L24: AT BRITANICO DE PUEBLO LIBRE | M24: PUEBLO LIBRE | N24: Médico Virtual Medicina General | O24: 45737.372 | P24: 45737.41 | Q24: 45737.406 | R24: - | S24: 45737.422 | U24: - | W24: SIN INFORMACION
A25: 45737.336 | B25: 24803995 | C25: 726975 | D25: Proveedor asignado | E25: CLAUDIA DE GUADALUPE | F25: ARIAS FLORES | G25: DNI | H25: 79660352 | I25: 8 | J25: 977464707 | K25: CALLE COCHAS MANZANA H3 LOTE 29 URBANIZACION LOS NARANJOS DISTRITO LOS OLIVOS - | L25: A DOS CUADRAS DEL OVALO HUANDOY - | M25: LOS OLIVOS | N25: Médico Virtual Pediatría | O25: 45737.345 | P25: 45737.424 | Q25: 45737.47 | R25: - | S25: 45737.472 | U25: - | W25: SIN INFORMACION
A26: 45737.351 | B26: 24804088 | C26: 727003 | D26: Proveedor asignado | E26: GIULIANA ZENAIDA | F26: OROSCO BENITES | G26: DNI | H26: 41385179 | I26: 43 | J26: 995010809 | K26: jiron vesalio 457 | L26: cuafra 33 aviación | M26: SAN BORJA | N26: Médico Virtual Medicina General | O26: 45737.359 | P26: 45737.424 | Q26: 45737.411 | R26: - | S26: 45737.534 | U26: - | W26: SIN INFORMACION
A27: 45737.354 | B27: 24804104 | C27: 727007 | D27: Proveedor asignado | E27: CLAUDIO JOSE ERNESTO | F27: FALCONE BALZA | G27: DNI | H27: 43906540 | I27: 38 | J27: 994609901 | K27: AVENIDA CENTRAL 306 MONTERRICO SURCO - | L27: ENTRE ALONSO DE MOLINA Y LA TRANQUERA DE LOS ALAMOS DE MONTERRICO - | M27: SANTIAGO DE SURCO | N27: Médico Virtual Medicina General | O27: 45737.358 | P27: 45737.465 | Q27: 45737.427 | R27: - | S27: 45737.439 | U27: - | W27: SIN INFORMACION
A28: 45737.356 | B28: 24804108 | C28: 727008 | D28: Proveedor asignado | E28: YANET SOHELEN | F28: SOTO HUAMANI | G28: DNI | H28: 70542844 | I28: 28 | J28: 920054990 | K28: ESTEBAN 154 - | L28: PARQUE PRIMERO DE MAYO - | M28: COMAS | N28: Médico Virtual Medicina General | O28: 45737.368 | P28: 45737.382 | Q28: 45737.379 | R28: - | S28: 45737.406 | U28: - | W28: SIN INFORMACION
A29: 45737.357 | B29: 24804116 | C29: 727009 | D29: Proveedor asignado | E29: RUTH MARISA | F29: CONCHA CHAVEZ | G29: DNI | H29: 23885252 | I29: 63 | J29: 996229017 | K29: JUVENAL VILLAVERDE 401 TERCER PISO - | L29: ENTRANDO DE POR LA TOMAS VALLE A LA SEGUNDA CUADRA EL PASAJE ESTA TAMBIEN SE LLAMA JUVENAL VILLA - | M29: SAN MARTIN DE PORRES | N29: Médico Virtual Medicina General | O29: 45737.369 | P29: 45737.396 | Q29: 45737.43 | R29: - | S29: 45737.631 | U29: - | W29: SIN INFORMACION
A30: 45737.364 | B30: 24804160 | C30: 727018 | D30: Proveedor asignado | E30: MARIA MAGDALENA | F30: DE LA CRUZ NARVAEZ | G30: DNI | H30: 32939541 | I30: 52 | J30: 925038721 | K30: JAVIER PRADO OESTE 390 | L30: ES UNA CASA JAVIER PRADO CON CALLE LOS FRESNOS | M30: SAN ISIDRO | N30: Médico Virtual Medicina General | O30: 45737.374 | P30: 45737.41 | Q30: 45737.441 | R30: - | S30: 45737.535 | U30: - | W30: SIN INFORMACION
A31: 45737.364 | B31: 24804125 | C31: 727019 | D31: Proveedor asignado | E31: SAMUEL GAMALIEL | F31: JUAREZ PULACHE | G31: DNI | H31: 46178479 | I31: 36 | J31: 917316291 | K31: AV BRASIL 3029 DPT 104 | L31: MEDIA CUADRA KFC DE JAVIER PRADO CON BRASIL | M31: MAGDALENA DEL MAR | N31: Médico Virtual Medicina General | O31: 45737.384 | P31: 45737.444 | Q31: 45737.422 | R31: - | S31: 45737.657 | U31: - | W31: SIN INFORMACION
A32: 45737.359 | B32: 24804126 | C32: 727013 | D32: Proveedor asignado | E32: VANESSA PAOLA | F32: ALCAZAR NAVARRO | G32: DNI | H32: 42070372 | I32: 41 | J32: 954062688 | K32: AVENIDA BUENAVISTA 235 - | L32: DURA PUENTE PRIMAVERA - | M32: SAN BORJA | N32: Médico Virtual Medicina General | O32: 45737.374 | P32: 45737.41 | Q32: 45737.421 | R32: - | S32: 45737.426 | U32: - | W32: SIN INFORMACION
A33: 45737.369 | B33: 24804179 | C33: 727026 | D33: Proveedor asignado | E33: LIZETH VANESSA | F33: USNO RABANAL | G33: DNI | H33: 72782506 | I33: 27 | J33: 970705010 | K33: jr saenz peña 287 | L33: tomas valle con angelica gamarra | M33: SAN MARTIN DE PORRES | N33: Médico Virtual Medicina General | O33: 45737.376 | P33: 45737.424 | Q33: 45738.54 | R33: - | S33: - | U33: - | W33: SIN INFORMACION
A34: 45737.374 | B34: 24804184 | C34: 727033 | D34: Proveedor asignado | E34: JHON CRISTHIAN | F34: CAMONES ORTIZ | G34: DNI | H34: 45897121 | I34: 35 | J34: 951125488 | K34: AV NICOLAS DE PIEROLA 529 | L34: RENIEC | M34: LIMA | N34: Médico Virtual Medicina General | O34: 45737.389 | P34: 45737.424 | Q34: 45737.431 | R34: - | S34: 45737.442 | U34: - | W34: SIN INFORMACION
A35: 45737.371 | B35: 24804207 | C35: 727029 | D35: Proveedor asignado | E35: MARCO ANTONIO | F35: BORRA RAMIREZ | G35: DNI | H35: 10735129 | I35: 46 | J35: 985858416 | K35: TOMAS RAMSEY 465 DPTO 503 | L35: CRUCE PARQUE GONZALES PRADA CON TOMAS RAMSEY | M35: MAGDALENA DEL MAR | N35: Médico Virtual Medicina General | O35: 45737.376 | P35: 45737.424 | Q35: 45737.424 | R35: - | S35: 45737.499 | U35: - | W35: SIN INFORMACION
A36: 45737.375 | B36: 24804253 | C36: 727037 | D36: Proveedor asignado | E36: LESLI ELISABETH | F36: VILLANUEVA SOTO | G36: DNI | H36: 48557314 | I36: 34 | J36: 994685630 | K36: JIRON SANTA ROSA 180 KM 12 DE LA TUPA COMAS - | L36: ALTURA DE LA RENIEC QUE ESTA EN LA PUPAS - | M36: COMAS | N36: Médico Virtual Medicina General | O36: 45737.379 | P36: 45737.438 | Q36: 45737.456 | R36: - | S36: 45737.469 | U36: - | W36: SIN INFORMACION
A37: 45737.376 | B37: 24804265 | C37: 727039 | D37: Proveedor asignado | E37: SANDRA ELIZABETH | F37: DE LA CRUZ BELICOSO | G37: DNI | H37: 43466267 | I37: 39 | J37: 961261109 | K37: AVENIDA ALFREDO ME ENVIO LA 1635 MARTIN DE PORRES - | L37: COSTADO DE CENTRO COMERCIAL RED TIENDA TOYOTA - | M37: SAN MARTIN DE PORRES | N37: Médico Virtual Medicina General | O37: 45737.38 | P37: 45737.438 | Q37: 45737.44 | R37: - | S37: 45737.455 | U37: - | W37: SIN INFORMACION
A38: 45737.377 | B38: 24804289 | C38: 727041 | D38: Proveedor asignado | E38: GIANCARLOS JORGE | F38: RICARDI FRANCO | G38: DNI | H38: 72230658 | I38: 34 | J38: 958665617 | K38: GIRO LA COMPANIA 253 URBANIZACION VILLA JARDIN SAN LUIS - | L38: ALTURA DE LA 438 DE LA AVENIDA CANADA - | M38: SAN LUIS | N38: Médico Virtual Medicina General | O38: 45737.381 | P38: 45737.444 | Q38: 45737.477 | R38: - | S38: - | U38: - | W38: SIN INFORMACION
A39: 45737.379 | B39: 24804312 | C39: 727044 | D39: Proveedor asignado | E39: RITA ROXANA | F39: PINEDO TORRES | G39: DNI | H39: 25738670 | I39: 56 | J39: 994691127 | K39: VENIDA FRIGUIDA SILVA DE OCHOA 181 | L39: TORRE H DPT 102 ESPALDAS DE TOTTUS DE LA MARIINA | M39: SAN MIGUEL | N39: Médico Virtual Medicina General | O39: 45737.383 | P39: 45737.424 | Q39: 45737.456 | R39: - | S39: 45737.469 | U39: - | W39: SIN INFORMACION
A40: 45737.383 | B40: 24804375 | C40: 727045 | D40: Proveedor asignado | E40: WILSON EDWARDS | F40: ANGULO SAONA | G40: DNI | H40: 44118408 | I40: 38 | J40: 933518327 | K40: GARCILASO DE LA VEGA 955 - | L40: CRUCE CON QUILCA - | M40: LIMA | N40: Médico Virtual Medicina General | O40: 45737.387 | P40: 45737.424 | Q40: 45737.427 | R40: - | S40: 45737.533 | U40: - | W40: SIN INFORMACION
A41: 45737.386 | B41: 24804457 | C41: 727046 | D41: Proveedor asignado | E41: YULY KAREN | F41: HUERTA AYALA | G41: DNI | H41: 80367201 | I41: 46 | J41: 981562462 | K41: JOSE BERNADO ALCEDO 712 | L41: ENTRE CRUCE ANGELICA GAMARRA Y TOMAS VALLE | M41: SAN MARTIN DE PORRES | N41: Médico Virtual Medicina General | O41: 45737.399 | P41: 45737.451 | Q41: 45737.433 | R41: - | S41: 45737.784 | U41: - | V41: SI | W41: ENTREGADO | X41: 45741 | Z41: VIVA 1A | AA41: SI
A42: 45737.393 | B42: 24804527 | C42: 727052 | D42: Proveedor asignado | E42: LIDIA | F42: QUISPE AVILA | G42: DNI | H42: 10169884 | I42: 52 | J42: 998175870 | K42: PASAJE RIO CHIRA 120 PUEBLO JOVEN VIRGEN DEL ROSARIO | L42: ULTIMO PARADERO DEL OVALO DE ROSARIO | M42: LURIGANCHO (CHOSICA) | N42: Médico Virtual Medicina General | O42: 45737.397 | P42: 45737.438 | Q42: 45737.625 | R42: - | S42: 45737.685 | U42: - | W42: SIN INFORMACION
A43: 45737.392 | B43: 24804571 | C43: 727051 | D43: Proveedor asignado | E43: LUIS | F43: VILLANUEVA GARCIA | G43: DNI | H43: 44024941 | I43: 38 | J43: 945432737 | K43: MZ B6 LOTE 7 | L43: A TRES CUADRAS DEL CRUCE DE LA AV HUAURA Y LA AV VÍCTOR RAÚL HAYA DE LA TORRE FRENTE A LA IGLESIA MORMONA CERCA AL PARQUE DEL SECTOR B | M43: MI PERÚ | N43: Médico Virtual Medicina General | O43: 45737.396 | P43: 45737.444 | Q43: 45737.443 | R43: - | S43: 45737.633 | U43: - | V43: SI | W43: REEMBOLSO | AA43: SI
A44: 45737.399 | B44: 24804761 | C44: 727056 | D44: Proveedor asignado | E44: PEDRO ALEXANDRE | F44: GOMEZ AREVALO | G44: DNI | H44: 47694900 | I44: 33 | J44: 51922908260 | K44: mz I 1 lote 15 - los portales de chillon | L44: CANCHA DE FUTBOL MAPS: TATTOS LOCAZO PUENTE PIEDRE | M44: PUENTE PIEDRA | N44: Médico Virtual Medicina General | O44: 45737.407 | P44: 45737.465 | Q44: 45737.46 | R44: - | S44: 45737.637 | U44: - | V44: SI | W44: ENTREGADO | X44: 45738 | Z44: REEMBOLSO | AA44: SI
A45: 45737.401 | B45: 24804807 | C45: 727059 | D45: Proveedor asignado | E45: EMILIA LUCIA | F45: CALDERON VILLANUEVA | G45: DNI | H45: 90550713 | I45: 7 | J45: 991589060 | K45: SURQUILLO - AV DOMINGO ORUE 456 TORRE 1 DPTO 804 | L45: DPTO ESTA FRENTE A TAMBO DE DOMINGO ORUE | M45: SURQUILLO | N45: Médico Virtual Pediatría | O45: 45737.405 | P45: 45737.451 | Q45: 45737.472 | R45: - | S45: 45737.489 | U45: - | W45: SIN INFORMACION
A46: 45737.401 | B46: 24804810 | C46: 727060 | D46: Proveedor asignado | E46: JORGE ANTONIO | F46: CERRO DE LA CRUZ | G46: DNI | H46: 8155696 | I46: 51 | J46: 986056458 | K46: ALZAMORA OESTE 108 - | L46: CON EL GOLF LOS 100 Y SANTO TORIBIO - | M46: SAN ISIDRO | N46: Médico Virtual Medicina General | O46: 45737.405 | P46: 45737.451 | Q46: 45737.463 | R46: - | S46: 45737.482 | U46: - | W46: SIN INFORMACION
A47: 45737.408 | B47: 24804874 | C47: 727069 | D47: Proveedor asignado | E47: VALERIA XIMENA | F47: AGUIRRE VALER | G47: DNI | H47: 71528818 | I47: 23 | J47: 970622245 | K47: Jiron Monte Ebano 375, Lima, Peru | L47: Al lado de monte ebano 369 | M47: SANTIAGO DE SURCO | N47: Médico Virtual Medicina General | O47: 45737.426 | P47: 45737.493 | Q47: 45737.583 | R47: - | S47: 45737.608 | U47: - | W47: SIN INFORMACION
A48: 45737.406 | B48: 24804880 | C48: 727065 | D48: Proveedor asignado | E48: SALEM BETZABE | F48: ESPINOZA ARROYO | G48: DNI | H48: 70451323 | I48: 18 | J48: 932958321 | K48: Departamento: LIMA Provincia: LIMA Distrito: CHORRILLOS Dirección: - | L48: FRENTE A PLAZA NORTE ENTRE LOS PARQUES SAN MARTIN Y SANTA ROSA - | M48: CHORRILLOS | N48: Médico Virtual Medicina General | O48: 45737.409 | P48: 45737.465 | Q48: 45738.82 | R48: - | S48: 45738.829 | U48: - | W48: SIN INFORMACION
A49: 45737.409 | B49: 24804964 | C49: 727074 | D49: Proveedor asignado | E49: KARINA | F49: CHUMPITAZ BUTRON | G49: DNI | H49: 41215708 | I49: 43 | J49: 932097642 | K49: CALLE MONTE CASSINO 153 DEPARTAMENTO 404 - | L49: ENTRE LA CUADRA 1 Y 2 DE REYNALDO VIVANCO - | M49: SANTIAGO DE SURCO | N49: Médico Virtual Medicina General | O49: 45737.424 | P49: 45737.493 | Q49: 45737.488 | R49: - | S49: 45737.532 | U49: - | W49: SIN INFORMACION
A50: 45737.41 | B50: 24804998 | C50: 727079 | D50: Proveedor asignado | E50: DANIELLA EVAN | F50: LOPEZ GUZMAN | G50: Ident. Menor de edad | H50: 405592523 | I50: 20 | J50: 914040354 | K50: CALLE ARTURO DURAY 260 DPTO 101 | L50: ENTRE AV PRINCIPAL Y VILLARAN | M50: SURQUILLO | N50: Médico Virtual Medicina General | O50: 45737.415 | P50: 45737.493 | Q50: 45737.47 | R50: - | S50: 45737.484 | U50: - | W50: SIN INFORMACION
A51: 45737.411 | B51: 24805012 | C51: 727080 | D51: Proveedor asignado | E51: CYNTHIA FABIOLA | F51: TABOADA PEREZ | G51: DNI | H51: 40167347 | I51: 45 | J51: 987416473 | K51: JIRON MOREYRA Y RIGLOS 793 - | L51: INCLUSO DE ALFREDO MALDONADO Y JIRON MOREYRA Y RIGLOS A LA ALTURA DE LA CUADRA 7 DE LA AVENIDA BOLIVAR ESPALDA DEL HOSPITAL SANTA ROSA - | M51: PUEBLO LIBRE | N51: Médico Virtual Medicina General | O51: 45737.415 | P51: 45737.479 | Q51: 45737.468 | R51: - | S51: 45737.5 | U51: - | W51: SIN INFORMACION
A52: 45737.415 | B52: 24805110 | C52: 727087 | D52: Proveedor asignado | E52: GEOVANNY MARIBEL | F52: TIRADO MELENDEZ | G52: DNI | H52: 41064609 | I52: 46 | J52: 982091812 | K52: SALEN LOS LUCUMOS MANZANA B LOTE 19 CIENEGUILLA - | L52: KILOMETRO 55 DE LA CARRETERA DE CIENEGUILLA - | M52: CIENEGUILLA | N52: Médico Virtual Medicina General | O52: 45737.419 | P52: 45737.479 | Q52: 45737.472 | R52: - | S52: 45737.513 | U52: - | W52: SIN INFORMACION
A53: 45737.419 | B53: 24805209 | C53: 727094 | D53: Proveedor asignado | E53: JANET | F53: FERNANDEZ HUAYTALLA | G53: DNI | H53: 43909672 | I53: 38 | J53: 991583399 | K53: AVENIDA SIMON BOLIVAR MANZANA 4 Y LOTE 1 COMITE 4 TABLADA DE LURIN CASA NUMERO 325 - | L53: ENTRE A AVENIDA MAMA OLLO Y MANCO KAWI - | M53: VILLA MARIA DEL TRIUNFO | N53: Médico Virtual Medicina General | O53: 45737.424 | P53: 45737.493 | Q53: 45737.478 | R53: - | S53: 45737.515 | U53: - | W53: SIN INFORMACION
A54: 45737.427 | B54: 24805314 | C54: 727105 | D54: Proveedor asignado | E54: JUAN DIEGO | F54: CORNEJO VIDALON | G54: DNI | H54: 74387766 | I54: 25 | J54: 940350063 | K54: CALLE CESAR VALLEJO 251 DEP 301 | L54: ALT CDRA 33 DE VELASCO ASTETE | M54: SANTIAGO DE SURCO | N54: Médico Virtual Medicina General | O54: 45737.432 | P54: 45737.493 | Q54: 45737.485 | R54: - | S54: 45737.498 | U54: - | W54: SIN INFORMACION
A55: 45737.434 | B55: 24805342 | C55: 727109 | D55: Proveedor asignado | E55: YANETH | F55: CABADA PACHACAMA | G55: DNI | H55: 45882728 | J55: 989959448 | K55: JR ANANCUSCO 723 3RA ZONA DE TAHUANTINSUYO | L55: ALT COLEGIO GRAN BRETAÑA | M55: INDEPENDENCIA | N55: Médico Virtual Medicina General | O55: 45737.439 | P55: 45737.447 | Q55: 45737.472 | R55: - | S55: 45737.481 | U55: - | W55: SIN INFORMACION
A56: 45737.433 | B56: 24805524 | C56: 727108 | D56: Proveedor asignado | E56: SANTIAGO JOAO | F56: LUQUE FLORES | G56: DNI | H56: 90308325 | I56: 7 | J56: 904734922 | K56: MANZANA CJ LOTE 2 ETAPA 1 LA ESTANCIA DE LURIN - | L56: PARQUE C LADO - | M56: LURIN | N56: Médico Virtual Pediatría | O56: 45737.437 | P56: 45737.444 | Q56: 45737.496 | R56: - | S56: 45737.502 | U56: - | W56: SIN INFORMACION
A57: 45737.438 | B57: 24805609 | C57: 727112 | D57: Proveedor asignado | E57: FABIANA RUTH ZULEIKA | F57: YATACO CABADA | G57: DNI | H57: 71686044 | I57: 16 | J57: 989959448 | K57: JR ANANCUSCO 723 3RA ZONA DE TAHUANTINSUYO | L57: ALT COLEGIO GRAN BRETAÑA | M57: INDEPENDENCIA | N57: Médico Virtual Medicina General | O57: 45737.503 | P57: 45737.667 | Q57: 45737.656 | R57: - | S57: 45737.669 | U57: - | W57: SIN INFORMACION
A58: 45737.438 | B58: 24805615 | C58: 727113 | D58: Proveedor asignado | E58: JAIME ALFREDO | F58: SALCEDO ANDRES | G58: DNI | H58: 21562887 | I58: 55 | J58: 955911100 | K58: GALVES SILVERA 125 URB. LA VIÑA | L58: RESIDENCIAL PATIÑO - SAN LUIS | M58: SAN LUIS | N58: Médico Virtual Medicina General | O58: 45737.458 | P58: 45737.465 | Q58: 45737.5 | R58: - | S58: 45737.526 | U58: - | W58: SIN INFORMACION
A59: 45737.446 | B59: 24805536 | C59: 727122 | D59: Proveedor asignado | E59: SOLANGE ALEXANDRA | F59: CUBA ACUÑA | G59: DNI | H59: 70096279 | I59: 25 | J59: 912581909 | K59: AV LOS DOMINICOS 273 | L59: ESPALDA DEL COLEGIO JUAN INGUNZA | M59: CALLAO | N59: Médico Virtual Medicina General | O59: 45737.453 | P59: 45737.46 | Q59: 45737.5 | R59: - | S59: 45737.512 | U59: - | W59: SIN INFORMACION
A60: 45737.437 | B60: 24805594 | C60: 727111 | D60: Proveedor asignado | E60: JESUS RIGOBERTO | F60: GUTIERREZ TINEO | G60: DNI | H60: 42273922 | I60: 41 | J60: 907909526 | K60: mz G lote 16 | L60: a dos cuadras de la UPA | M60: VENTANILLA | N60: Médico Virtual Medicina General | O60: 45737.444 | P60: 45737.493 | Q60: 45737.488 | R60: - | S60: 45737.579 | U60: - | W60: SIN INFORMACION
A61: 45737.451 | B61: 24805927 | C61: 727129 | D61: Proveedor asignado | E61: ANDREA STEFANIA | F61: CASTRO GONZALES | G61: DNI | H61: 45902430 | J61: 51990348071 | K61: Ca. Pinerolo, 149, Santiago de Surco, 15023, Peru | L61: El ingreso es por la Avenida PIO XII | M61: SANTIAGO DE SURCO | N61: Médico Virtual Medicina General | O61: 45737.472 | P61: 45737.636 | Q61: 45737.515 | R61: - | S61: 45737.792 | U61: - | W61: SIN INFORMACION
A62: 45737.453 | B62: 24805947 | C62: 727130 | D62: Proveedor asignado | E62: ALESSANDRA LUCIA | F62: RIVERA ESPINOZA | G62: DNI | H62: 78782895 | I62: 10 | J62: 981176534 | K62: ALTURA 7 DE LA AVENIDA COLOMBIA - | L62: ALTURA 7 DE LA AVENIDA COLOMBIA - | M62: PUEBLO LIBRE | N62: Médico Virtual Pediatría | O62: 45737.456 | P62: 45737.493 | Q62: 45737.51 | R62: - | S62: 45737.524 | U62: - | W62: SIN INFORMACION
A63: 45737.453 | B63: 24805949 | C63: 727131 | D63: Proveedor asignado | E63: JORGE | F63: RODRIGUEZ IGLESIAS | G63: DNI | H63: 42633787 | I63: 40 | J63: 998560048 | K63: CALLE ROMA 314 DEPARTAMENTO S04 MIRAFLORES - | L63: A LA ALTURA DE LA CUADRA 9 DE PARDO - | M63: MIRAFLORES | N63: Médico Virtual Medicina General | O63: 45737.456 | P63: 45737.493 | Q63: 45737.489 | R63: - | S63: 45737.53 | U63: - | W63: SIN INFORMACION
A64: 45737.456 | B64: 24805819 | C64: 727136 | D64: Proveedor asignado | E64: ERIKA DEL CARMEN PALOMA | F64: CHAVEZ POVIS | G64: DNI | H64: 72421483 | I64: 20 | J64: 999910074 | K64: ELCUADRO CHACLACAYO MZ F LT 4 | L64: PASANDO ÑAÑA | M64: CHACLACAYO | N64: Médico Virtual Medicina General | O64: 45737.46 | P64: 45737.507 | Q64: 45737.505 | R64: - | S64: 45737.511 | U64: - | W64: SIN INFORMACION
A65: 45737.448 | B65: 24805837 | C65: 727123 | D65: Proveedor asignado | E65: KAREN ISABEL | F65: ASCENCIO CAYO | G65: DNI | H65: 70665970 | I65: 27 | J65: 989010500 | K65: AVENIDA PETIT THOUARS 1944 - | L65: ESTA CERCA EL CRUCE DE CANEVARO CON PETIT THOUARS - | M65: LINCE | N65: Médico Virtual Medicina General | O65: 45737.451 | P65: 45737.459 | Q65: 45737.488 | R65: - | S65: 45737.5 | U65: - | W65: SIN INFORMACION
A66: 45737.467 | B66: 24805991 | C66: 727147 | D66: Proveedor asignado | E66: KARINA PILAR | F66: CARRERO AVANTO | G66: DNI | H66: 8718563 | I66: 58 | J66: 980962574 | K66: Validar direccion con el paciente | L66: Validar direccion con el paciente | M66: SAN MIGUEL | N66: Médico Virtual Medicina General | O66: 45737.472 | P66: 45737.479 | Q66: 45737.516 | R66: - | S66: 45737.536 | U66: - | W66: SIN INFORMACION
A67: 45737.467 | B67: 24806227 | C67: 727143 | D67: Proveedor asignado | E67: YULEISSY CAROLINA | F67: CRUZ ACOSTA | G67: DNI | H67: 48111717 | I67: 32 | J67: 957627002 | K67: AMPLIACION ALTO CERRO VERDE H2 - | L67: A ESPALDAS DE JAPANESES - | M67: UCHUMAYO | N67: Médico Virtual Medicina General | O67: 45737.493 | P67: 45737.501 | Q67: 45737.523 | R67: - | S67: 45737.581 | U67: - | W67: SIN INFORMACION
A68: 45737.469 | B68: 24806262 | C68: 727149 | D68: Proveedor asignado | E68: SARA CAMILA | F68: ARANCIBIA CANCHARI | G68: DNI | H68: 78102824 | I68: 11 | J68: 940919137 | K68: AVENIDA ARNALDO MARQUEZ 679 INTERIOR 604 - | L68: ALTURA DE LA CUADRA 6 DE LA AVENIDA BRASIL - | M68: JESUS MARIA | N68: Médico Virtual Pediatría | O68: 45737.472 | P68: 45737.48 | Q68: 45737.524 | R68: - | S68: 45737.535 | U68: - | W68: SIN INFORMACION
A69: 45737.47 | B69: 24806295 | C69: 727150 | D69: Proveedor asignado | E69: JOVANY | F69: PEREZ CHAVARRY | G69: DNI | H69: 19260252 | I69: 47 | J69: 967964882 | K69: av federico villarreal 259 miraflores segundo piso | L69: toyota mitzui | M69: MIRAFLORES | N69: Médico Virtual Medicina General | O69: 45737.474 | P69: 45737.481 | Q69: 45737.501 | R69: - | S69: 45737.578 | U69: - | W69: SIN INFORMACION
A70: 45737.474 | B70: 24806307 | C70: 727154 | D70: Proveedor asignado | E70: PIERO JESUS ALFONSO | F70: CIPRIANI LEVANO | G70: DNI | H70: 76691076 | I70: 29 | J70: 982731338 | K70: AV MANCO CAPAC 992 DEP 302 | L70: CRUCE CON ISABEL LA CATOLICA | M70: LA VICTORIA | N70: Médico Virtual Medicina General | O70: 45737.486 | P70: 45737.493 | Q70: 45737.524 | R70: - | S70: 45737.526 | U70: - | W70: SIN INFORMACION
A71: 45737.478 | B71: 24806436 | C71: 727159 | D71: Proveedor asignado | E71: CRHISTIAN FARID | F71: PEREZ CASHU | G71: DNI | H71: 72976379 | I71: 28 | J71: 950693526 | K71: CALLE OCTAVIO PAZ MANZANA O LOTE 9 - | L71: ALTURA DE PLAZA VEA ANGAMOS - | M71: SURQUILLO | N71: Médico Virtual Medicina General | O71: 45737.494 | P71: 45737.501 | Q71: 45737.516 | R71: - | S71: 45737.529 | U71: - | W71: SIN INFORMACION
A72: 45737.479 | B72: 24806469 | C72: 727160 | D72: Proveedor asignado | E72: SARA CATALINA | F72: PINEDO MEZA | G72: DNI | H72: 40942370 | I72: 44 | J72: 924034047 | K72: DESEO CONVERSAR CON DOCTOR POR TELEFONO - | L72: - | M72: CARABAYLLO | N72: Médico Virtual Medicina General | O72: 45737.483 | P72: 45737.521 | Q72: 45737.585 | R72: - | S72: 45737.787 | U72: - | W72: SIN INFORMACION
A73: 45737.489 | B73: 24806641 | C73: 727166 | D73: Proveedor asignado | E73: MAURICIO ALONSO | F73: LOZANO LOPEZ | G73: DNI | H73: 91394243 | I73: 5 | J73: 946593468 | K73: LOS CALCULISTAS 183 SANTA FELICIA - | L73: ALTURA CUADRA 5 DE CONSTRUCTORES - | M73: LA MOLINA | N73: Médico Virtual Pediatría | O73: 45737.493 | P73: 45737.5 | Q73: 45737.536 | R73: - | S73: 45737.542 | U73: - | W73: SIN INFORMACION
A74: 45737.503 | B74: 24806900 | C74: 727175 | D74: Proveedor asignado | E74: YANETH | F74: CABADA PACHACAMA | G74: DNI | H74: 45882728 | I74: 35 | J74: 989959448 | K74: JR ANANCUSCO 723 3RA ZONA DE TAHUANTINSUYO | L74: ALT COLEGIO GRAN BRETAÑA | M74: INDEPENDENCIA | N74: Médico Virtual Medicina General | O74: 45737.512 | P74: 45737.519 | Q74: 45737.538 | R74: - | S74: - | U74: - | V74: SI | W74: ENTREGADO | X74: 45743 | Z74: VIVA 1A
A75: 45737.503 | B75: 24806918 | C75: 727177 | D75: Proveedor asignado | E75: CLAUDIA GIULIANA | F75: MATTOS BARRANTES | G75: DNI | H75: 43195364 | I75: 39 | J75: 994405442 | K75: URB JAMES STRONGE B 24 TALARA | L75: CARRETERA DE NEGRITOS | M75: PARIÑAS | N75: Médico Virtual Medicina General | O75: 45737.751 | P75: 45737.812 | Q75: 45737.903 | R75: - | S75: 45737.915 | U75: - | W75: SIN INFORMACION
A76: 45737.505 | B76: 24806847 | C76: 727179 | D76: Proveedor asignado | E76: MARIA DEL ROSARIO | F76: GORDILLO BLANES | G76: DNI | H76: 9163424 | I76: 62 | J76: 996596040 | K76: JIRON BOZOVICH 169 | L76: DEPARTAMENTO 101 ENTRE LAS CUADRAS 9 - 10 DE LA AVENIDA SAN BORJA SUR | M76: SAN BORJA | N76: Médico Virtual Medicina General | O76: 45737.51 | P76: 45737.518 | Q76: 45737.528 | R76: - | S76: 45737.534 | U76: - | W76: SIN INFORMACION
A77: 45737.501 | B77: 24806869 | C77: 727173 | D77: Proveedor asignado | E77: ALVARO FABIAN | F77: VASQUEZ ZAVALETA | G77: DNI | H77: 74162448 | I77: 24 | J77: 921704317 | K77: AVENIDA ARMENDARIZ 480 - | L77: AL FRENTE DE LA DE LA PRE CAYETANO - | M77: MIRAFLORES | N77: Médico Virtual Medicina General | O77: 45737.505 | P77: 45737.512 | Q77: 45737.528 | R77: - | S77: 45737.537 | U77: - | W77: SIN INFORMACION
A78: 45737.506 | B78: 24806984 | C78: 727182 | D78: Proveedor asignado | E78: IZAN CASTIEL | F78: LOARTE MARTINEZ | G78: DNI | H78: 93982502 | I78: 0 | J78: 981527147 | K78: MANZANA Y LOTE 18 BARRIO 2 SECTOR 2 CUARTA ETAPA - | L78: POR EL COLEGIO ELIAS AGUIRRE - | M78: VILLA EL SALVADOR | N78: Médico Virtual Pediatría | O78: 45737.51 | P78: 45737.517 | Q78: - | R78: - | S78: - | U78: - | W78: SIN INFORMACION
A79: 45737.507 | B79: 24806995 | C79: 727183 | D79: Proveedor asignado | E79: INGRID LISETTE | F79: SANTOS MILLONES | G79: DNI | H79: 41358217 | I79: 42 | J79: 972080156 | K79: JIRON TACNA 419 - | L79: A MEDIA A DOS CUADRAS DE LA PLAZA MAYOR DE SURCO - | M79: SANTIAGO DE SURCO | N79: Médico Virtual Medicina General | O79: 45737.511 | P79: 45737.56 | Q79: 45737.534 | R79: - | S79: 45737.537 | U79: - | W79: SIN INFORMACION
A80: 45737.515 | B80: 24807167 | C80: 727188 | D80: Proveedor asignado | E80: LEONARDO MATIAS | F80: NUÑEZ PORTOCARRERO | G80: DNI | H80: 75305467 | I80: 14 | J80: 988302163 | K80: JIRON GERMAN CARRASCO 2030 URB CHACRA RIO SUR | L80: ALTURA DE LA CUADRA 13 DE LA AVENIDA TINGO MARIA - CON ALEJANDRO BERTELO | M80: LIMA | N80: Médico Virtual Pediatría | O80: 45737.522 | P80: 45737.529 | Q80: 45737.542 | R80: - | S80: 45737.794 | U80: - | V80: SI | W80: EN COORDINACION | Z80: VIVA 1A
A81: 45737.519 | B81: 24807235 | C81: 727190 | D81: Proveedor asignado | E81: NIEVES ESTHER | F81: LUCAS CABELLO | G81: DNI | H81: 4058088 | I81: 58 | J81: 994196807 | K81: URBANIZACION SAN ANTONIO DE CARAPONGO MANZANA Q LOTE 10 CALLE 13 - | L81: COLEGIO PERUANO AMERICANO - | M81: LURIGANCHO (CHOSICA) | N81: Médico Virtual Medicina General | O81: 45737.523 | P81: 45737.531 | Q81: 45737.544 | R81: - | S81: 45737.551 | U81: - | W81: SIN INFORMACION
A82: 45737.531 | B82: 24807428 | C82: 727200 | D82: Proveedor asignado | E82: ANDRES EMILIANO | F82: ANDRADE DIAZ | G82: DNI | H82: 75742383 | I82: 29 | J82: 942331865 | K82: A GUSTO PEREZ ARANIBAR 2250 DEPARTAMENTO 1004 TORRE A - | L82: FRENTE A EL PARQUE DE LA PERA - | M82: SAN ISIDRO | N82: Médico Virtual Medicina General | O82: 45737.535 | P82: 45737.542 | Q82: 45737.557 | R82: - | S82: 45737.565 | U82: - | W82: SIN INFORMACION
A83: 45737.543 | B83: 24807634 | C83: 727215 | D83: Proveedor asignado | E83: IAN SANTIAGO | F83: SANTA CRUZ LLANOS | G83: DNI | H83: 90376705 | I83: 7 | J83: 966429857 | K83: CALLE R MANZANA K1 LOTE 18 TERCERA ETAPA DE LA URBANIZACION SANTO DOMINGO CARABAYLLO - | L83: ALTURA DEL PARADERO DEL METROPOLITANO EN LA AVENIDA CONDORCANQUI - | M83: CARABAYLLO | N83: Médico Virtual Pediatría | O83: 45737.563 | P83: 45737.571 | Q83: 45737.577 | R83: - | S83: 45737.593 | U83: - | W83: SIN INFORMACION
A84: 45737.548 | B84: 24807652 | C84: 727221 | D84: Proveedor asignado | E84: ALONDRA VALERIA | F84: PALMA MARQUEZ | G84: DNI | H84: 72497877 | I84: 19 | J84: 998704674 | K84: CALLE TRINITARIA N 195 7MA ZONA EL AGUSTINO | L84: ALTURA CDRA 3 DE LA AV JOSE DE LA RIVAGUERO | M84: EL AGUSTINO | N84: Médico Virtual Medicina General | O84: 45737.552 | P84: 45737.56 | Q84: 45737.589 | R84: - | S84: 45737.598 | U84: - | W84: SIN INFORMACION
A85: 45737.549 | B85: 24807735 | C85: 727224 | D85: Proveedor asignado | E85: LOUSSIANA QORIANKA | F85: BERNAL DE LA FUENTE CHAVEZ | G85: DNI | H85: 73294576 | I85: 15 | J85: 959110261 | K85: ADAN SMITH 118 DPTO 801 LA CALERA | L85: LA PERA CON ADAM SMITH PLAZA VEA DE ANGAMOS | M85: SURQUILLO | N85: Médico Virtual Medicina General | O85: 45737.553 | P85: 45737.56 | Q85: 45737.562 | R85: - | S85: 45737.576 | U85: - | W85: SIN INFORMACION
A86: 45737.552 | B86: 24807777 | C86: 727232 | D86: Proveedor asignado | E86: BRYANNA ALESSANDRA | F86: CALERO REJAS | G86: DNI | H86: 77899038 | I86: 12 | J86: 986670690 | K86: LOS AMARANTOS 1116 DEPARTAMENTO 401 LOS OLIVOS - | L86: PARA - | M86: LOS OLIVOS | N86: Médico Virtual Pediatría | O86: 45737.583 | P86: 45737.618 | Q86: 45737.61 | R86: - | S86: 45737.64 | U86: - | W86: SIN INFORMACION
A87: 45737.551 | B87: 24807699 | C87: 727230 | D87: Proveedor asignado | E87: JANET DEL PILAR | F87: COVEÑAS LOPEZ | G87: DNI | H87: 48523992 | I87: 30 | J87: 913206577 | K87: MARIANO CARRANZA 436 CERCADO DE LIMA | L87: CENTRO DE LABORES FRENTE AL CANAL 4 1 ER PISO - ES UN OBRA | M87: LIMA | N87: Médico Virtual Medicina General | O87: 45737.563 | P87: 45737.571 | Q87: 45737.603 | R87: - | S87: 45737.611 | U87: - | V87: SI | W87: ENTREGADO | X87: 45741 | Z87: VIVA 1A | AA87: SI
A88: 45737.552 | B88: 24807330 | C88: 727233 | D88: Proveedor asignado | E88: SANDRA SARA | F88: GONZALES SANTANA | G88: DNI | H88: 41384633 | I88: 43 | J88: 951293588 | K88: av prolognacion iquitos 2650 dpto 1301 torre | L88: a 2 cdra de av javier prado | M88: LINCE | N88: Médico Virtual Medicina General | O88: 45737.566 | P88: 45737.574 | Q88: 45737.597 | R88: - | S88: 45737.609 | U88: - | W88: SIN INFORMACION
A89: 45737.525 | B89: 24807331 | C89: 727196 | D89: Proveedor asignado | E89: ELSI CLAUDIA | F89: GAMBINI CHAVEZ | G89: DNI | H89: 6780837 | J89: 987724732 | K89: av paseo de la republica 7921 - pto 903 | L89: frente al Colegio Champagnat | M89: SANTIAGO DE SURCO | N89: Médico Virtual Medicina General | O89: 45737.528 | P89: 45737.536 | Q89: 45737.542 | R89: - | S89: 45737.564 | U89: - | W89: SIN INFORMACION
A90: 45737.554 | B90: 24807823 | C90: 727235 | D90: Proveedor asignado | E90: CANDICE | F90: SUAREZ OPPE | G90: DNI | H90: 25817293 | I90: 48 | J90: 940196672 | K90: BRONCA EN AYACUCHO 805 SAN MIGUEL - | L90: COLEGIO CHINO JUAN 23 - | M90: SAN MIGUEL | N90: Médico Virtual Medicina General | O90: 45737.566 | P90: 45737.574 | Q90: 45737.615 | R90: - | S90: 45737.624 | U90: - | W90: SIN INFORMACION
A91: 45737.555 | B91: 24807835 | C91: 727236 | D91: Proveedor asignado | E91: SILVIA GABRIELA | F91: DUHARTE MONTERO | G91: DNI | H91: 25720465 | I91: 62 | J91: 997524528 | K91: AVENIDA JORGE CHAVEZ 375 DEPARTAMENTO 701 MIRAFLORES - | L91: A TRES CUADRAS DEL CRUCE DE LA AVENIDA PARDO CON LA AVENIDA ESPINAR DIRECCION AL MALECON - | M91: MIRAFLORES | N91: Médico Virtual Medicina General | O91: 45737.624 | P91: 45737.665 | Q91: 45737.665 | R91: - | S91: - | U91: - | W91: SIN INFORMACION
A92: 45737.562 | B92: 24807917 | C92: 727239 | D92: Proveedor asignado | E92: VICTOR JULIAN | F92: CCAHUANA ZAVALA | G92: DNI | H92: 9918271 | I92: 48 | J92: 999951514 | K92: LAS DALIAS 431 - | L92: ALTURA DE LA CUADRA 5 DE LA AVENIDA LOS INGENIEROS - | M92: SANTIAGO DE SURCO | N92: Médico Virtual Medicina General | O92: 45737.565 | P92: 45737.573 | Q92: 45737.608 | R92: - | S92: 45737.619 | U92: - | W92: SIN INFORMACION
A93: 45737.572 | B93: 24808068 | C93: 727251 | D93: Proveedor asignado | E93: ALEJANDRO HISAO | F93: YAMASHIRO ALVAREZ | G93: DNI | H93: 46732092 | I93: 34 | J93: 941026966 | K93: EL NINO TOMAS ALEJANDRO 13:15 CERQUILLO - | L93: EDIFICIO VERDE ALTURA DE LA CUADRATURA - | M93: SURQUILLO | N93: Médico Virtual Medicina General | O93: 45737.585 | P93: 45737.618 | Q93: 45737.611 | R93: - | S93: 45737.622 | U93: - | W93: SIN INFORMACION
A94: 45737.573 | B94: 24808019 | C94: 727253 | D94: Proveedor asignado | E94: ANGIE | F94: REBAZA MONTOYA | G94: DNI | H94: 43014240 | I94: 39 | J94: 959069212 | K94: HOTEL CASA ANDINA SELECT HABITACION 220 | L94: A 10 MIN DE AGENCIA CRUZ DEL SUR | M94: PARACAS | N94: Médico Virtual Medicina General | O94: 45737.625 | P94: 45737.66 | Q94: 45737.668 | R94: - | S94: 45737.681 | U94: - | W94: SIN INFORMACION
A95: 45737.571 | B95: 24808056 | C95: 727249 | D95: Proveedor asignado | E95: ESTRELLA ROSANNA | F95: TORRES PRADA | G95: DNI | H95: 8451467 | I95: 60 | J95: 916664210 | K95: HABLANDO MARQUEZ 1440 INTERIOR 103 - | L95: AL COSTADO DEL BANCO DE CREDITO DE LA 14 DE ARNALDO MARQUEZ - | M95: JESUS MARIA | N95: Médico Virtual Medicina General | O95: 45737.654 | P95: 45737.703 | Q95: 45737.669 | R95: - | S95: 45737.676 | U95: - | W95: SIN INFORMACION
A96: 45737.574 | B96: 24808107 | C96: 727256 | D96: Proveedor asignado | E96: PABLO ANTONIO JAVIER | F96: CUETO AGUILAR | G96: DNI | H96: 40851249 | J96: 995574206 | K96: calle santa prisca 156 | L96: frente a parque carlos lison | M96: LIMA | N96: Médico Virtual Medicina General | O96: 45737.586 | P96: 45737.618 | Q96: 45737.624 | R96: - | S96: 45737.652 | U96: - | V96: SI | W96: CANCELADO POR PACIENTE | X96: 45741 | Z96: VIVA 1A | AA96: SI
A97: 45737.578 | B97: 24808170 | C97: 727260 | D97: Proveedor asignado | E97: AUSTING NICOLAS | F97: CARRION SEGUNDO | G97: DNI | H97: 77618310 | I97: 12 | J97: 969389017 | K97: AV NICOLAS AYLLON 7548 | L97: CONDOIMINIOS VILLA SANTA CLARA BLOQUE 16 DPTO 703 - PUERTA 2 | M97: ATE | N97: Médico Virtual Pediatría | O97: 45737.583 | P97: 45737.618 | Q97: 45737.641 | R97: - | S97: 45737.654 | U97: - | W97: SIN INFORMACION
A98: 45737.585 | B98: 24808279 | C98: 727269 | D98: Proveedor asignado | E98: OSCAR ARMANDO | F98: MORALES YSLA | G98: DNI | H98: 74024522 | I98: 28 | J98: 989343659 | K98: JIRON CASTILLA 751 | L98: PISO 5 OFICINA 501 GALERIA SANTA PATRICIA | M98: MAGDALENA DEL MAR | N98: Médico Virtual Medicina General | O98: 45737.588 | P98: 45737.596 | Q98: 45737.683 | R98: - | S98: - | U98: - | V98: SI | W98: NO CONTESTA
A99: 45737.585 | B99: 24808231 | C99: 727271 | D99: Proveedor asignado | E99: SILVIA DEL CARMEN | F99: PALACIOS OBREGON | G99: DNI | H99: 71234707 | I99: 33 | J99: 980702807 | K99: MZ G LOTE 30 ISRAEL | L99: ALTURA DEL COLEGIO CARLOS NORIEGA JIMENEZ A 3 CDRS | M99: SAN JUAN DE LURIGANCHO | N99: Médico Virtual Medicina General | O99: 45737.589 | P99: 45737.597 | Q99: 45737.654 | R99: - | S99: 45737.749 | U99: - | W99: SIN INFORMACION
A100: 45737.585 | B100: 24808278 | C100: 727268 | D100: Proveedor asignado | E100: CARLOS ADRIAN | F100: MONGE GIL | G100: DNI | H100: 78737003 | I100: 10 | J100: 932915460 | K100: CALLE ECOLOGICA MANZANA E LOTE 32 CHORRILLOS - | L100: ENTRE EL CRUCE DE DEFENSORES DEL MORRO CON AVENIDA HORIZONTES - | M100: CHORRILLOS | N100: Médico Virtual Pediatría | O100: 45737.588 | P100: 45737.596 | Q100: 45737.658 | R100: - | S100: - | U100: - | W100: SIN INFORMACION
A101: 45737.585 | B101: 24808286 | C101: 727272 | D101: Proveedor asignado | E101: JESSY ISABEL | F101: HUERTA VENEGAS | G101: DNI | H101: 25627013 | I101: 61 | J101: 972875873 | K101: MERCEDES GALLAGHER 253 SAN MIGUEL - | L101: FRENTE A PLAZA SAN MIGUEL - | M101: SAN MIGUEL | N101: Médico Virtual Medicina General | O101: 45737.589 | P101: 45737.597 | Q101: 45737.683 | R101: - | S101: 45737.688 | U101: - | W101: SIN INFORMACION
A102: 45737.588 | B102: 24808327 | C102: 727274 | D102: Proveedor asignado | E102: ALEJANDRO HISAO | F102: YAMASHIRO ALVAREZ | G102: DNI | H102: 46732092 | I102: 34 | J102: 941026966 | K102: AV TOMAS MARZO 1315 SURQUILLO | L102: 13 DE TOMAS MARZANO | M102: SURQUILLO | N102: Médico Virtual Medicina General | O102: 45737.592 | P102: 45737.632 | Q102: - | R102: - | S102: - | U102: - | W102: SIN INFORMACION
...

Sheet HOJA 3 MEDICAMENTOS
A1: Fecha | B1: NúmeroPedido | C1: Canal Estratégico | D1: Subcanal | E1: Contratante | F1: Anillo | G1: DNI | H1: Correo | I1: direccionEnvio | J1: latitudEnvio | K1: Distrito | L1: EstadoPedido | M1: TipoDespacho | N1: Fecha - Día | O1: Rango Hora Entrega | P1: CheckIn_Pedido | Q1: Entregado_Pedido
A2: 45742 | B2: DMI-126087 | C2: Express | D2: VIVA1A | E2: PUNTO VISUAL S.A. | F2: Anillo 2 | G2: 70422204 | I2: Jiron Cristobal de Peralta Sur, 349, Santiago de Surco | J2: -12113688 | K2: Santiago de Surco | L2: Entregado | M2: Express | N2: 26 | O2: 9:12 AM - 12:12 PM | P2: 3/26/2025 10:43:10 AM | Q2: 3/26/2025 10:48:23 AM
A3: 45742 | B3: DMI-126120 | C3: Express | D3: VIVA1A | E3: AMERICA MOVIL PERU S.A.C. | F3: Anillo 5 | G3: 43454029 | I3: Calle los cedros 173 urbanización la alborada | J3: -11910451 | K3: Comas | L3: Entregado | M3: Express | N3: 26 | O3: 10:24 AM - 2:24 PM | P3: 3/26/2025 12:35:17 PM | Q3: 3/26/2025 12:35:31 PM
A4: 45742 | B4: DMI-126143 | C4: Express | D4: VIVA1A | E4: ADMINISTRACION FOOD REGIONAL S.A.C. | F4: Anillo 2 | G4: 46294397 | I4: TIRABANTI 281 | J4: -12143508 | K4: Barranco | L4: Entregado | M4: Express | N4: 26 | O4: 11:06 AM - 2:06 PM | P4: 3/26/2025 1:56:13 PM | Q4: 3/26/2025 1:59:15 PM
A5: 45741 | B5: DMI-126008 | C5: Express | D5: VIVA1A | F5: Anillo 3 | G5: 9764276 | I5: AV. LOS GORRIONES 235 DPTO 613 BLOCK C - CHORRILLOS | J5: -12181916 | K5: Chorrillos | L5: Entregado | M5: Express | N5: 25 | O5: 9:47 PM - 1:47 AM | P5: 3/25/2025 11:30:07 PM | Q5: 3/25/2025 11:37:13 PM
A6: 45741 | B6: DMI-126014 | C6: Express | D6: VIVA1A | F6: Anillo 3 | G6: 62712992 | I6: CALLE PIEDRA REDONDA MANZANA D10 LOTE 46 LOS CEDROS DE VILLA - | J6: -12205388 | K6: Chorrillos | L6: Entregado | M6: Express | N6: 25 | O6: 8:36 PM - 12:36 AM | P6: 3/25/2025 11:14:59 PM | Q6: 3/25/2025 11:18:09 PM
A7: 45741 | B7: DMI-126036 | C7: Express | D7: VIVA1A | F7: Anillo 2 | G7: 91040753 | I7: JR JACARANDA 370 DPT 401 | J7: -12120750 | K7: Santiago de Surco | L7: Entregado | M7: Express | N7: 25 | O7: 9:56 PM - 12:56 AM | P7: 3/25/2025 10:46:44 PM | Q7: 3/26/2025 12:14:08 AM
A8: 45742 | B8: DMI-126046 | C8: Express | D8: VIVA1A | F8: Anillo 2 | G8: 91553866 | I8: JIRON JACARANDA 570 DEPARTAMENTO 202 -, SANTIAGO DE SURCO | J8: -12122898 | K8: Santiago de Surco | L8: Entregado | M8: Express | N8: 26 | O8: 7:24 AM - 10:24 AM | P8: 3/26/2025 8:30:44 AM | Q8: 3/26/2025 8:31:34 AM
A9: 45742 | B9: DMI-126048 | C9: Express | D9: VIVA1A | F9: Anillo 5 | G9: 46408946 | I9: AVENIDA LURIGANCHO 1076- San Juan de Lurigancho, Perú | J9: -12016682 | K9: San Juan de Lurigancho | L9: Entregado | M9: Express | N9: 26 | O9: 7:29 AM - 11:29 AM | P9: 3/26/2025 8:56:59 AM | Q9: 3/26/2025 8:59:09 AM
A10: 45742 | B10: DMI-126070 | C10: Express | D10: VIVA1A | F10: Anillo 4 | G10: 75352626 | I10: COLCABAMBA 249 DPTO 201 | J10: -11997038 | K10: Los Olivos | L10: Entregado | M10: Express | N10: 26 | O10: 8:42 AM - 12:42 PM | P10: 3/26/2025 12:25:57 PM | Q10: 3/26/2025 12:28:34 PM
A11: 45742 | B11: DMI-126071 | C11: Express | D11: VIVA1A | F11: Anillo 1 | G11: 70431471 | I11: AVENIDA WILLIAMS 233 DEPARTAMENTO 101 - SURQUILLO | J11: -12113795 | K11: Surquillo | L11: Entregado | M11: Express | N11: 26 | O11: 8:45 AM - 11:45 AM | P11: 3/26/2025 10:12:47 AM | Q11: 3/26/2025 10:13:48 AM
A12: 45742 | B12: DMI-126075 | C12: Express | D12: VIVA1A | F12: Anillo 5 | G12: 78303691 | I12: mariscal cáceres Mz b 16 lte22 | J12: -11959738 | K12: San Juan de Lurigancho | L12: Entregado | M12: Express | N12: 26 | O12: 8:50 AM - 12:50 PM | P12: 3/26/2025 12:16:06 PM | Q12: 3/26/2025 12:16:20 PM
A13: 45742 | B13: DMI-126078 | C13: Express | D13: VIVA1A | F13: Anillo 5 | G13: 40842480 | I13: CALLE C 1 (JIRON H) S/N CONDOMINIO MAMBO 3, dto 606 | J13: -11933200 | K13: Comas | L13: Entregado | M13: Express | N13: 26 | O13: 8:53 AM - 12:53 PM | P13: 3/26/2025 11:43:31 AM | Q13: 3/26/2025 11:43:44 AM
A14: 45742 | B14: DMI-126081 | C14: Express | D14: VIVA1A | F14: Anillo 4 | G14: 77588181 | I14: Jr. Fitzcarrald 1234, Los Olivos | J14: -11997318 | K14: Los Olivos | L14: Entregado | M14: Express | N14: 26 | O14: 9:02 AM - 1:02 PM | P14: 3/26/2025 11:52:04 AM | Q14: 3/26/2025 11:53:50 AM
A15: 45742 | B15: DMI-126085 | C15: Express | D15: VIVA1A | F15: Anillo 5 | G15: 42928515 | I15: jr Kalasasaya 1062 mangomarca | J15: -12015987 | K15: San Juan de Lurigancho | L15: Entregado | M15: Express | N15: 26 | O15: 9:09 AM - 1:09 PM | P15: 3/26/2025 11:20:23 AM | Q15: 3/26/2025 11:20:32 AM
A16: 45742 | B16: DMI-126092 | C16: Express | D16: VIVA1A | F16: Anillo 4 | G16: 44632024 | H16: kristyarteaga2015@gmail.com | I16: CALLE G MZ G 16 LOTE 11 SECTOR 5 BOCANEGRA | J16: -12024413 | K16: Callao - Callao | L16: Entregado | M16: Express | N16: 26 | O16: 9:17 AM - 1:17 PM | P16: 3/26/2025 11:17:58 AM | Q16: 3/26/2025 11:27:14 AM
A17: 45742 | B17: DMI-126100 | C17: Express | D17: VIVA1A | F17: Anillo 2 | G17: 78710296 | I17: AVENIDA VICUS Cdr 4 MANZANA Y LOTE 86 URBANIZACION LA CAPULLANA SANTIAGO DE SURCO | J17: -12136138 | K17: Santiago de Surco | L17: Entregado | M17: Express | N17: 26 | O17: 9:39 AM - 12:39 PM | P17: 3/26/2025 10:45:33 AM | Q17: 3/26/2025 10:46:54 AM
A18: 45742 | B18: DMI-126107 | C18: Express | D18: VIVA1A | F18: Anillo 4 | G18: 78755314 | I18: Calle San Ernesto 6214 Santa Luisa 2da etapa - Los olivos | J18: -11957613 | K18: Los Olivos | L18: Entregado | M18: Express | N18: 26 | O18: 10:02 AM - 2:02 PM | P18: 3/26/2025 12:49:41 PM | Q18: 3/26/2025 12:50:11 PM
A19: 45742 | B19: DMI-126114 | C19: Express | D19: VIVA1A | F19: Anillo 5 | G19: 77546741 | I19: JR MAMACONA 659 URB MANGOMARCA, SJL | J19: -12009788 | K19: San Juan de Lurigancho | L19: Entregado | M19: Express | N19: 26 | O19: 10:16 AM - 2:16 PM | P19: 3/26/2025 12:49:02 PM | Q19: 3/26/2025 12:49:14 PM
A20: 45742 | B20: DMI-126117 | C20: Express | D20: VIVA1A | F20: Anillo 4 | G20: 91736444 | I20: JIRON LAS ROSAS 162 dpto 202 torre 6 CONDOMINIO PASEO TOMAS VALLE - | J20: -12010433 | K20: Los Olivos | L20: Entregado | M20: Express | N20: 26 | O20: 10:19 AM - 2:19 PM | P20: 3/26/2025 12:24:06 PM | Q20: 3/26/2025 12:24:22 PM
A21: 45742 | B21: DMI-126119 | C21: Express | D21: VIVA1A | F21: Anillo 5 | G21: 72509032 | I21: UCV 100 LT 42 ZONA F HUAYCAN | J21: -12017288 | K21: Ate | L21: Entregado | M21: Express | N21: 26 | O21: 10:24 AM - 2:24 PM | P21: 3/26/2025 12:40:45 PM | Q21: 3/26/2025 12:41:08 PM
A22: 45742 | B22: DMI-126126 | C22: Express | D22: VIVA1A | F22: Anillo 5 | G22: 9356964 | I22: JR PARURO 111 COOPERATIVA 27 DE ABRIL(limite con santa anita) | J22: -12055963 | K22: Ate | L22: Entregado | M22: Express | N22: 26 | O22: 10:36 AM - 2:36 PM | P22: 3/26/2025 12:48:02 PM | Q22: 3/26/2025 12:48:17 PM
A23: 45742 | B23: DMI-126127 | C23: Express | D23: VIVA1A | F23: Anillo 2 | G23: 41247452 | H23: jfarfan2509@gmail.com | I23: CALLE BACA FLOR 104 DPT 402B, PUEBLO LIBRE | J23: -12073147 | K23: Pueblo Libre | L23: Entregado | M23: Express | N23: 26 | O23: 10:40 AM - 1:40 PM | P23: 3/26/2025 12:20:37 PM | Q23: 3/26/2025 12:22:11 PM
A24: 45742 | B24: DMI-126134 | C24: Express | D24: VIVA1A | F24: Anillo 2 | G24: 45033722 | I24: Jirón Ayacucho 649, Magdalena del Mar | J24: -12086940 | K24: Magdalena del Mar | L24: Entregado | M24: Express | N24: 26 | O24: 10:51 AM - 1:51 PM | P24: 3/26/2025 1:12:01 PM | Q24: 3/26/2025 1:13:46 PM
A25: 45742 | B25: DMI-126136 | C25: Express | D25: VIVA1A | F25: Anillo 4 | G25: 47623959 | H25: KBALLENALARA@GMAIL.COM | I25: Es chicmabamba, mzi lote 2 | J25: -11999388 | K25: San Martín de Porres | L25: Entregado | M25: Express | N25: 26 | O25: 10:52 AM - 2:52 PM | P25: 3/26/2025 2:42:08 PM | Q25: 3/26/2025 2:42:20 PM
A26: 45742 | B26: DMI-126140 | C26: Express | D26: VIVA1A | F26: Anillo 1 | G26: 46191064 | I26: AV MARISCAL CACERES 327 DPTO 601 | J26: -12119350 | K26: Surquillo | L26: Entregado | M26: Express | N26: 26 | O26: 10:57 AM - 1:57 PM | P26: 3/26/2025 12:18:38 PM | Q26: 3/26/2025 12:22:23 PM
A27: 45742 | B27: DMI-126145 | C27: Express | D27: VIVA1A | F27: Anillo 4 | G27: 9798504 | I27: AV. COLONIAL 5015 DPTO G 103 - CONDOMINIO EL PRADO SAN JOSE - CALLAO | J27: -12051933 | K27: Callao - Callao | L27: Entregado | M27: Express | N27: 26 | O27: 11:14 AM - 3:14 PM | P27: 3/26/2025 2:03:01 PM | Q27: 3/26/2025 2:05:11 PM
A28: 45742 | B28: DMI-126147 | C28: Express | D28: VIVA1A | F28: Anillo 5 | G28: 10631813 | I28: LOS TALLADORES 248 URB LOS ARTESANOS, ATE | J28: -12062963 | K28: Ate | L28: Entregado | M28: Express | N28: 26 | O28: 11:09 AM - 3:09 PM | P28: 3/26/2025 3:06:37 PM | Q28: 3/26/2025 3:09:47 PM
A29: 45742 | B29: DMI-126151 | C29: Express | D29: VIVA1A | F29: Anillo 3 | G29: 91240947 | I29: AV COSTANER 970 DPT 509, LIMA, LIMA, SAN MIGUEL | J29: -12087159 | K29: San Miguel | L29: Entregado | M29: Express | N29: 26 | O29: 11:24 AM - 3:24 PM | P29: 3/26/2025 12:48:03 PM | Q29: 3/26/2025 12:54:07 PM
A30: 45742 | B30: DMI-126157 | C30: Express | D30: VIVA1A | F30: Anillo 5 | G30: 42252177 | H30: mirely.atuncar@hotmail.com | I30: SECTOR 2 GRUPO 19 MZ D LT 24 -. VILLA EL SALVADOR. | J30: -12211663 | K30: Villa El Salvador | L30: Entregado | M30: Express | N30: 26 | O30: 11:31 AM - 3:31 PM | P30: 3/26/2025 1:07:47 PM | Q30: 3/26/2025 1:10:14 PM
A31: 45742 | B31: DMI-126164 | C31: Express | D31: VIVA1A | F31: Anillo 2 | G31: 91025289 | H31: milagrosmarcenaro@gmail.com | I31: jr emilio altaos 697 | J31: -12079988 | K31: Lince | L31: Entregado | M31: Express | N31: 26 | O31: 11:55 AM - 2:55 PM | P31: 3/26/2025 12:42:48 PM | Q31: 3/26/2025 12:43:08 PM
A32: 45742 | B32: DMI-126169 | C32: Express | D32: VIVA1A | F32: Anillo 6 | G32: 9549304 | I32: CALLE AUGUSTO SALAVERRY 272 URBANIZACION LUCYANA CARABAYLLO | J32: -11893483 | K32: Carabayllo | L32: Entregado | M32: Express | N32: 26 | O32: 12:15 PM - 6:15 PM | P32: 3/26/2025 3:20:07 PM | Q32: 3/26/2025 3:20:28 PM
A33: 45742 | B33: DMI-126170 | C33: Express | D33: VIVA1A | F33: Anillo 6 | G33: 9549304 | I33: CALLE AUGUSTO SALAVERRY 272 URBANIZACION LUCYANA CARABAYLLO | J33: -11893483 | K33: Carabayllo | L33: Entregado | M33: Express | N33: 26 | O33: 12:29 PM - 6:29 PM | P33: 3/26/2025 3:21:20 PM | Q33: 3/26/2025 3:21:49 PM
A34: 45742 | B34: DMI-126174 | C34: Express | D34: VIVA1A | F34: Anillo 4 | G34: 74835968 | I34: Avenida mariano ignacio prado 3014 san Martín de Porres | J34: -12028113 | K34: San Martín de Porres | L34: Entregado | M34: Express | N34: 26 | O34: 12:51 PM - 4:51 PM | P34: 3/26/2025 2:21:39 PM | Q34: 3/26/2025 2:24:17 PM
A35: 45742 | B35: DMI-126178 | C35: Express | D35: VIVA1A | F35: Anillo 2 | G35: 10547568 | I35: AVENIDA LA MERCED 822 DEP 301 | J35: -12134995 | K35: Santiago de Surco | L35: Entregado | M35: Express | N35: 26 | O35: 1:05 PM - 4:05 PM | P35: 3/26/2025 2:01:37 PM | Q35: 3/26/2025 2:03:40 PM
A36: 45742 | B36: DMI-126183 | C36: Express | D36: VIVA1A | F36: Anillo 1 | G36: 48946399 | I36: BASADRE 347 SAN ISIDRO | J36: -12094782 | K36: San Isidro | L36: Entregado | M36: Express | N36: 26 | O36: 1:24 PM - 4:24 PM | P36: 3/26/2025 2:50:30 PM | Q36: 3/26/2025 2:52:36 PM
A37: 45742 | B37: DMI-126185 | C37: Express | D37: VIVA1A | F37: Anillo 3 | G37: 7388655 | I37: CALLE CABO BLANCO Mz C5 Lt 20 URB LOS CEDROS | J37: -12202913 | K37: Chorrillos | L37: Entregado | M37: Express | N37: 26 | O37: 1:31 PM - 5:31 PM | P37: 3/26/2025 4:05:37 PM | Q37: 3/26/2025 4:11:26 PM
A38: 45742 | B38: DMI-126188 | C38: Express | D38: VIVA1A | F38: Anillo 1 | G38: 73177689 | I38: CALLE HARRINGTON 309 DPT 101, SURQUILLO | J38: -12114463 | K38: Surquillo | L38: Entregado | M38: Express | N38: 26 | O38: 1:44 PM - 4:44 PM | P38: 3/26/2025 4:47:09 PM | Q38: 3/26/2025 4:49:07 PM
A39: 45742 | B39: DMI-126189 | C39: Express | D39: VIVA1A | F39: Anillo 2 | G39: 45943138 | H39: jorge.medicina.24@gmail.com | I39: Av Oscar R Benavides 1111 Block G dep 903 - Condominio alto Benavides | J39: -12047997 | K39: Cercado de Lima | L39: Entregado | M39: Express | N39: 26 | O39: 1:47 PM - 4:47 PM | P39: 3/26/2025 3:14:52 PM | Q39: 3/26/2025 3:17:22 PM
A40: 45742 | B40: DMI-126192 | C40: Express | D40: VIVA1A | F40: Anillo 5 | G40: 45299105 | H40: gianjf@hotmail.com | I40: Jirón Santa Leonor 6336, urbanización santa luisa primera etapa, Comas, | J40: -11951740 | K40: Comas | L40: Entregado | M40: Express | N40: 26 | O40: 1:52 PM - 5:52 PM | P40: 3/26/2025 5:34:27 PM | Q40: 3/26/2025 5:37:26 PM
A41: 45742 | B41: DMI-126193 | C41: Express | D41: VIVA1A | F41: Anillo 4 | G41: 9865932 | I41: MANZANA B LOTE 30 urb jasminez 4 etapa callao | J41: -12006213 | K41: Callao - Callao | L41: Entregado | M41: Express | N41: 26 | O41: 1:57 PM - 5:57 PM | P41: 3/26/2025 4:02:00 PM | Q41: 3/26/2025 4:02:50 PM
A42: 45742 | B42: DMI-126196 | C42: Express | D42: VIVA1A | F42: Anillo 2 | G42: 72589606 | I42: EL CORTIJO 442 DEPARTAMENTO 401 | J42: -12098547 | K42: Santiago de Surco | L42: Entregado | M42: Express | N42: 26 | O42: 2:06 PM - 5:06 PM | P42: 3/26/2025 4:27:02 PM | Q42: 3/26/2025 4:27:34 PM
A43: 45742 | B43: DMI-126205 | C43: Express | D43: VIVA1A | F43: Anillo 2 | G43: 43644355 | I43: Jr Rodolfo rutee 232 | J43: -12094614 | K43: Magdalena del Mar | L43: Entregado | M43: Express | N43: 26 | O43: 2:29 PM - 5:29 PM | P43: 3/26/2025 6:43:53 PM | Q43: 3/26/2025 6:45:05 PM
A44: 45742 | B44: DMI-126209 | C44: Express | D44: VIVA1A | F44: Anillo 2 | G44: 9878695 | I44: Jirón Navarra 417 Dpto 302, Santiago de Surco, Perú | J44: -12126290 | K44: Santiago de Surco | L44: Entregado | M44: Express | N44: 26 | O44: 2:31 PM - 5:31 PM | P44: 3/26/2025 5:01:43 PM | Q44: 3/26/2025 5:01:55 PM
A45: 45742 | B45: DMI-126212 | C45: Express | D45: VIVA1A | F45: Anillo 2 | G45: 73977767 | I45: CALLE LAS MAGNOLIAS MZ I 2 LOTE 1 - PISO 5 (bodega las magnolias )) | J45: -12141188 | K45: Santiago de Surco | L45: Entregado | M45: Express | N45: 26 | O45: 2:40 PM - 5:40 PM | P45: 3/26/2025 5:20:30 PM | Q45: 3/26/2025 5:20:41 PM
A46: 45742 | B46: DMI-126222 | C46: Express | D46: VIVA1A | F46: Anillo 6 | G46: 70404976 | I46: Calle Los Zorzales, Mz B Lt 18 ,Lurín | J46: -12238863 | K46: Lurin | L46: Entregado | M46: Express | N46: 26 | O46: 3:01 PM - 9:01 PM | P46: 3/26/2025 5:35:53 PM | Q46: 3/26/2025 5:38:29 PM
A47: 45742 | B47: DMI-126227 | C47: Express | D47: VIVA1A | F47: Anillo 2 | G47: 74190657 | I47: AVENIDA BOULEVARD DE SURCO 416 DEPARTAMENTO 401 SAN BORJA - | J47: -12091443 | K47: San Borja | L47: Entregado | M47: Express | N47: 26 | O47: 3:04 PM - 6:04 PM | P47: 3/26/2025 4:41:51 PM | Q47: 3/26/2025 4:45:44 PM
A48: 45742 | B48: DMI-126232 | C48: Express | D48: VIVA1A | F48: Anillo 5 | G48: 77986806 | I48: PASAJE JOSE PEZET 155 RETABLO - COMAS | J48: -11936629 | K48: Comas | L48: Entregado | M48: Express | N48: 26 | O48: 3:19 PM - 7:19 PM | P48: 3/26/2025 5:09:54 PM | Q48: 3/26/2025 5:11:07 PM
A49: 45742 | B49: DMI-126242 | C49: Express | D49: VIVA1A | F49: Anillo 5 | G49: 44673697 | I49: AVENIDA LOS POSTES OESTE 189 SAN JUAN DE LURIGANCHO - | J49: -11997920 | K49: San Juan de Lurigancho | L49: Entregado | M49: Express | N49: 26 | O49: 3:44 PM - 7:44 PM | P49: 3/26/2025 6:06:02 PM | Q49: 3/26/2025 6:06:20 PM
A50: 45742 | B50: DMI-126244 | C50: Express | D50: VIVA1A | F50: Anillo 3 | G50: 71466608 | I50: Av de los Precursores 960, San Miguel, Perú | J50: -12068776 | K50: San Miguel | L50: Entregado | M50: Express | N50: 26 | O50: 3:45 PM - 7:45 PM | P50: 3/26/2025 6:50:21 PM | Q50: 3/26/2025 6:50:43 PM
A51: 45742 | B51: DMI-126245 | C51: Express | D51: VIVA1A | F51: Anillo 2 | G51: 78570161 | I51: JIRON DON BOSCO 473 DEPARTAMENTO 401 -, BREÑA | J51: -12060108 | K51: Breña | L51: Entregado | M51: Express | N51: 26 | O51: 3:46 PM - 6:46 PM | P51: 3/26/2025 5:04:33 PM | Q51: 3/26/2025 5:04:55 PM
A52: 45742 | B52: DMI-126248 | C52: Express | D52: VIVA1A | F52: Anillo 2 | G52: 78876403 | I52: Jirón Ariadna 180 dpto 302,- SANTIAGO DE SURCO | J52: -12162138 | K52: Santiago de Surco | L52: Entregado | M52: Express | N52: 26 | O52: 3:49 PM - 6:49 PM | P52: 3/26/2025 6:30:04 PM | Q52: 3/26/2025 6:31:14 PM
... A62: 45742 | B62: DMI-126308 | C62: Express | D62: VIVA1A | F62: Anillo 2 | G62: 7867286 | I62: CALLE LAS MAGNOLIAS 173 DPTO 402 - Barranco | J62: -12140193 | K62: Barranco | L62: Entregado | M62: Express | N62: 26 | O62: 5:57 PM - 8:57 PM | P62: 3/26/2025 6:42:25 PM | Q62: 3/26/2025 6:42:38 PM
A63: 45744 | B63: DMI-126885 | C63: Express | D63: VIVA1A | E63: UNIDAD EJECUTORA 003 CORTE SUPERIOR DE JUSTICIA DE LIMA | F63: Anillo 1 | G63: 47481744 | I63: Jr. Leonardo Barbieri 1340 | J63: Surquillo | K63: Lima | L63: Entregado | M63: Express | N63: 45744 | O63: 3:06 PM - 6:06 PM | P63: 3/28/2025 4:06:56 PM | Q63: 3/28/2025 4:07:17 PM
A64: 45744 | B64: DMI-126892 | C64: Express | D64: VIVA1A | E64: MURILLO OLAYA GIPSY DIANNETH | F64: Anillo 4 | G64: 71772633 | I64: Juan Pablo II MzA4, lt o4 | J64: Callao - Bellavista | K64: Callao | L64: Entregado | M64: Express | N64: 45744 | O64: 3:15 PM - 7:15 PM | P64: 3/28/2025 5:59:14 PM | Q64: 3/28/2025 6:10:26 PM
A65: 45744 | B65: DMI-126714 | C65: Express | D65: VIVA1A | F65: Anillo 5 | G65: 78457383 | I65: CONDOMINIO VILLAFLORES MANZANA E LOTE 14 VILLA EL SALVADOR | J65: Villa El Salvador | K65: Lima | L65: Entregado | M65: Express | N65: 45744 | O65: 7:25 AM - 11:25 AM | P65: 3/28/2025 9:11:15 AM | Q65: 3/28/2025 9:12:38 AM
A66: 45744 | B66: DMI-126724 | C66: Express | D66: VIVA1A | F66: Anillo 4 | G66: 79810156 | I66: CALLE LAS GAVIOTAS 288 DPTO 502, CALLAO, BELLAVISTA | J66: Callao - Bellavista | K66: Callao | L66: Entregado | M66: Express | N66: 45744 | O66: 7:57 AM - 11:57 AM | P66: 3/28/2025 9:42:39 AM | Q66: 3/28/2025 9:42:51 AM
A67: 45744 | B67: DMI-126725 | C67: Express | D67: VIVA1A | F67: Anillo 4 | G67: 77339002 | I67: calle campania 216 | J67: Callao - Bellavista | K67: Callao | L67: Entregado | M67: Express | N67: 45744 | O67: 8:10 AM - 12:10 PM | P67: 3/28/2025 10:14:24 AM | Q67: 3/28/2025 10:15:20 AM
A68: 45744 | B68: DMI-126728 | C68: Express | D68: VIVA1A | F68: Anillo 2 | G68: 21867894 | I68: JIRON LA MADRILEÑA 395 - SAN LUIS | J68: San Luis | K68: Lima | L68: Entregado | M68: Express | N68: 45744 | O68: 8:13 AM - 11:13 AM | P68: 3/28/2025 9:47:08 AM | Q68: 3/28/2025 9:49:39 AM
A69: 45744 | B69: DMI-126732 | C69: Express | D69: VIVA1A | F69: Anillo 2 | G69: 70650569 | I69: CALLE ISLAS ANTILLAS 159 DPTO 604 - Pueblo Libre | J69: Pueblo Libre | K69: Lima | L69: Entregado | M69: Express | N69: 45744 | O69: 8:26 AM - 11:26 AM | P69: 3/28/2025 9:52:34 AM | Q69: 3/28/2025 9:53:50 AM
A70: 45744 | B70: DMI-126733 | C70: Express | D70: VIVA1A | F70: Anillo 4 | G70: 42254914 | I70: AV SAN JOSE- PRADERA DE NARANJAL MZ A LTE 16 PRIMERA ETAPA, Lima, LIMA, SAN MARTIN DE PORRES | J70: San Martín de Porres | K70: Lima | L70: Entregado | M70: Express | N70: 45744 | O70: 8:28 AM - 12:28 PM | Q70: 3/28/2025 12:25:00 PM
A71: 45744 | B71: DMI-126734 | C71: Express | D71: VIVA1A | F71: Anillo 1 | G71: 73150778 | I71: CALLE LOS NEGOCIOS 280 DPTO 301 SURQUILLO | J71: Surquillo | K71: Lima | L71: Entregado | M71: Express | N71: 45744 | O71: 8:28 AM - 11:28 AM | P71: 3/28/2025 9:09:52 AM | Q71: 3/28/2025 9:14:53 AM
A72: 45744 | B72: DMI-126739 | C72: Express | D72: VIVA1A | F72: Anillo 5 | G72: 41870074 | I72: MZ E2 LOTE 46 LOS JARDINES DE CHILLON PUENTE PIEDRA | J72: Puente Piedra | K72: Lima | L72: Entregado | M72: Express | N72: 45744 | O72: 8:35 AM - 12:35 PM | P72: 3/28/2025 11:24:54 AM | Q72: 3/28/2025 11:25:04 AM
A73: 45744 | B73: DMI-126741 | C73: Express | D73: VIVA1A | F73: Anillo 4 | G73: 76417111 | I73: José Bernardo Alcedo 179, La Molina, Perú | J73: La Molina | K73: Lima | L73: Entregado | M73: Express | N73: 45744 | O73: 8:36 AM - 12:36 PM | P73: 3/28/2025 11:43:49 AM | Q73: 3/28/2025 11:45:28 AM
A74: 45744 | B74: DMI-126760 | C74: Express | D74: VIVA1A | F74: Anillo 4 | G74: 76133385 | I74: CALLE SAN JUAN DE AMANCAES MZ 50, LOTE 12 | J74: Rímac | K74: Lima | L74: Entregado | M74: Express | N74: 45744 | O74: 9:17 AM - 1:17 PM | P74: 3/28/2025 11:10:39 AM | Q74: 3/28/2025 11:11:15 AM
A75: 45744 | B75: DMI-126769 | C75: Express | D75: VIVA1A | F75: Anillo 3 | G75: 40255991 | I75: AV RAFAEL ESCARDON 660 DPTO 704 | J75: San Miguel | K75: Lima | L75: Entregado | M75: Express | N75: 45744 | O75: 9:29 AM - 1:29 PM | P75: 3/28/2025 10:56:26 AM | Q75: 3/28/2025 10:59:58 AM
A76: 45744 | B76: DMI-126776 | C76: Express | D76: VIVA1A | F76: Anillo 5 | G76: 44280027 | H76: raquelverastegui253@gmail.com | I76: CONDOMINIO TORRES LAS PRADERAS MZ E PUERTA E2 DPTO 1404, TORRE E2, COMAS | J76: Comas | K76: Lima | L76: Entregado | M76: Express | N76: 45744 | O76: 9:50 AM - 1:50 PM | P76: 3/28/2025 12:31:59 PM | Q76: 3/28/2025 12:36:00 PM
A77: 45744 | B77: DMI-126781 | C77: Express | D77: VIVA1A | F77: Anillo 5 | G77: 43811489 | I77: AVENIDA MICAELA BASTIDAS 919 CONDOMINIO TORRES LAS PRADERAS | J77: Comas | K77: Lima | L77: Entregado | M77: Express | N77: 45744 | O77: 10:03 AM - 2:03 PM | P77: 3/28/2025 12:19:41 PM | Q77: 3/28/2025 12:26:19 PM
A78: 45744 | B78: DMI-126783 | C78: Express | D78: VIVA1A | F78: Anillo 5 | G78: 70627396 | I78: AVENIDA GRAN CHIMÚ 1703 URBANIZACION ZARATE | J78: San Juan de Lurigancho | K78: Lima | L78: Entregado | M78: Express | N78: 45744 | O78: 10:06 AM - 2:06 PM | P78: 3/28/2025 1:49:10 PM | Q78: 3/28/2025 1:52:27 PM
A79: 45744 | B79: DMI-126786 | C79: Express | D79: VIVA1A | F79: Anillo 4 | G79: 74812479 | I79: MANZANA C-3 LOTE 5 TERCERA ETAPA SAN JUAN DE VILLA SOLIDARIDAD SAN JUAN DE MIRAFLORES | J79: San Juan de Miraflores | K79: Lima | L79: Entregado | M79: Express | N79: 45744 | O79: 10:12 AM - 2:12 PM | P79: 3/28/2025 12:54:19 PM | Q79: 3/28/2025 12:54:30 PM
A80: 45744 | B80: DMI-126796 | C80: Express | D80: VIVA1A | F80: Anillo 4 | G80: 75504211 | I80: calle san Sebastián 240 la Molina casa 3 | J80: La Molina | K80: Lima | L80: Entregado | M80: Express | N80: 45744 | O80: 10:40 AM - 2:40 PM | P80: 3/28/2025 12:14:31 PM | Q80: 3/28/2025 12:16:51 PM
A81: 45744 | B81: DMI-126804 | C81: Express | D81: VIVA1A | F81: Anillo 2 | G81: 72366344 | I81: daniel cornejo 234 surco | J81: Santiago de Surco | K81: Lima | L81: Entregado | M81: Express | N81: 45744 | O81: 11:01 AM - 2:01 PM | P81: 3/28/2025 12:43:56 PM | Q81: 3/28/2025 12:44:31 PM
A82: 45744 | B82: DMI-126807 | C82: Express | D82: VIVA1A | F82: Anillo 4 | G82: 6167643 | I82: JR CESAR VALLEJO 768 URB MERCURIO LOS OLIVOS | J82: Los Olivos | K82: Lima | L82: Entregado | M82: Express | N82: 45744 | O82: 11:10 AM - 3:10 PM | P82: 3/28/2025 2:18:50 PM | Q82: 3/28/2025 2:19:21 PM
A83: 45744 | B83: DMI-126813 | C83: Express | D83: VIVA1A | F83: Anillo 5 | G83: 47578578 | H83: matincks3@hotmail.com | I83: Av. Revolucion Mz A Lt 25, Barrio 2 4ta etapa, Urb. Pachacamac, Villa El Salvador | J83: Villa El Salvador | K83: Lima | L83: Entregado | M83: Express | N83: 45744 | O83: 11:25 AM - 3:25 PM | P83: 3/28/2025 1:56:57 PM | Q83: 3/28/2025 1:57:39 PM
A84: 45744 | B84: DMI-126818 | C84: Express | D84: VIVA1A | F84: Anillo 4 | G84: 70063443 | I84: CALLE ALMIRANTE GUISSE MZ L LOTE 5 URB MONTECARLO PRIMERA ETAPA - San Martín de Porres | J84: San Martín de Porres | K84: Lima | L84: Entregado | M84: Express | N84: 45744 | O84: 11:33 AM - 3:33 PM | P84: 3/28/2025 1:12:12 PM | Q84: 3/28/2025 1:12:27 PM
A85: 45744 | B85: DMI-126819 | C85: Express | D85: VIVA1A | F85: Anillo 3 | G85: 7976383 | I85: Calle Mario Valdivia 110 dpto 401 - San Miguel | J85: San Miguel | K85: Lima | L85: Entregado | M85: Express | N85: 45744 | O85: 12:02 PM - 4:02 PM | P85: 3/28/2025 1:33:56 PM | Q85: 3/28/2025 1:35:32 PM
A86: 45744 | B86: DMI-126823 | C86: Express | D86: VIVA1A | F86: Anillo 4 | G86: 25720093 | I86: CALLE DIEGO FERRE 335 2do Piso, LA PUNTA CALLAO | J86: Callao - La Punta | K86: Callao | L86: Entregado | M86: Express | N86: 45744 | O86: 11:49 AM - 3:49 PM | P86: 3/28/2025 1:47:37 PM | Q86: 3/28/2025 1:47:51 PM
A87: 45744 | B87: DMI-126826 | C87: Express | D87: VIVA1A | F87: Anillo 2 | G87: 9301371 | I87: jr SAN IGNACIO 246 CENTRO COMERCIAL MONTERRICO SURCO | J87: Santiago de Surco | K87: Lima | L87: Entregado | M87: Express | N87: 45744 | O87: 11:55 AM - 2:55 PM | P87: 3/28/2025 2:39:36 PM | Q87: 3/28/2025 2:40:01 PM
A88: 45744 | B88: DMI-126827 | C88: Express | D88: VIVA1A | F88: Anillo 3 | G88: 70581478 | I88: Calle La Mar 451 - SAN MIGUEL | J88: San Miguel | K88: Lima | L88: Entregado | M88: Express | N88: 45744 | O88: 11:56 AM - 3:56 PM | P88: 3/28/2025 12:40:20 PM | Q88: 3/28/2025 12:42:48 PM
A89: 45744 | B89: DMI-126828 | C89: Express | D89: VIVA1A | F89: Anillo 2 | G89: 6167823 | I89: Jirón Tarapacá 158 dpto 401 | J89: Magdalena del Mar | K89: Lima | L89: Entregado | M89: Express | N89: 45744 | O89: 11:56 AM - 2:56 PM | P89: 3/28/2025 1:44:24 PM | Q89: 3/28/2025 1:45:00 PM
A90: 45744 | B90: DMI-126831 | C90: Express | D90: VIVA1A | F90: Anillo 4 | G90: 3217327 | H90: fabiolafm314@gmail.com | I90: CALLE SEIS MZ K LT 3 URB LOS GIRASOLES | J90: La Molina | K90: Lima | L90: Entregado | M90: Express | N90: 45744 | O90: 12:02 PM - 4:02 PM | P90: 3/28/2025 3:44:10 PM | Q90: 3/28/2025 3:44:31 PM
A91: 45744 | B91: DMI-126833 | C91: Express | D91: VIVA1A | F91: Anillo 3 | G91: 76239331 | I91: CALLE NUEVA ESPARTA MZ C11 LT 20 CEDROS DE VILLA | J91: Chorrillos | K91: Lima | L91: Entregado | M91: Express | N91: 45744 | O91: 12:10 PM - 4:10 PM | P91: 3/28/2025 2:09:03 PM | Q91: 3/28/2025 2:09:22 PM
A92: 45744 | B92: DMI-126834 | C92: Express | D92: VIVA1A | F92: Anillo 4 | G92: 48083145 | I92: Asociacion la floresta MZ F LOT 20 DPTO 101 - SAN JUAM DE MIRAFLORES | J92: San Juan de Miraflores | K92: Lima | L92: Entregado | M92: Express | N92: 45744 | O92: 12:20 PM - 4:20 PM | P92: 3/28/2025 1:45:19 PM | Q92: 3/28/2025 1:45:34 PM
A93: 45744 | B93: DMI-126840 | C93: Express | D93: VIVA1A | F93: Anillo 5 | G93: 3822554 | H93: yoce.ya@gmail.com | I93: Calle Valladolid 262 Urbanización Mayorazgo | J93: Ate Vitarte (Zona 1, 2 y 3) | K93: Lima | L93: Entregado | M93: Express | N93: 45744 | O93: 12:36 PM - 4:36 PM | P93: 3/28/2025 2:43:12 PM | Q93: 3/28/2025 2:43:46 PM
A94: 45744 | B94: DMI-126841 | C94: Express | D94: VIVA1A | F94: Anillo 4 | G94: 78037871 | I94: AVENIDA OSCAR R BENAVIDES 3046 CONDOMINIO ALTO COLONIAL TORRE EUCALIPTO DPTO 502, CALLAO | J94: Callao - Callao | K94: Callao | L94: Entregado | M94: Express | N94: 45744 | O94: 12:52 PM - 4:52 PM | P94: 3/28/2025 2:31:56 PM | Q94: 3/28/2025 2:33:46 PM
A95: 45744 | B95: DMI-126842 | C95: Express | D95: VIVA1A | F95: Anillo 5 | G95: 78248852 | I95: PASAJE LEONCIO PRADO 173 URBANIZACION SAN FELIPE | J95: Comas | K95: Lima | L95: Entregado | M95: Express | N95: 45744 | O95: 12:47 PM - 4:47 PM | P95: 3/28/2025 3:53:26 PM | Q95: 3/28/2025 3:57:19 PM
A96: 45744 | B96: DMI-126848 | C96: Express | D96: VIVA1A | F96: Anillo 4 | G96: 9757773 | I96: AV. CARLOS IZAGUIRRE 176-INDEPENDENCIA | J96: Independencia | K96: Lima | L96: Entregado | M96: Express | N96: 45744 | O96: 1:08 PM - 5:08 PM | P96: 3/28/2025 4:06:25 PM | Q96: 3/28/2025 4:09:07 PM
A97: 45744 | B97: DMI-126849 | C97: Express | D97: VIVA1A | F97: Anillo 5 | G97: 47349856 | H97: ANGEL_07_10_91@HOTMAIL.COM | I97: residencial villa jacaranda 203 - 205 torre 3 dpto 1105 | J97: Comas | K97: Lima | L97: Entregado | M97: Express | N97: 45744 | O97: 1:08 PM - 5:08 PM | P97: 3/28/2025 4:10:37 PM | Q97: 3/28/2025 4:15:40 PM
A98: 45744 | B98: DMI-126850 | C98: Express | D98: VIVA1A | F98: Anillo 4 | G98: 43343871 | I98: CALLE LOS MELONES 338 URBANIZACION AMPLIACION RESIDENCIAL MONTERRICO - LA MOLINA | J98: La Molina | K98: Lima | L98: Entregado | M98: Express | N98: 45744 | O98: 1:10 PM - 5:10 PM | P98: 3/28/2025 3:12:00 PM | Q98: 3/28/2025 3:12:10 PM
A99: 45744 | B99: DMI-126851 | C99: Express | D99: VIVA1A | F99: Anillo 4 | G99: 10782121 | I99: CALLE PENELOPE 154 SANTA ANITA | J99: Santa Anita | K99: Lima | L99: Entregado | M99: Express | N99: 45744 | O99: 1:11 PM - 5:11 PM | P99: 3/28/2025 3:26:12 PM | Q99: 3/28/2025 3:26:30 PM
A100: 45744 | B100: DMI-126852 | C100: Express | D100: VIVA1A | F100: Anillo 2 | G100: 9460512 | I100: CALLE SANTA BERNARDITA 488 PISO 2 URB PANDO TERCERA ETAPA - CERCADO DE LIMA | J100: Cercado de Lima | K100: Lima | L100: Entregado | M100: Express | N100: 45744 | O100: 1:13 PM - 4:13 PM | P100: 3/28/2025 3:22:11 PM | Q100: 3/28/2025 3:24:21 PM
A101: 45744 | B101: DMI-126853 | C101: Express | D101: VIVA1A | F101: Anillo 2 | G101: 76526194 | I101: AVENIDA PROLONGACIÓN IQUITOS 2515 DEPARTAMENTO 607 | J101: Lince | K101: Lima | L101: Entregado | M101: Express | N101: 45744 | O101: 1:13 PM - 4:13 PM | P101: 3/28/2025 2:42:47 PM | Q101: 3/28/2025 2:45:02 PM
A102: 45744 | B102: DMI-126854 | C102: Express | D102: VIVA1A | F102: Anillo 4 | G102: 42847059 | I102: CALLE MARCELINO VARELA 421 - SEGUNDO PISO - URBANIZACIÓN LOS FICUS - SANTA ANITA | J102: Santa Anita | K102: Lima | L102: Entregado | M102: Express | N102: 45744 | O102: 1:14 PM - 5:14 PM | P102: 3/28/2025 3:30:34 PM | Q102: 3/28/2025 3:31:01 PM
A103: 45744 | B103: DMI-126855 | C103: Express | D103: VIVA1A | F103: Anillo 1 | G103: 43484145 | I103: calle berlin 828 dpto 701 - Miraflores | J103: Miraflores | K103: Lima | L103: Entregado | M103: Express | N103: 45744 | O103: 1:16 PM - 4:16 PM | P103: 3/28/2025 3:20:08 PM | Q103: 3/28/2025 3:27:59 PM
A104: 45744 | B104: DMI-126858 | C104: Express | D104: VIVA1A | F104: Anillo 2 | G104: 42070372 | I104: Avenida Buena Vista 235, San Borja, Lima, Perú | J104: San Borja | K104: Lima | L104: Entregado | M104: Express | N104: 45744 | O104: 1:30 PM - 4:30 PM | P104: 3/28/2025 3:57:27 PM | Q104: 3/28/2025 4:00:59 PM
A105: 45744 | B105: DMI-126863 | C105: Express | D105: VIVA1A | F105: Anillo 3 | G105: 91522483 | I105: SAN AURELIO 243- CHORRILLOS | J105: Chorrillos | K105: Lima | L105: Entregado | M105: Express | N105: 45744 | O105: 2:04 PM - 6:04 PM | P105: 3/28/2025 4:46:43 PM | Q105: 3/28/2025 4:52:31 PM
A106: 45744 | B106: DMI-126866 | C106: Express | D106: VIVA1A | F106: Anillo 4 | G106: 72529104 | I106: AV CALLAO 507 D- DPT 301 -LA PERLA ALTA CALLAO - Callao - La Perla | J106: Callao - La Perla | K106: Callao | L106: Entregado | M106: Express | N106: 45744 | O106: 2:09 PM - 6:09 PM | P106: 3/28/2025 5:03:41 PM | Q106: 3/28/2025 5:04:13 PM
A107: 45744 | B107: DMI-126910 | C107: Express | D107: VIVA1A | F107: Anillo 5 | G107: 8160096 | I107: Pasaje Puruchuca MZ B Lote 16 | J107: Ate | K107: Lima | L107: Entregado | M107: Express | N107: 45744 | O107: 4:02 PM - 8:02 PM | P107: 3/28/2025 7:27:41 PM | Q107: 3/28/2025 7:27:53 PM
A108: 45744 | B108: DMI-126913 | C108: Express | D108: VIVA1A | F108: Anillo 4 | G108: 73132654 | I108: AVENIDA PROCERES DE HUANDOY 4858- LOS OLIVOS | J108: Los Olivos | K108: Lima | L108: Entregado | M108: Express | N108: 45744 | O108: 4:03 PM - 8:03 PM | P108: 3/28/2025 6:13:58 PM | Q108: 3/28/2025 6:14:20 PM
A109: 45744 | B109: DMI-126923 | C109: Express | D109: VIVA1A | F109: Anillo 4 | G109: 74061812 | I109: Av. los Fresnos 258, La Molina, Perú | J109: La Molina | K109: Lima | L109: Entregado | M109: Express | N109: 45744 | O109: 4:23 PM - 8:23 PM | P109: 3/28/2025 6:56:58 PM | Q109: 3/28/2025 7:01:38 PM
...

Sheet DATA CORREO
A1: PERIODO | B1: ASEGURADOR | C1: SEDE | D1: CONTRATO | E1: TIPO CONTRATO | F1: TIPO DE DOCUMENTO | G1: dn | H1: PACIENTE | I1: DIRECCIÓN | J1: TELÉFONO | K1: CORREO | L1: RADICADO | M1: COD. SUBASTA | N1: PROCESO | O1: VIA DE RECEPCIÓN | P1: DESCRIPCIÓN QUEJA | Q1: MOTIVO | R1: SERVICIO | S1: ESPECIALIDAD | T1: FECHA DEL INCIDENTE | U1: RESPUESTA | V1: FECHA DE RESPUESTA | W1: ESTADO | X1: T. RESPUESTA | Y1: ESTADO FINAL | Z1: HORAS DIAS2 | AA1: ESTADO 2 | AB1: FECHA SI | AC1: CRUCE ARCHIVO EXCEL RIMAC | AD1: CRUCE MEDICAMENTOS REPORTE DE CASOS MAD | AE1: CRUCE MEDICAMENTOS HOJA 3 | AF1: CRUCE BASE PENDIENTES | AG1: CRUCE BASE lorena | AH1: CRUCE BASE lorena2 | AI1: CRUCE PROCESO | AJ1: CRUCE AGRUPADOR | AK1: Columna1
A2: =YEAR(Tabla1[[#This Row],[FECHA DEL INCIDENTE]])*100+MONTH(Tabla1[[#This Row],[FECHA DEL INCIDENTE]]) -> 202501 | B2: PERÚ | C2: VIVA1A CENTRO MEDICO | D2: RIMAC | E2: CRONICOS | F2: DNI | G2: 8155039 | H2: ELVA EDITH MIRANDA FALCONI | L2: 25-EPS001903_x000D_ | M2: 24209084 | N2: RECLAMOS | O2: LIBRO DE RECLAMOS ASEGURADOR | P2: "Yo ELVA EDITH MIRANDA FALCONI con DNI: 08155039 presento mi reclamo hacia el proveedor VIVA 1A S.A.C., ya que es la segunda vez que me atienden y me informan que los medicamentos me los van a enviar después de 24 horas. Eso no ayuda en la mejora de mi salud. Solicito se tomen las medidas correspondientes." | Q2: DEMORA EN LA ENTREGA DE MEDICAMENTOS | R2: PRESTADOR EXTERNO | S2: FARMACIA | T2: 45663 | U2: Informe de Resultado del Reclamo 1. Canal de Ingreso del Reclamo: Reclamo ingresado el 03 de enero de 2025, a través del Libro de Reclamaciones Virtual (LRV) de RIMAC EPS, mediante la Hoja de Reclamación N°25- EPS001903; el cual nos fue trasladado el 22 de enero del 2025 y registramos como Reclamo N° LVR-25-000013. 2. Identificación del usuario afectado y de quien presenta el reclamo: El reclamo fue presentado por Elva Edith Miranda Falconi con DNI N° 08155039. 3. Descripción y causa del reclamo: “Yo ELVA EDITH MIRANDA FALCONI con DNI: 08155039 presento mi reclamo hacia el proveedor VIVA 1ª S.A.C., ya que es la segunda vez que me atienden y me informan que los medicamentos me los van a enviar después de 24 horas. Eso no ayuda en la mejora de mi salud. Solicito se tomen las medidas correspondientes.” 4. Análisis de los hechos que sustentan el reclamo: Habiendo solicitado el descargo respectivo a las áreas involucradas en su atención, como parte de las diligencias para atender su reclamo, cordialmente, le informamos lo siguiente: Sentimos los inconvenientes ocasionados y manifestamos que la salud de nuestros pacientes es nuestra prioridad. Lamentablemente, por fallas del sistema logístico de nuestro proveedor no se realizó la entrega el mismo día de la atención la cual se gestionó el despacho el día 3 de enero. No obstante, comprendemos su inquietud respecto a la percepción de demora y por ello lamentamos lo sucedido. 5. Conclusiones En consecuencia, de acuerdo con los fundamentos expuestos, nuestra institución declara fundado su reclamo. Viva 1A agradece su reclamo pues nos permite tener el debido conocimiento de las eventualidades y deficiencias que puedan producirse durante la atención, tomar medidas correctivas evitando a futuro alguna otra disconformidad que refleja insatisfacción en situaciones similares. Avenida Faustino Sánchez Carrión 230. viva1a.com.pe (01)6183000 Lamentamos que la percepción de la atención brindada no haya sido de su satisfacción, no obstante, le reiteramos nuestro compromiso de seguir trabajando en pro de la mejora de los procesos establecidos en nuestra institución; asimismo le informamos que, ante cualquier consulta o duda futura, puede contactarse con nuestro personal de Plataforma de Atención al Usuario en Salud (PAUS) por los siguientes canales: quejasyreclamos@viva1a.com.pe 6. Medidas a adoptar o adoptadas: Finalmente, es oportuno informarle que hemos adoptado las siguientes medidas: a) Mejorar la comunicación sobre rangos de entrega, especialmente en zonas alejadas o con limitaciones logísticas. b) Seguimiento personalizado post atención, para verificar la satisfacción del usuario con el servicio recibido. Quedamos atentos ante cualquier solicitud, prestos a servirle siempre. “EN VIVA 1A CUIDAMOS LA SALUD DE TU FAMILIA COMO SI FUERA LA NUESTRA” | V2: 45761 | W2: CERRADA | X2: =NETWORKDAYS(Tabla1[[#This Row],[FECHA DEL INCIDENTE]],Tabla1[[#This Row],[FECHA DE RESPUESTA]]) -> 71 | Y2: =IF(Tabla1[[#This Row],[ESTADO]]="ACTIVA","ACTIVA",IF(Tabla1[[#This Row],[ESTADO]]="CERRADA","CERRADA",IF(Tabla1[[#This Row],[ESTADO]]="TRASLADADA","CERRADA",IF(Tabla1[[#This Row],[ESTADO]]="DESMONTADA","CERRADA",IF(Tabla1[[#This Row],[ESTADO]]="SEGUIMIENTO","ACTIVA"))))) -> CERRADA | Z2: =+IF(Tabla1[[#This Row],[T. RESPUESTA]]<=1,"24 HORAS",IF(Tabla1[[#This Row],[T. RESPUESTA]]=2,"48 HORAS",IF(Tabla1[[#This Row],[T. RESPUESTA]]=3,"72 HORAS",IF(Tabla1[[#This Row],[T. RESPUESTA]]=4,"96 HORAS",IF(Tabla1[[#This Row],[T. RESPUESTA]]=5,"120 HORAS",IF(Tabla1[[#This Row],[T. RESPUESTA]]>=6,"6 DIAS O MAS","ERROR")))))) -> 6 DIAS O MAS | AA2: ATRIBUIBLE | AB2: =TEXT(Tabla1[[#This Row],[FECHA DEL INCIDENTE]],"MMM-DD") -> ene-06 | AC2: =VLOOKUP(G2,'Archivo data rimac reclamos'!B:C,2,0) -> #N/A | AD2: =VLOOKUP(Tabla1[[#This Row],[dn]],'Reporte de casos MAD'!H:W,16,0) -> #N/A | AE2: =VLOOKUP(Tabla1[[#This Row],[dn]],'HOJA 3 MEDICAMENTOS'!G:Q,11,0) -> #N/A | AF2: =VLOOKUP(Tabla1[[#This Row],[dn]],'base pendientes viva 1a'!C:Q,15,0) -> #N/A | AG2: #N/A | AH2: #N/A | AI2: =VLOOKUP(Tabla1[[#This Row],[MOTIVO]],clasificador!A:C,2,0) -> Medicamentos | AJ2: =VLOOKUP(Tabla1[[#This Row],[MOTIVO]],clasificador!A:C,3,0) -> SERVICIO
A3: =YEAR(Tabla1[[#This Row],[FECHA DEL INCIDENTE]])*100+MONTH(Tabla1[[#This Row],[FECHA DEL INCIDENTE]]) -> 202502 | B3: PERÚ | C3: VIVA1A CENTRO MEDICO | D3: RIMAC | E3: CRONICOS | F3: DNI | G3: 8160842 | H3: YOLANDA YESENIA MILAGROS YACILA CUYA DE VALDIVIA | I3: Jr. Edmundo del Aguila S/N -Moyobamba | J3: 998722960 | N3: SOLICITUD | O3: ASEGURADOR | P3: Buenos días Guisela Por favor su apoyo para el ingreso al programa de la asegurada: Yolanda Yesenia Milagros Yacila Cuya de Valdivia D.N.I. 08160842 Domicilio: Jr. Edmundo del Aguila S/N -Moyobamba Celular: 998722960 Al haber mi entidad laboral realizado cambio de EPS en el presente año, habiéndome encontrado en el programa Siempre Sano de la EPS Pacifico, por tener enfermedad Crónica de Hipertensión, hiperlipidemia mixta y hiperuricemia, recibiendo mi atención en forma virtual, toda vez que radicó en la ciudad de Moyobamba, departamento de san Martín, localidad y departamento en el cual no se cuenta con dichos servicios, asimismo debo de manifestarle que soy paciente oncológica, al haber sido diagnosticada con cáncer de mama, solicito que por su intermedio se pueda realizar el ingreso correspondiente y pueda realizar mi control médico en forma virtual así como la recepción de mis medicinas en esta localidad, para tal efecto acompaño las documentales pertinentes. | Q3: INGRESO A PROGRAMA | R3: CRONICOS | S3: DISLIPIDEMIA | T3: 45712 | U3: Estimada Guissela, buena noche: Previo cordial saludo y las disculpas del caso por la demora en responder se informa sobre paciente que, la atención fue efectiva el día 5 del presente, con entrega de farmacia conforme. Saludos Cordiales, | V3: 45735 | W3: CERRADA | X3: =NETWORKDAYS(Tabla1[[#This Row],[FECHA DEL INCIDENTE]],Tabla1[[#This Row],[FECHA DE RESPUESTA]]) -> 18 | Y3: =IF(Tabla1[[#This Row],[ESTADO]]="ACTIVA","ACTIVA",IF(Tabla1[[#This Row],[ESTADO]]="CERRADA","CERRADA",IF(Tabla1[[#This Row],[ESTADO]]="TRASLADADA","CERRADA",IF(Tabla1[[#This Row],[ESTADO]]="DESMONTADA","CERRADA",IF(Tabla1[[#This Row],[ESTADO]]="SEGUIMIENTO","ACTIVA"))))) -> CERRADA | Z3: =+IF(Tabla1[[#This Row],[T. RESPUESTA]]<=1,"24 HORAS",IF(Tabla1[[#This Row],[T. RESPUESTA]]=2,"48 HORAS",IF(Tabla1[[#This Row],[T. RESPUESTA]]=3,"72 HORAS",IF(Tabla1[[#This Row],[T. RESPUESTA]]=4,"96 HORAS",IF(Tabla1[[#This Row],[T. RESPUESTA]]=5,"120 HORAS",IF(Tabla1[[#This Row],[T. RESPUESTA]]>=6,"6 DIAS O MAS","ERROR")))))) -> 6 DIAS O MAS | AA3: ATRIBUIBLE | AB3: =TEXT(Tabla1[[#This Row],[FECHA DEL INCIDENTE]],"MMM-DD") -> feb-24 | AC3: =VLOOKUP(G3,'Archivo data rimac reclamos'!B:C,2,0) -> REMITO INFORMACION PARA SER CONSIDERADA EN EL PROGRAMA CUIDATE DE RIMAC EPS | AD3: =VLOOKUP(Tabla1[[#This Row],[dn]],'Reporte de casos MAD'!H:W,16,0) -> #N/A | AE3: =VLOOKUP(Tabla1[[#This Row],[dn]],'HOJA 3 MEDICAMENTOS'!G:Q,11,0) -> #N/A | AF3: =VLOOKUP(Tabla1[[#This Row],[dn]],'base pendientes viva 1a'!C:Q,15,0) -> #N/A | AG3: #N/A | AH3: #N/A | AI3: =VLOOKUP(Tabla1[[#This Row],[MOTIVO]],clasificador!A:C,2,0) -> Solicitud | AJ3: =VLOOKUP(Tabla1[[#This Row],[MOTIVO]],clasificador!A:C,3,0) -> SOLICITUD
A4: =YEAR(Tabla1[[#This Row],[FECHA DEL INCIDENTE]])*100+MONTH(Tabla1[[#This Row],[FECHA DEL INCIDENTE]]) -> 202502 | B4: PERÚ | C4: VIVA1A CENTRO MEDICO | D4: RIMAC | E4: CRONICOS | F4: DNI | G4: 71003215 | H4: ABANTO CABANILLAS, DAVID ABELARDO | J4: 916425674 () 916425674 | N4: SOLICITUD | O4: ASEGURADOR | P4: RE: POTENCIALES AL PROGRAMA CUIDATE Y OTROS CRONICOS-SURA /RIESGO Estimada @gsiguenas@viva1a.com.pe Se requiere el reporte de contactibilidad y ingresos. Estimados @gsiguenas@viva1a.com.pe@Julio Marco Inocencio Pereyra Su gentil apoyo con el contacto de caracterización y de ingreso a programas crónicos usuarios identificados como potenciales por chequeo médico contratante Sura (68 usuarios) Se adjunta el listado en el formato de plantilla para su gestión Atentamente. | Q4: INGRESO A PROGRAMA | R4: CUIDATE | S4: ASMA | T4: 45712 | U4: ATENDIDO 11/04/2025 Antonio David Moncada Catalan | V4: 45754 | W4: CERRADA | X4: =NETWORKDAYS(Tabla1[[#This Row],[FECHA DEL INCIDENTE]],Tabla1[[#This Row],[FECHA DE RESPUESTA]]) -> 31 | Y4: =IF(Tabla1[[#This Row],[ESTADO]]="ACTIVA","ACTIVA",IF(Tabla1[[#This Row],[ESTADO]]="CERRADA","CERRADA",IF(Tabla1[[#This Row],[ESTADO]]="TRASLADADA","CERRADA",IF(Tabla1[[#This Row],[ESTADO]]="DESMONTADA","CERRADA",IF(Tabla1[[#This Row],[ESTADO]]="SEGUIMIENTO","ACTIVA"))))) -> CERRADA | Z4: =+IF(Tabla1[[#This Row],[T. RESPUESTA]]<=1,"24 HORAS",IF(Tabla1[[#This Row],[T. RESPUESTA]]=2,"48 HORAS",IF(Tabla1[[#This Row],[T. RESPUESTA]]=3,"72 HORAS",IF(Tabla1[[#This Row],[T. RESPUESTA]]=4,"96 HORAS",IF(Tabla1[[#This Row],[T. RESPUESTA]]=5,"120 HORAS",IF(Tabla1[[#This Row],[T. RESPUESTA]]>=6,"6 DIAS O MAS","ERROR")))))) -> 6 DIAS O MAS | AA4: ATRIBUIBLE | AB4: =TEXT(Tabla1[[#This Row],[FECHA DEL INCIDENTE]],"MMM-DD") -> feb-24 | AC4: =VLOOKUP(G4,'Archivo data rimac reclamos'!B:C,2,0) -> #N/A | AD4: =VLOOKUP(Tabla1[[#This Row],[dn]],'Reporte de casos MAD'!H:W,16,0) -> #N/A | AE4: =VLOOKUP(Tabla1[[#This Row],[dn]],'HOJA 3 MEDICAMENTOS'!G:Q,11,0) -> #N/A | AF4: =VLOOKUP(Tabla1[[#This Row],[dn]],'base pendientes viva 1a'!C:Q,15,0) -> #N/A | AI4: =VLOOKUP(Tabla1[[#This Row],[MOTIVO]],clasificador!A:C,2,0) -> Solicitud | AJ4: =VLOOKUP(Tabla1[[#This Row],[MOTIVO]],clasificador!A:C,3,0) -> SOLICITUD
A5: =YEAR(Tabla1[[#This Row],[FECHA DEL INCIDENTE]])*100+MONTH(Tabla1[[#This Row],[FECHA DEL INCIDENTE]]) -> 202502 | B5: PERÚ | C5: VIVA1A CENTRO MEDICO | D5: RIMAC | E5: CRONICOS | F5: DNI | G5: 71466728 | H5: ALARCÓN CHUFANDAMA, RAÚL RODRIGO | J5: 958850901 | N5: SOLICITUD | O5: ASEGURADOR | P5: RE: POTENCIALES AL PROGRAMA CUIDATE Y OTROS CRONICOS-SURA /RIESGO Estimada @gsiguenas@viva1a.com.pe Se requiere el reporte de contactibilidad y ingresos. Estimados @gsiguenas@viva1a.com.pe@Julio Marco Inocencio Pereyra Su gentil apoyo con el contacto de caracterización y de ingreso a programas crónicos usuarios identificados como potenciales por chequeo médico contratante Sura (68 usuarios) Se adjunta el listado en el formato de plantilla para su gestión Atentamente. | Q5: INGRESO A PROGRAMA | R5: CUIDATE | S5: ASMA | T5: 45712 | U5: NO DESEA ENTRAR PROGRAMA | V5: 45754 | W5: CERRADA | X5: =NETWORKDAYS(Tabla1[[#This Row],[FECHA DEL INCIDENTE]],Tabla1[[#This Row],[FECHA DE RESPUESTA]]) -> 31 | Y5: =IF(Tabla1[[#This Row],[ESTADO]]="ACTIVA","ACTIVA",IF(Tabla1[[#This Row],[ESTADO]]="CERRADA","CERRADA",IF(Tabla1[[#This Row],[ESTADO]]="TRASLADADA","CERRADA",IF(Tabla1[[#This Row],[ESTADO]]="DESMONTADA","CERRADA",IF(Tabla1[[#This Row],[ESTADO]]="SEGUIMIENTO","ACTIVA"))))) -> CERRADA | Z5: =+IF(Tabla1[[#This Row],[T. RESPUESTA]]<=1,"24 HORAS",IF(Tabla1[[#This Row],[T. RESPUESTA]]=2,"48 HORAS",IF(Tabla1[[#This Row],[T. RESPUESTA]]=3,"72 HORAS",IF(Tabla1[[#This Row],[T. RESPUESTA]]=4,"96 HORAS",IF(Tabla1[[#This Row],[T. RESPUESTA]]=5,"120 HORAS",IF(Tabla1[[#This Row],[T. RESPUESTA]]>=6,"6 DIAS O MAS","ERROR")))))) -> 6 DIAS O MAS | AA5: ATRIBUIBLE | AB5: =TEXT(Tabla1[[#This Row],[FECHA DEL INCIDENTE]],"MMM-DD") -> feb-24 | AC5: =VLOOKUP(G5,'Archivo data rimac reclamos'!B:C,2,0) -> #N/A | AD5: =VLOOKUP(Tabla1[[#This Row],[dn]],'Reporte de casos MAD'!H:W,16,0) -> #N/A | AE5: =VLOOKUP(Tabla1[[#This Row],[dn]],'HOJA 3 MEDICAMENTOS'!G:Q,11,0) -> #N/A | AF5: =VLOOKUP(Tabla1[[#This Row],[dn]],'base pendientes viva 1a'!C:Q,15,0) -> #N/A | AI5: =VLOOKUP(Tabla1[[#This Row],[MOTIVO]],clasificador!A:C,2,0) -> Solicitud | AJ5: =VLOOKUP(Tabla1[[#This Row],[MOTIVO]],clasificador!A:C,3,0) -> SOLICITUD
A6: =YEAR(Tabla1[[#This Row],[FECHA DEL INCIDENTE]])*100+MONTH(Tabla1[[#This Row],[FECHA DEL INCIDENTE]]) -> 202502 | B6: PERÚ | C6: VIVA1A CENTRO MEDICO | D6: RIMAC | E6: CRONICOS | F6: DNI | G6: 41656878 | H6: AMORETTI SOTELO, ROSA ADRIANA | J6: 999941060 () 999941060 | N6: SOLICITUD | O6: ASEGURADOR | P6: RE: POTENCIALES AL PROGRAMA CUIDATE Y OTROS CRONICOS-SURA /RIESGO Estimada @gsiguenas@viva1a.com.pe Se requiere el reporte de contactibilidad y ingresos. Estimados @gsiguenas@viva1a.com.pe@Julio Marco Inocencio Pereyra Su gentil apoyo con el contacto de caracterización y de ingreso a programas crónicos usuarios identificados como potenciales por chequeo médico contratante Sura (68 usuarios) Se adjunta el listado en el formato de plantilla para su gestión Atentamente. | Q6: INGRESO A PROGRAMA | R6: CUIDATE | S6: DIABETES | T6: 45712 | U6: NO DESEA ENTRAR PROGRAMA | V6: 45754 | W6: CERRADA | X6: =NETWORKDAYS(Tabla1[[#This Row],[FECHA DEL INCIDENTE]],Tabla1[[#This Row],[FECHA DE RESPUESTA]]) -> 31 | Y6: =IF(Tabla1[[#This Row],[ESTADO]]="ACTIVA","ACTIVA",IF(Tabla1[[#This Row],[ESTADO]]="CERRADA","CERRADA",IF(Tabla1[[#This Row],[ESTADO]]="TRASLADADA","CERRADA",IF(Tabla1[[#This Row],[ESTADO]]="DESMONTADA","CERRADA",IF(Tabla1[[#This Row],[ESTADO]]="SEGUIMIENTO","ACTIVA"))))) -> CERRADA | Z6: =+IF(Tabla1[[#This Row],[T. RESPUESTA]]<=1,"24 HORAS",IF(Tabla1[[#This Row],[T. RESPUESTA]]=2,"48 HORAS",IF(Tabla1[[#This Row],[T. RESPUESTA]]=3,"72 HORAS",IF(Tabla1[[#This Row],[T. RESPUESTA]]=4,"96 HORAS",IF(Tabla1[[#This Row],[T. RESPUESTA]]=5,"120 HORAS",IF(Tabla1[[#This Row],[T. RESPUESTA]]>=6,"6 DIAS O MAS","ERROR")))))) -> 6 DIAS O MAS | AA6: ATRIBUIBLE | AB6: =TEXT(Tabla1[[#This Row],[FECHA DEL INCIDENTE]],"MMM-DD") -> feb-24 | AC6: =VLOOKUP(G6,'Archivo data rimac reclamos'!B:C,2,0) -> #N/A | AD6: =VLOOKUP(Tabla1[[#This Row],[dn]],'Reporte de casos MAD'!H:W,16,0) -> #N/A | AE6: =VLOOKUP(Tabla1[[#This Row],[dn]],'HOJA 3 MEDICAMENTOS'!G:Q,11,0) -> #N/A | AF6: =VLOOKUP(Tabla1[[#This Row],[dn]],'base pendientes viva 1a'!C:Q,15,0) -> #N/A | AI6: =VLOOKUP(Tabla1[[#This Row],[MOTIVO]],clasificador!A:C,2,0) -> Solicitud | AJ6: =VLOOKUP(Tabla1[[#This Row],[MOTIVO]],clasificador!A:C,3,0) -> SOLICITUD
A7: =YEAR(Tabla1[[#This Row],[FECHA DEL INCIDENTE]])*100+MONTH(Tabla1[[#This Row],[FECHA DEL INCIDENTE]]) -> 202502 | B7: PERÚ | C7: VIVA1A CENTRO MEDICO | D7: RIMAC | E7: CRONICOS | F7: DNI | G7: 46815882 | H7: ARCE ALARCON, GUILLERMO JUAN PABLO | J7: 986351295 | N7: SOLICITUD | O7: ASEGURADOR | P7: RE: POTENCIALES AL PROGRAMA CUIDATE Y OTROS CRONICOS-SURA /RIESGO Estimada @gsiguenas@viva1a.com.pe Se requiere el reporte de contactibilidad y ingresos. Estimados @gsiguenas@viva1a.com.pe@Julio Marco Inocencio Pereyra Su gentil apoyo con el contacto de caracterización y de ingreso a programas crónicos usuarios identificados como potenciales por chequeo médico contratante Sura (68 usuarios) Se adjunta el listado en el formato de plantilla para su gestión Atentamente. | Q7: INGRESO A PROGRAMA | R7: CUIDATE | S7: ASMA | T7: 45712 | U7: NO CONTESTA, SE DEJA WHATSAPP | V7: 45768 | W7: CERRADA | X7: =NETWORKDAYS(Tabla1[[#This Row],[FECHA DEL INCIDENTE]],Tabla1[[#This Row],[FECHA DE RESPUESTA]]) -> 41 | Y7: =IF(Tabla1[[#This Row],[ESTADO]]="ACTIVA","ACTIVA",IF(Tabla1[[#This Row],[ESTADO]]="CERRADA","CERRADA",IF(Tabla1[[#This Row],[ESTADO]]="TRASLADADA","CERRADA",IF(Tabla1[[#This Row],[ESTADO]]="DESMONTADA","CERRADA",IF(Tabla1[[#This Row],[ESTADO]]="SEGUIMIENTO","ACTIVA"))))) -> CERRADA | Z7: =+IF(Tabla1[[#This Row],[T. RESPUESTA]]<=1,"24 HORAS",IF(Tabla1[[#This Row],[T. RESPUESTA]]=2,"48 HORAS",IF(Tabla1[[#This Row],[T. RESPUESTA]]=3,"72 HORAS",IF(Tabla1[[#This Row],[T. RESPUESTA]]=4,"96 HORAS",IF(Tabla1[[#This Row],[T. RESPUESTA]]=5,"120 HORAS",IF(Tabla1[[#This Row],[T. RESPUESTA]]>=6,"6 DIAS O MAS","ERROR")))))) -> 6 DIAS O MAS | AA7: ATRIBUIBLE | AB7: =TEXT(Tabla1[[#This Row],[FECHA DEL INCIDENTE]],"MMM-DD") -> feb-24 | AC7: =VLOOKUP(G7,'Archivo data rimac reclamos'!B:C,2,0) -> #N/A | AD7: =VLOOKUP(Tabla1[[#This Row],[dn]],'Reporte de casos MAD'!H:W,16,0) -> #N/A | AE7: =VLOOKUP(Tabla1[[#This Row],[dn]],'HOJA 3 MEDICAMENTOS'!G:Q,11,0) -> #N/A | AF7: =VLOOKUP(Tabla1[[#This Row],[dn]],'base pendientes viva 1a'!C:Q,15,0) -> #N/A | AI7: =VLOOKUP(Tabla1[[#This Row],[MOTIVO]],clasificador!A:C,2,0) -> Solicitud | AJ7: =VLOOKUP(Tabla1[[#This Row],[MOTIVO]],clasificador!A:C,3,0) -> SOLICITUD
A8: =YEAR(Tabla1[[#This Row],[FECHA DEL INCIDENTE]])*100+MONTH(Tabla1[[#This Row],[FECHA DEL INCIDENTE]]) -> 202502 | B8: PERÚ | C8: VIVA1A CENTRO MEDICO | D8: RIMAC | E8: CRONICOS | F8: DNI | G8: 8775165 | H8: ARCE MENDOZA, GLADYS CAROLINA | J8: 2215736 989140252 | N8: SOLICITUD | O8: ASEGURADOR | P8: RE: POTENCIALES AL PROGRAMA CUIDATE Y OTROS CRONICOS-SURA /RIESGO Estimada @gsiguenas@viva1a.com.pe Se requiere el reporte de contactibilidad y ingresos. Estimados @gsiguenas@viva1a.com.pe@Julio Marco Inocencio Pereyra Su gentil apoyo con el contacto de caracterización y de ingreso a programas crónicos usuarios identificados como potenciales por chequeo médico contratante Sura (68 usuarios) Se adjunta el listado en el formato de plantilla para su gestión Atentamente. | Q8: INGRESO A PROGRAMA | R8: CUIDATE | S8: ASMA | T8: 45712 | U8: NO CONTESTA, SE DEJA WHATSAPP | V8: 45768 | W8: CERRADA | X8: =NETWORKDAYS(Tabla1[[#This Row],[FECHA DEL INCIDENTE]],Tabla1[[#This Row],[FECHA DE RESPUESTA]]) -> 41 | Y8: =IF(Tabla1[[#This Row],[ESTADO]]="ACTIVA","ACTIVA",IF(Tabla1[[#This Row],[ESTADO]]="CERRADA","CERRADA",IF(Tabla1[[#This Row],[ESTADO]]="TRASLADADA","CERRADA",IF(Tabla1[[#This Row],[ESTADO]]="DESMONTADA","CERRADA",IF(Tabla1[[#This Row],[ESTADO]]="SEGUIMIENTO","ACTIVA"))))) -> CERRADA | Z8: =+IF(Tabla1[[#This Row],[T. RESPUESTA]]<=1,"24 HORAS",IF(Tabla1[[#This Row],[T. RESPUESTA]]=2,"48 HORAS",IF(Tabla1[[#This Row],[T. RESPUESTA]]=3,"72 HORAS",IF(Tabla1[[#This Row],[T. RESPUESTA]]=4,"96 HORAS",IF(Tabla1[[#This Row],[T. RESPUESTA]]=5,"120 HORAS",IF(Tabla1[[#This Row],[T. RESPUESTA]]>=6,"6 DIAS O MAS","ERROR")))))) -> 6 DIAS O MAS | AA8: ATRIBUIBLE | AB8: =TEXT(Tabla1[[#This Row],[FECHA DEL INCIDENTE]],"MMM-DD") -> feb-24 | AC8: =VLOOKUP(G8,'Archivo data rimac reclamos'!B:C,2,0) -> #N/A | AD8: =VLOOKUP(Tabla1[[#This Row],[dn]],'Reporte de casos MAD'!H:W,16,0) -> #N/A | AE8: =VLOOKUP(Tabla1[[#This Row],[dn]],'HOJA 3 MEDICAMENTOS'!G:Q,11,0) -> #N/A | AF8: =VLOOKUP(Tabla1[[#This Row],[dn]],'base pendientes viva 1a'!C:Q,15,0) -> #N/A | AI8: =VLOOKUP(Tabla1[[#This Row],[MOTIVO]],clasificador!A:C,2,0) -> Solicitud | AJ8: =VLOOKUP(Tabla1[[#This Row],[MOTIVO]],clasificador!A:C,3,0) -> SOLICITUD
A9: =YEAR(Tabla1[[#This Row],[FECHA DEL INCIDENTE]])*100+MONTH(Tabla1[[#This Row],[FECHA DEL INCIDENTE]]) -> 202502 | B9: PERÚ | C9: VIVA1A CENTRO MEDICO | D9: RIMAC | E9: CRONICOS | F9: DNI | G9: 71521815 | H9: ATUSPARIA CIERTO, MARÍA FE | J9: 958822672 | N9: SOLICITUD | O9: ASEGURADOR | P9: RE: POTENCIALES AL PROGRAMA CUIDATE Y OTROS CRONICOS-SURA /RIESGO Estimada @gsiguenas@viva1a.com.pe Se requiere el reporte de contactibilidad y ingresos. Estimados @gsiguenas@viva1a.com.pe@Julio Marco Inocencio Pereyra Su gentil apoyo con el contacto de caracterización y de ingreso a programas crónicos usuarios identificados como potenciales por chequeo médico contratante Sura (68 usuarios) Se adjunta el listado en el formato de plantilla para su gestión Atentamente. | Q9: INGRESO A PROGRAMA | R9: CUIDATE | S9: ASMA | T9: 45712 | U9: ATENDIDO 6/04/2025Antonio David Moncada Catalan MEDICA FAMILIAR - TELECONSULTA | V9: 45754 | W9: CERRADA | X9: =NETWORKDAYS(Tabla1[[#This Row],[FECHA DEL INCIDENTE]],Tabla1[[#This Row],[FECHA DE RESPUESTA]]) -> 31 | Y9: =IF(Tabla1[[#This Row],[ESTADO]]="ACTIVA","ACTIVA",IF(Tabla1[[#This Row],[ESTADO]]="CERRADA","CERRADA",IF(Tabla1[[#This Row],[ESTADO]]="TRASLADADA","CERRADA",IF(Tabla1[[#This Row],[ESTADO]]="DESMONTADA","CERRADA",IF(Tabla1[[#This Row],[ESTADO]]="SEGUIMIENTO","ACTIVA"))))) -> CERRADA | Z9: =+IF(Tabla1[[#This Row],[T. RESPUESTA]]<=1,"24 HORAS",IF(Tabla1[[#This Row],[T. RESPUESTA]]=2,"48 HORAS",IF(Tabla1[[#This Row],[T. RESPUESTA]]=3,"72 HORAS",IF(Tabla1[[#This Row],[T. RESPUESTA]]=4,"96 HORAS",IF(Tabla1[[#This Row],[T. RESPUESTA]]=5,"120 HORAS",IF(Tabla1[[#This Row],[T. RESPUESTA]]>=6,"6 DIAS O MAS","ERROR")))))) -> 6 DIAS O MAS | AA9: ATRIBUIBLE | AB9: =TEXT(Tabla1[[#This Row],[FECHA DEL INCIDENTE]],"MMM-DD") -> feb-24 | AC9: =VLOOKUP(G9,'Archivo data rimac reclamos'!B:C,2,0) -> #N/A | AD9: =VLOOKUP(Tabla1[[#This Row],[dn]],'Reporte de casos MAD'!H:W,16,0) -> #N/A | AE9: =VLOOKUP(Tabla1[[#This Row],[dn]],'HOJA 3 MEDICAMENTOS'!G:Q,11,0) -> #N/A | AF9: =VLOOKUP(Tabla1[[#This Row],[dn]],'base pendientes viva 1a'!C:Q,15,0) -> #N/A | AI9: =VLOOKUP(Tabla1[[#This Row],[MOTIVO]],clasificador!A:C,2,0) -> Solicitud | AJ9: =VLOOKUP(Tabla1[[#This Row],[MOTIVO]],clasificador!A:C,3,0) -> SOLICITUD
A10: =YEAR(Tabla1[[#This Row],[FECHA DEL INCIDENTE]])*100+MONTH(Tabla1[[#This Row],[FECHA DEL INCIDENTE]]) -> 202502 | B10: PERÚ | C10: VIVA1A CENTRO MEDICO | D10: RIMAC | E10: CRONICOS | F10: DNI | G10: 75181231 | H10: BAZALAR URBINA, LUIS | J10: 987320968 | N10: SOLICITUD | O10: ASEGURADOR | P10: RE: POTENCIALES AL PROGRAMA CUIDATE Y OTROS CRONICOS-SURA /RIESGO Estimada @gsiguenas@viva1a.com.pe Se requiere el reporte de contactibilidad y ingresos. Estimados @gsiguenas@viva1a.com.pe@Julio Marco Inocencio Pereyra Su gentil apoyo con el contacto de caracterización y de ingreso a programas crónicos usuarios identificados como potenciales por chequeo médico contratante Sura (68 usuarios) Se adjunta el listado en el formato de plantilla para su gestión Atentamente. | Q10: INGRESO A PROGRAMA | R10: CUIDATE | S10: ASMA | T10: 45712 | U10: ATENDIDO 5/04/2025 Antonio David Moncada Catalan MEDICA FAMILIAR - TELECONSULTA | V10: 45754 | W10: CERRADA | X10: =NETWORKDAYS(Tabla1[[#This Row],[FECHA DEL INCIDENTE]],Tabla1[[#This Row],[FECHA DE RESPUESTA]]) -> 31 | Y10: =IF(Tabla1[[#This Row],[ESTADO]]="ACTIVA","ACTIVA",IF(Tabla1[[#This Row],[ESTADO]]="CERRADA","CERRADA",IF(Tabla1[[#This Row],[ESTADO]]="TRASLADADA","CERRADA",IF(Tabla1[[#This Row],[ESTADO]]="DESMONTADA","CERRADA",IF(Tabla1[[#This Row],[ESTADO]]="SEGUIMIENTO","ACTIVA"))))) -> CERRADA | Z10: =+IF(Tabla1[[#This Row],[T. RESPUESTA]]<=1,"24 HORAS",IF(Tabla1[[#This Row],[T. RESPUESTA]]=2,"48 HORAS",IF(Tabla1[[#This Row],[T. RESPUESTA]]=3,"72 HORAS",IF(Tabla1[[#This Row],[T. RESPUESTA]]=4,"96 HORAS",IF(Tabla1[[#This Row],[T. RESPUESTA]]=5,"120 HORAS",IF(Tabla1[[#This Row],[T. RESPUESTA]]>=6,"6 DIAS O MAS","ERROR")))))) -> 6 DIAS O MAS | AA10: ATRIBUIBLE | AB10: =TEXT(Tabla1[[#This Row],[FECHA DEL INCIDENTE]],"MMM-DD") -> feb-24 | AC10: =VLOOKUP(G10,'Archivo data rimac reclamos'!B:C,2,0) -> #N/A | AD10: =VLOOKUP(Tabla1[[#This Row],[dn]],'Reporte de casos MAD'!H:W,16,0) -> #N/A | AE10: =VLOOKUP(Tabla1[[#This Row],[dn]],'HOJA 3 MEDICAMENTOS'!G:Q,11,0) -> #N/A | AF10: =VLOOKUP(Tabla1[[#This Row],[dn]],'base pendientes viva 1a'!C:Q,15,0) -> #N/A | AI10: =VLOOKUP(Tabla1[[#This Row],[MOTIVO]],clasificador!A:C,2,0) -> Solicitud | AJ10: =VLOOKUP(Tabla1[[#This Row],[MOTIVO]],clasificador!A:C,3,0) -> SOLICITUD
A11: =YEAR(Tabla1[[#This Row],[FECHA DEL INCIDENTE]])*100+MONTH(Tabla1[[#This Row],[FECHA DEL INCIDENTE]]) -> 202502 | B11: PERÚ | C11: VIVA1A CENTRO MEDICO | D11: RIMAC | E11: CRONICOS | F11: DNI | G11: 71878358 | H11: BELTRAN LAVADO, JANETTE YSABEL | J11: 955709580 | N11: SOLICITUD | O11: ASEGURADOR | P11: RE: POTENCIALES AL PROGRAMA CUIDATE Y OTROS CRONICOS-SURA /RIESGO Estimada @gsiguenas@viva1a.com.pe Se requiere el reporte de contactibilidad y ingresos. Estimados @gsiguenas@viva1a.com.pe@Julio Marco Inocencio Pereyra Su gentil apoyo con el contacto de caracterización y de ingreso a programas crónicos usuarios identificados como potenciales por chequeo médico contratante Sura (68 usuarios) Se adjunta el listado en el formato de plantilla para su gestión Atentamente. | Q11: INGRESO A PROGRAMA | R11: CUIDATE | S11: ASMA | T11: 45712 | U11: ATENDIDO 15/04/2025 Janet Giovanna Quispe Vargas REUMATOLOGÍA - TELECONSULTA | V11: 45759 | W11: CERRADA | X11: =NETWORKDAYS(Tabla1[[#This Row],[FECHA DEL INCIDENTE]],Tabla1[[#This Row],[FECHA DE RESPUESTA]]) -> 35 | Y11: =IF(Tabla1[[#This Row],[ESTADO]]="ACTIVA","ACTIVA",IF(Tabla1[[#This Row],[ESTADO]]="CERRADA","CERRADA",IF(Tabla1[[#This Row],[ESTADO]]="TRASLADADA","CERRADA",IF(Tabla1[[#This Row],[ESTADO]]="DESMONTADA","CERRADA",IF(Tabla1[[#This Row],[ESTADO]]="SEGUIMIENTO","ACTIVA"))))) -> CERRADA | Z11: =+IF(Tabla1[[#This Row],[T. RESPUESTA]]<=1,"24 HORAS",IF(Tabla1[[#This Row],[T. RESPUESTA]]=2,"48 HORAS",IF(Tabla1[[#This Row],[T. RESPUESTA]]=3,"72 HORAS",IF(Tabla1[[#This Row],[T. RESPUESTA]]=4,"96 HORAS",IF(Tabla1[[#This Row],[T. RESPUESTA]]=5,"120 HORAS",IF(Tabla1[[#This Row],[T. RESPUESTA]]>=6,"6 DIAS O MAS","ERROR")))))) -> 6 DIAS O MAS | AA11: ATRIBUIBLE | AB11: =TEXT(Tabla1[[#This Row],[FECHA DEL INCIDENTE]],"MMM-DD") -> feb-24 | AC11: =VLOOKUP(G11,'Archivo data rimac reclamos'!B:C,2,0) -> #N/A | AD11: =VLOOKUP(Tabla1[[#This Row],[dn]],'Reporte de casos MAD'!H:W,16,0) -> #N/A | AE11: =VLOOKUP(Tabla1[[#This Row],[dn]],'HOJA 3 MEDICAMENTOS'!G:Q,11,0) -> #N/A | AF11: =VLOOKUP(Tabla1[[#This Row],[dn]],'base pendientes viva 1a'!C:Q,15,0) -> #N/A | AI11: =VLOOKUP(Tabla1[[#This Row],[MOTIVO]],clasificador!A:C,2,0) -> Solicitud | AJ11: =VLOOKUP(Tabla1[[#This Row],[MOTIVO]],clasificador!A:C,3,0) -> SOLICITUD
A12: =YEAR(Tabla1[[#This Row],[FECHA DEL INCIDENTE]])*100+MONTH(Tabla1[[#This Row],[FECHA DEL INCIDENTE]]) -> 202502 | B12: PERÚ | C12: VIVA1A CENTRO MEDICO | D12: RIMAC | E12: CRONICOS | F12: DNI | G12: 40528265 | H12: CARRAN SÁNCHEZ, CÉSAR ROGELIO | J12: 3606602 980686238 | N12: SOLICITUD | O12: ASEGURADOR | P12: RE: POTENCIALES AL PROGRAMA CUIDATE Y OTROS CRONICOS-SURA /RIESGO Estimada @gsiguenas@viva1a.com.pe Se requiere el reporte de contactibilidad y ingresos. Estimados @gsiguenas@viva1a.com.pe@Julio Marco Inocencio Pereyra Su gentil apoyo con el contacto de caracterización y de ingreso a programas crónicos usuarios identificados como potenciales por chequeo médico contratante Sura (68 usuarios) Se adjunta el listado en el formato de plantilla para su gestión Atentamente. | Q12: INGRESO A PROGRAMA | R12: CUIDATE | S12: ASMA | T12: 45712 | U12: ATENDIDO 8/04/2025 Antonio David Moncada Catalan MEDICA FAMILIAR - TELECONSULTA | V12: 45757 | W12: CERRADA | X12: =NETWORKDAYS(Tabla1[[#This Row],[FECHA DEL INCIDENTE]],Tabla1[[#This Row],[FECHA DE RESPUESTA]]) -> 34 | Y12: =IF(Tabla1[[#This Row],[ESTADO]]="ACTIVA","ACTIVA",IF(Tabla1[[#This Row],[ESTADO]]="CERRADA","CERRADA",IF(Tabla1[[#This Row],[ESTADO]]="TRASLADADA","CERRADA",IF(Tabla1[[#This Row],[ESTADO]]="DESMONTADA","CERRADA",IF(Tabla1[[#This Row],[ESTADO]]="SEGUIMIENTO","ACTIVA"))))) -> CERRADA | Z12: =+IF(Tabla1[[#This Row],[T. RESPUESTA]]<=1,"24 HORAS",IF(Tabla1[[#This Row],[T. RESPUESTA]]=2,"48 HORAS",IF(Tabla1[[#This Row],[T. RESPUESTA]]=3,"72 HORAS",IF(Tabla1[[#This Row],[T. RESPUESTA]]=4,"96 HORAS",IF(Tabla1[[#This Row],[T. RESPUESTA]]=5,"120 HORAS",IF(Tabla1[[#This Row],[T. RESPUESTA]]>=6,"6 DIAS O MAS","ERROR")))))) -> 6 DIAS O MAS | AA12: ATRIBUIBLE | AB12: =TEXT(Tabla1[[#This Row],[FECHA DEL INCIDENTE]],"MMM-DD") -> feb-24 | AC12: =VLOOKUP(G12,'Archivo data rimac reclamos'!B:C,2,0) -> #N/A | AD12: =VLOOKUP(Tabla1[[#This Row],[dn]],'Reporte de casos MAD'!H:W,16,0) -> #N/A | AE12: =VLOOKUP(Tabla1[[#This Row],[dn]],'HOJA 3 MEDICAMENTOS'!G:Q,11,0) -> #N/A | AF12: =VLOOKUP(Tabla1[[#This Row],[dn]],'base pendientes viva 1a'!C:Q,15,0) -> #N/A | AI12: =VLOOKUP(Tabla1[[#This Row],[MOTIVO]],clasificador!A:C,2,0) -> Solicitud | AJ12: =VLOOKUP(Tabla1[[#This Row],[MOTIVO]],clasificador!A:C,3,0) -> SOLICITUD
A13: =YEAR(Tabla1[[#This Row],[FECHA DEL INCIDENTE]])*100+MONTH(Tabla1[[#This Row],[FECHA DEL INCIDENTE]]) -> 202502 | B13: PERÚ | C13: VIVA1A CENTRO MEDICO | D13: RIMAC | E13: CRONICOS | F13: DNI | G13: 47619369 | H13: CARRAN SANCHEZ, CHRISTIAN ROGELIO | J13: 981427883 | N13: SOLICITUD | O13: ASEGURADOR | P13: RE: POTENCIALES AL PROGRAMA CUIDATE Y OTROS CRONICOS-SURA /RIESGO Estimada @gsiguenas@viva1a.com.pe Se requiere el reporte de contactibilidad y ingresos. Estimados @gsiguenas@viva1a.com.pe@Julio Marco Inocencio Pereyra Su gentil apoyo con el contacto de caracterización y de ingreso a programas crónicos usuarios identificados como potenciales por chequeo médico contratante Sura (68 usuarios) Se adjunta el listado en el formato de plantilla para su gestión Atentamente. | Q13: INGRESO A PROGRAMA | R13: CUIDATE | S13: ASMA | T13: 45712 | U13: NO ASISTIO A CITA 5/04/2025 Antonio David Moncada Catalan MEDICA FAMILIAR - TELECONSULTA | V13: 45754 | W13: CERRADA | X13: =NETWORKDAYS(Tabla1[[#This Row],[FECHA DEL INCIDENTE]],Tabla1[[#This Row],[FECHA DE RESPUESTA]]) -> 31 | Y13: =IF(Tabla1[[#This Row],[ESTADO]]="ACTIVA","ACTIVA",IF(Tabla1[[#This Row],[ESTADO]]="CERRADA","CERRADA",IF(Tabla1[[#This Row],[ESTADO]]="TRASLADADA","CERRADA",IF(Tabla1[[#This Row],[ESTADO]]="DESMONTADA","CERRADA",IF(Tabla1[[#This Row],[ESTADO]]="SEGUIMIENTO","ACTIVA"))))) -> CERRADA | Z13: =+IF(Tabla1[[#This Row],[T. RESPUESTA]]<=1,"24 HORAS",IF(Tabla1[[#This Row],[T. RESPUESTA]]=2,"48 HORAS",IF(Tabla1[[#This Row],[T. RESPUESTA]]=3,"72 HORAS",IF(Tabla1[[#This Row],[T. RESPUESTA]]=4,"96 HORAS",IF(Tabla1[[#This Row],[T. RESPUESTA]]=5,"120 HORAS",IF(Tabla1[[#This Row],[T. RESPUESTA]]>=6,"6 DIAS O MAS","ERROR")))))) -> 6 DIAS O MAS | AA13: ATRIBUIBLE | AB13: =TEXT(Tabla1[[#This Row],[FECHA DEL INCIDENTE]],"MMM-DD") -> feb-24 | AC13: =VLOOKUP(G13,'Archivo data rimac reclamos'!B:C,2,0) -> #N/A | AD13: =VLOOKUP(Tabla1[[#This Row],[dn]],'Reporte de casos MAD'!H:W,16,0) -> #N/A | AE13: =VLOOKUP(Tabla1[[#This Row],[dn]],'HOJA 3 MEDICAMENTOS'!G:Q,11,0) -> #N/A | AF13: =VLOOKUP(Tabla1[[#This Row],[dn]],'base pendientes viva 1a'!C:Q,15,0) -> #N/A | AI13: =VLOOKUP(Tabla1[[#This Row],[MOTIVO]],clasificador!A:C,2,0) -> Solicitud | AJ13: =VLOOKUP(Tabla1[[#This Row],[MOTIVO]],clasificador!A:C,3,0) -> SOLICITUD
A14: =YEAR(Tabla1[[#This Row],[FECHA DEL INCIDENTE]])*100+MONTH(Tabla1[[#This Row],[FECHA DEL INCIDENTE]]) -> 202502 | B14: PERÚ | C14: VIVA1A CENTRO MEDICO | D14: RIMAC | E14: CRONICOS | F14: DNI | G14: 71490247 | H14: CARRANZA AGUIRRE, FIORELLA | J14: 936647435 | N14: SOLICITUD | O14: ASEGURADOR | P14: RE: POTENCIALES AL PROGRAMA CUIDATE Y OTROS CRONICOS-SURA /RIESGO Estimada @gsiguenas@viva1a.com.pe Se requiere el reporte de contactibilidad y ingresos. Estimados @gsiguenas@viva1a.com.pe@Julio Marco Inocencio Pereyra Su gentil apoyo con el contacto de caracterización y de ingreso a programas crónicos usuarios identificados como potenciales por chequeo médico contratante Sura (68 usuarios) Se adjunta el listado en el formato de plantilla para su gestión Atentamente. | Q14: INGRESO A PROGRAMA | R14: CUIDATE | S14: ASMA | T14: 45712 | U14: ATENDIDO 11/04/2025 Antonio David Moncada Catalan MEDICA FAMILIAR - TELECONSULTA | V14: 45754 | W14: CERRADA | X14: =NETWORKDAYS(Tabla1[[#This Row],[FECHA DEL INCIDENTE]],Tabla1[[#This Row],[FECHA DE RESPUESTA]]) -> 31 | Y14: =IF(Tabla1[[#This Row],[ESTADO]]="ACTIVA","ACTIVA",IF(Tabla1[[#This Row],[ESTADO]]="CERRADA","CERRADA",IF(Tabla1[[#This Row],[ESTADO]]="TRASLADADA","CERRADA",IF(Tabla1[[#This Row],[ESTADO]]="DESMONTADA","CERRADA",IF(Tabla1[[#This Row],[ESTADO]]="SEGUIMIENTO","ACTIVA"))))) -> CERRADA | Z14: =+IF(Tabla1[[#This Row],[T. RESPUESTA]]<=1,"24 HORAS",IF(Tabla1[[#This Row],[T. RESPUESTA]]=2,"48 HORAS",IF(Tabla1[[#This Row],[T. RESPUESTA]]=3,"72 HORAS",IF(Tabla1[[#This Row],[T. RESPUESTA]]=4,"96 HORAS",IF(Tabla1[[#This Row],[T. RESPUESTA]]=5,"120 HORAS",IF(Tabla1[[#This Row],[T. RESPUESTA]]>=6,"6 DIAS O MAS","ERROR")))))) -> 6 DIAS O MAS | AA14: ATRIBUIBLE | AB14: =TEXT(Tabla1[[#This Row],[FECHA DEL INCIDENTE]],"MMM-DD") -> feb-24 | AC14: =VLOOKUP(G14,'Archivo data rimac reclamos'!B:C,2,0) -> #N/A | AD14: =VLOOKUP(Tabla1[[#This Row],[dn]],'Reporte de casos MAD'!H:W,16,0) -> #N/A | AE14: =VLOOKUP(Tabla1[[#This Row],[dn]],'HOJA 3 MEDICAMENTOS'!G:Q,11,0) -> #N/A | AF14: =VLOOKUP(Tabla1[[#This Row],[dn]],'base pendientes viva 1a'!C:Q,15,0) -> #N/A | AI14: =VLOOKUP(Tabla1[[#This Row],[MOTIVO]],clasificador!A:C,2,0) -> Solicitud | AJ14: =VLOOKUP(Tabla1[[#This Row],[MOTIVO]],clasificador!A:C,3,0) -> SOLICITUD
A15: =YEAR(Tabla1[[#This Row],[FECHA DEL INCIDENTE]])*100+MONTH(Tabla1[[#This Row],[FECHA DEL INCIDENTE]]) -> 202502 | B15: PERÚ | C15: VIVA1A CENTRO MEDICO | D15: RIMAC | E15: CRONICOS | F15: DNI | G15: 6672892 | H15: CASTAÑEDA NEGRON, KARLA PATRICIA LILIANA | J15: 955888700 () 955888700 | N15: SOLICITUD | O15: ASEGURADOR | P15: RE: POTENCIALES AL PROGRAMA CUIDATE Y OTROS CRONICOS-SURA /RIESGO Estimada @gsiguenas@viva1a.com.pe Se requiere el reporte de contactibilidad y ingresos. Estimados @gsiguenas@viva1a.com.pe@Julio Marco Inocencio Pereyra Su gentil apoyo con el contacto de caracterización y de ingreso a programas crónicos usuarios identificados como potenciales por chequeo médico contratante Sura (68 usuarios) Se adjunta el listado en el formato de plantilla para su gestión Atentamente. | Q15: INGRESO A PROGRAMA | R15: CUIDATE | S15: DISLIPIDEMIA/DIABETES | T15: 45712 | U15: NO ASISTIO A CITA 9/04/2025 Nilda Noriko Kawamura MurilloENDOCRINOLOGÍA - TELECONSULTA | V15: 45754 | W15: CERRADA | X15: =NETWORKDAYS(Tabla1[[#This Row],[FECHA DEL INCIDENTE]],Tabla1[[#This Row],[FECHA DE RESPUESTA]]) -> 31 | Y15: =IF(Tabla1[[#This Row],[ESTADO]]="ACTIVA","ACTIVA",IF(Tabla1[[#This Row],[ESTADO]]="CERRADA","CERRADA",IF(Tabla1[[#This Row],[ESTADO]]="TRASLADADA","CERRADA",IF(Tabla1[[#This Row],[ESTADO]]="DESMONTADA","CERRADA",IF(Tabla1[[#This Row],[ESTADO]]="SEGUIMIENTO","ACTIVA"))))) -> CERRADA | Z15: =+IF(Tabla1[[#This Row],[T. RESPUESTA]]<=1,"24 HORAS",IF(Tabla1[[#This Row],[T. RESPUESTA]]=2,"48 HORAS",IF(Tabla1[[#This Row],[T. RESPUESTA]]=3,"72 HORAS",IF(Tabla1[[#This Row],[T. RESPUESTA]]=4,"96 HORAS",IF(Tabla1[[#This Row],[T. RESPUESTA]]=5,"120 HORAS",IF(Tabla1[[#This Row],[T. RESPUESTA]]>=6,"6 DIAS O MAS","ERROR")))))) -> 6 DIAS O MAS | AA15: ATRIBUIBLE | AB15: =TEXT(Tabla1[[#This Row],[FECHA DEL INCIDENTE]],"MMM-DD") -> feb-24 | AC15: =VLOOKUP(G15,'Archivo data rimac reclamos'!B:C,2,0) -> #N/A | AD15: =VLOOKUP(Tabla1[[#This Row],[dn]],'Reporte de casos MAD'!H:W,16,0) -> #N/A | AE15: =VLOOKUP(Tabla1[[#This Row],[dn]],'HOJA 3 MEDICAMENTOS'!G:Q,11,0) -> #N/A | AF15: =VLOOKUP(Tabla1[[#This Row],[dn]],'base pendientes viva 1a'!C:Q,15,0) -> #N/A | AI15: =VLOOKUP(Tabla1[[#This Row],[MOTIVO]],clasificador!A:C,2,0) -> Solicitud | AJ15: =VLOOKUP(Tabla1[[#This Row],[MOTIVO]],clasificador!A:C,3,0) -> SOLICITUD
